Workbook

Sheet MMPS
A1: versionid | B1: versionname | C1: tablename | D1: sequence | E1: elementname | F1: turnaroundind | G1: sampledata | H1: exportind | I1: elementid | J1: parentelementid | K1: parentelementid | L1: relationshiptype | M1: elementtype | N1: fieldname | O1: columnname | P1: languagecode | Q1: ddetype | R1: countrydesc | S1: countrycode | T1: regioncode | U1: elementlength | V1: elementprecision | W1: collectionunits | X1: guidelines | Y1: csfieldname | Z1: colusage | AA1: ascentnullableind | AB1: nullableind | AC1: note | AD1: fieldname | AE1: elementname | AF1: elementdesc | AG1: guidelines | AH1: sampledata | AI1: excelformula | AJ1: expression | AK1: loadrule
A2: A24261921654 | B2: 2025 MMPS Template | C2: SUBMISSIONINCUMBENT | D2: 1 | E2: Country Code | F2: Y | G2: ~NA:USA~DEFAULT:GBR~APAC:JPN~LATAM:BRA~CHINA:CHN~EDUCATION:MYS | H2: Y | I2: 14 | J2: NULL | K2: NULL | L2: NULL | M2: CHAR | N2: COUNTRYCODE | O2: COUNTRYCODE | P2: USE | Q2: L | R2: United States | S2: USA | T2: USA | U2: 5 | V2: 0 | W2: W | X2: Refer to the Country Codes tab. | Y2: NULL | Z2: M | AA2: N | AB2: N | AC2: INT:~CORE~CYCAR~ | AD2: COUNTRYCODE | AE2: Country Code | AF2: The country code of the primary office to which they are assigned. | AG2: Refer to the Country Codes tab. | AH2: ~NA:USA~DEFAULT:GBR~APAC:JPN~LATAM:BRA~CHINA:CHN~EDUCATION:MYS | AI2: NULL | AK2: If(:COUNTRYCODE="xx",null,Trim(Upper(:COUNTRYCODE)))
A3: A24261921654 | B3: 2025 MMPS Template | C3: SUBMISSIONUNIT | D3: 1 | E3: New Hire [Calculated] | F3: N | G3: NULL | H3: N | I3: NULL | J3: NULL | K3: NULL | L3: NULL | M3: BOOL | N3: SCOPE_UNIT | O3: NULL | P3: USE | Q3: C | R3: United States | S3: USA | T3: USA | U3: 12 | V3: 0 | W3: W | X3: NULL | Y3: NULL | Z3: NULL | AA3: Y | AB3: Y | AC3: ~XXX~ | AD3: SCOPE_UNIT | AE3: New Hire [Calculated] | AF3: The incumbent was hired on or after 1 January of the previous year. | AG3: NULL | AH3: NULL | AI3: NULL | AJ3: if(isnull( :FD_DOH_DAT),null,if(Number(FormatDate(:FD_DOH_DAT,"YYYY")) >= 2021, "Y", "N")) | AK3: NULL
A4: A24261921654 | B4: 2025 MMPS Template | C4: SUBMISSIONCONTACT | D4: 1 | E4: Report Recipient Name | F4: N | G4: Ms. Jan Doe | H4: Y | I4: 990 | J4: NULL | K4: NULL | L4: NULL | M4: CHAR | N4: CONTACT_NAME | O4: DDE034 | P4: USE | Q4: L | R4: United States | S4: USA | T4: USA | U4: 250 | V4: 0 | W4: W | Y4: NULL | Z4: M | AA4: Y | AB4: Y | AC4: ~CORE_NA~AERO_NA~ | AD4: CONTACT_NAME | AE4: Report Recipient Name | AF4: Report Recipient Name | AH4: Ms. Jan Doe | AI4: NULL | AK4: NULL
A5: A24261921654 | B5: 2025 MMPS Template | C5: SUBMISSIONGRANT | D5: 1 | E5: Case Number | F5: N | G5: NULL | H5: N | I5: 22 | J5: NULL | K5: NULL | L5: NULL | M5: CHAR | N5: CASEID | O5: CASEID | P5: USE | Q5: L | R5: United States | S5: USA | T5: USA | U5: 7 | V5: 0 | W5: W | X5: NULL | Y5: NULL | Z5: M | AA5: N | AB5: N | AC5: ADV,DSW:~CORE~;HID:~MFG_LATAM~CYCAR~ | AD5: CASEID | AE5: Case Number | AF5: Seven-digit case number to uniquely identify each incumbent. | AG5: NULL | AH5: NULL | AI5: NULL | AK5: If(:CASEID="XXXX",null,LPad(:CASEID,6,"0"))
A6: A24261921654 | B6: 2025 MMPS Template | C6: SUBMISSIONCOMPANY | D6: 1 | E6: Participating Entity Name | F6: N | G6: ~CSR:ABC Subsidiary~DEFAULT:Your Company Name~ | H6: Y | I6: 566 | J6: NULL | K6: NULL | L6: NULL | M6: CHAR | N6: COMPANY_NAME | O6: DDE038 | P6: USE | Q6: L | R6: United States | S6: USA | T6: USA | U6: 255 | V6: 0 | W6: W | X6: NULL | Y6: NULL | Z6: M | AA6: Y | AB6: Y | AC6: ~CORE~CYCAR~ | AD6: COMPANY_NAME | AE6: Participating Entity Name | AF6: The name of your organization. | AG6: NULL | AH6: ~CSR:ABC Subsidiary~DEFAULT:Your Company Name~ | AI6: NULL | AK6: NULL
A7: A24261921654 | B7: 2025 MMPS Template | C7: SUBMISSIONGRANT | D7: 2 | E7: Long-Term Incentive Plan Type | F7: N | G7: PP | H7: Y | I7: 83 | J7: NULL | K7: NULL | L7: NULL | M7: PICK | N7: PLANTYPE | O7: PLANTYPE | P7: USE | Q7: L | R7: United States | S7: USA | T7: USA | U7: 5 | V7: 0 | W7: W | X7: PP-Performance Plan Awards: Performance Plan Awards are contingent grants of cash or stock that are earned in whole or in part according to the degree of achievement of performance goals over a defined period (usually three years). In EMEA, some grants can be contingent upon bonus deferral (deferred bonus matching plans) or the purchase of company stock (co-investment plans). RS-Restricted Stock/Stock Units: Restricted Stock/Stock Units are grants of stock or stock units at no or nominal cost. The restrictions and risk of forfeiture lapse with continued employment over a period of years. If vesting also includes a performance condition, such condition is considered to be nominal with a high likelihood of being attained. Dividends or dividend equivalents may be paid or accrued during the restricted period. SO-Stock Options/SARs: Stock Options are rights to purchase a fixed number of shares of a company's stock, at a stated price for a specified period of time. Stock Appreciation Rights (SARs) are rights to receive payment equal in value to the appreciation on a share of stock between the date on which the SAR was granted and the date on which the employee exercises his/her appreciation rights. | Y7: NULL | Z7: M | AA7: Y | AB7: Y | AC7: INT:~CORE~ | AD7: PLANTYPE | AE7: Long-Term Incentive Plan Type | AF7: Type of long-term grant data being reported. | AG7: PP-Performance Plan Awards: Performance Plan Awards are contingent grants of cash or stock that are earned in whole or in part according to the degree of achievement of performance goals over a defined period (usually three years). In EMEA, some grants can be contingent upon bonus deferral (deferred bonus matching plans) or the purchase of company stock (co-investment plans). RS-Restricted Stock/Stock Units: Restricted Stock/Stock Units are grants of stock or stock units at no or nominal cost. The restrictions and risk of forfeiture lapse with continued employment over a period of years. If vesting also includes a performance condition, such condition is considered to be nominal with a high likelihood of being attained. Dividends or dividend equivalents may be paid or accrued during the restricted period. SO-Stock Options/SARs: Stock Options are rights to purchase a fixed number of shares of a company's stock, at a stated price for a specified period of time. Stock Appreciation Rights (SARs) are rights to receive payment equal in value to the appreciation on a share of stock between the date on which the SAR was granted and the date on which the employee exercises his/her appreciation rights. | AH7: PP | AI7: NULL | AK7: UPPER(TRIM(:PLANTYPE))
A8: A24261921654 | B8: 2025 MMPS Template | C8: SUBMISSIONCOMPANY | D8: 2 | E8: Participating Entity Country | F8: Y | G8: ~NA:USA [United States]~DEFAULT:GBR [United Kingdom]~APAC:JPN [Japan]~LATAM:BRA [Brazil]~CHINA:CHN [China]~EDUCATION:MYS [Malaysia]~ | H8: Y | I8: 35000 | J8: NULL | K8: NULL | L8: NULL | M8: PICK | N8: ISO3 | O8: DDE207 | P8: USE | Q8: L | R8: United States | S8: USA | T8: USA | U8: 5 | V8: 0 | W8: W | X8: Refer to the Country Codes tab. | Y8: NULL | Z8: M | AA8: N | AB8: Y | AC8: DSW:~CORE~CYCAR~ | AD8: ISO3 | AE8: Participating Entity Country | AF8: The country where the participating entity is based/headquartered. | AG8: Refer to the Country Codes tab. | AH8: ~NA:USA [United States]~DEFAULT:GBR [United Kingdom]~APAC:JPN [Japan]~LATAM:BRA [Brazil]~CHINA:CHN [China]~EDUCATION:MYS [Malaysia]~ | AI8: NULL | AK8: NULL
A9: A24261921654 | B9: 2025 MMPS Template | C9: SUBMISSIONINCUMBENT | D9: 2 | E9: Country Code (PHRA) | F9: Y | G9: USA | H9: Y | I9: 78097 | J9: NULL | K9: NULL | L9: NULL | M9: PICK | N9: COUNTRY_PHE | O9: DDE641 | P9: USE | Q9: L | R9: United States | S9: USA | T9: USA | U9: 5 | V9: 0 | W9: W | X9: Refer to the Country Codes tab. NOTE: As agreed by the PHRA, all top 30 highest paid EX level incumbents should be included regardless of country or pay currency. | Y9: NULL | Z9: S | AA9: N | AB9: Y | AC9: ~PHRA_NA~ | AD9: COUNTRY_PHE | AE9: Country Code (PHRA) | AF9: For PHRA, the country code of the primary office to which they are assigned. | AG9: Refer to the Country Codes tab. NOTE: As agreed by the PHRA, all top 30 highest paid EX level incumbents should be included regardless of country or pay currency. | AH9: USA | AI9: NULL | AK9: NULL
A10: A24261921654 | B10: 2025 MMPS Template | C10: SUBMISSIONUNIT | D10: 2 | E10: Unit Number | F10: Y | G10: 1 | H10: N | I10: 10 | J10: NULL | K10: NULL | L10: NULL | M10: CHAR | N10: UNITNUM | O10: UNITNUM | P10: USE | Q10: L | R10: United States | S10: USA | T10: USA | U10: 12 | V10: 0 | W10: W | X10: Enter a unique three-digit code (e.g., 001, 002) to identify each unit. Unit numbers will be assigned to the corresponding incumbent in these units in the Incumbent Data worksheet. | Y10: NULL | Z10: M | AA10: N | AB10: N | AC10: ~CORE~AERO_NA~SSO~RCE~AGRO_ZAF~MDSUK~YOUNGGRAD~RENEWABLE~RENEWCLUB_FRA~AERO_EMEA~AERO_BRA~HC_GCC~HC_APAC~HIGHER_EDU~CMPIF_CHN~EDU_APAC~UPSTREAM_MYS~LEGAL_FEE_EARNERS~CL_PS_SUPPORTSTAFF_INTL~CL_HRG~CYCAR~ | AD10: UNITNUM | AE10: Unit Number | AF10: The unit number for the incumbent's unit. | AG10: Enter a unique three-digit code (e.g., 001, 002) to identify each unit. Unit numbers will be assigned to the corresponding incumbent in these units in the Incumbent Data worksheet. | AH10: 1 | AI10: NULL | AK10: NULL
A11: A24261921654 | B11: 2025 MMPS Template | C11: SUBMISSIONCONTACT | D11: 2 | E11: Report Recipient Title | F11: N | G11: Compensation Analyst | H11: Y | I11: 991 | J11: NULL | K11: NULL | L11: NULL | M11: CHAR | N11: CONTACT_TITLE | O11: DDE035 | P11: USE | Q11: L | R11: United States | S11: USA | T11: USA | U11: 250 | V11: 0 | W11: W | Y11: NULL | Z11: M | AA11: Y | AB11: Y | AC11: ~CORE_NA~AERO_NA~ | AD11: CONTACT_TITLE | AE11: Report Recipient Title | AF11: Report Recipient Title | AH11: Compensation Analyst | AI11: NULL | AK11: NULL
A12: A24261921654 | B12: 2025 MMPS Template | C12: SUBMISSIONUNIT | D12: 3 | E12: 2020 Radio Rank | F12: Y | G12: NULL | H12: Y | I12: 1081 | J12: NULL | K12: NULL | L12: NULL | M12: PICK | N12: NEXT_YEAR_RADIO_RANK | O12: DDE028 | P12: USE | Q12: L | R12: United States | S12: USA | T12: USA | U12: 5 | V12: 0 | W12: W | X12: NULL | Y12: NULL | Z12: S | AA12: Y | AB12: Y | AC12: ~XXX~ | AD12: NEXT_YEAR_RADIO_RANK | AE12: 2020 Radio Rank | AF12: The appropriate radio market rank for each station. | AG12: NULL | AH12: NULL | AI12: NULL | AJ12: NULL | AK12: NULL
A13: A24261921654 | B13: 2025 MMPS Template | C13: SUBMISSIONCONTACT | D13: 3 | E13: Report Recipient Address 1 | F13: N | G13: 100 Park Ave | H13: Y | I13: 992 | J13: NULL | K13: NULL | L13: NULL | M13: CHAR | N13: CONTACT_ADDRESS_1 | O13: DDE036 | P13: USE | Q13: L | R13: United States | S13: USA | T13: USA | U13: 250 | V13: 0 | W13: W | Y13: NULL | Z13: M | AA13: Y | AB13: Y | AC13: ~CORE_NA~AERO_NA~ | AD13: CONTACT_ADDRESS_1 | AE13: Report Recipient Address 1 | AF13: Report Recipient Address 1 | AH13: 100 Park Ave | AI13: NULL | AK13: NULL
A14: A24261921654 | B14: 2025 MMPS Template | C14: SUBMISSIONCOMPANY | D14: 3 | E14: Participating Entity Structure | F14: Y | G14: ~CSR:3~DEFAULT:1 [Public Parent]~ | H14: Y | I14: 3162 | J14: NULL | K14: NULL | L14: NULL | M14: PICK | N14: CRP_STRUCTURE | O14: DDE127 | P14: USE | Q14: L | R14: United States | S14: USA | T14: USA | U14: 5 | V14: 0 | W14: W | X14: 1-Public Parent 2-Private Parent 3-Wholly Owned Subsidiary 4-Publicly Traded Subsidiary 5-Not-for-Profit 6-Government Agency 7-Joint Venture 8-Mutual Company | Y14: NULL | Z14: M | AA14: Y | AB14: Y | AC14: ADV:~CORE_EXEC~CORE_NONEXEC_NA;INT:~CORE_NONEXEC_EMEA~CORE_NONEXEC_LATAM~CORE_NONEXEC_APAC~CYCAR~ | AD14: CRP_STRUCTURE | AE14: Participating Entity Structure | AF14: Corporate structure of the participating entity. | AG14: 1-Public Parent 2-Private Parent 3-Wholly Owned Subsidiary 4-Publicly Traded Subsidiary 5-Not-for-Profit 6-Government Agency 7-Joint Venture 8-Mutual Company | AH14: ~CSR:3~DEFAULT:1 [Public Parent]~ | AI14: NULL | AK14: NULL
A15: A24261921654 | B15: 2025 MMPS Template | C15: SUBMISSIONINCUMBENT | D15: 3 | E15: Case Number | F15: Y | G15: 1 | H15: Y | I15: 12 | J15: NULL | K15: NULL | L15: NULL | M15: CHAR | N15: CASEID | O15: CASEID | P15: USE | Q15: L | R15: United States | S15: USA | T15: USA | U15: 7 | V15: 0 | W15: W | X15: Number the cases starting with 0000001. | Y15: NULL | Z15: M | AA15: N | AB15: N | AC15: ADV,DSW:~CORE~;HID:~MFG_LATAM~ | AD15: CASEID | AE15: Case Number | AF15: Seven-digit case number to uniquely identify each incumbent. | AG15: Number the cases starting with 0000001. | AH15: 1 | AI15: NULL | AK15: If(:CASEID="XXXX",null,LPad(:CASEID,6,"0"))
A16: A24261921654 | B16: 2025 MMPS Template | C16: SUBMISSIONGRANT | D16: 3 | E16: Long-Term Incentive Plan Number | F16: N | G16: PP01 | H16: Y | I16: 23 | J16: NULL | K16: NULL | L16: NULL | M16: CHAR | N16: PLANCODE | O16: PLANCODE | P16: USE | Q16: L | R16: United States | S16: USA | T16: USA | U16: 12 | V16: 0 | W16: W | X16: If under the same plan different incumbents have different vesting arrangements, report each plan separately. For example, if a performance cash plan has a TSR performance condition applicable to board member and an EPS performance condition applicable to all other incumbents, code each as a separate plan. | Y16: NULL | Z16: M | AA16: Y | AB16: Y | AC16: DSW,INT:~CORE~;HID:~MFG_LATAM~CYCAR~ | AD16: PLANCODE | AE16: Long-Term Incentive Plan Number | AF16: The plan number is located on each plan type worksheet on the data submission spreadsheet and is required for each grant. The Long-Term Plan Number (e.g., PP01) ties the shares granted with the plan data. | AG16: If under the same plan different incumbents have different vesting arrangements, report each plan separately. For example, if a performance cash plan has a TSR performance condition applicable to board member and an EPS performance condition applicable to all other incumbents, code each as a separate plan. | AH16: PP01 | AI16: NULL | AK16: TRIM(UPPER(:PLANCODE))
A17: A24261921654 | B17: 2025 MMPS Template | C17: SUBMISSIONCONTACT | D17: 4 | E17: Report Recipient Address 2 | F17: N | G17: 9th Floor | H17: Y | I17: 993 | J17: NULL | K17: NULL | L17: NULL | M17: CHAR | N17: CONTACT_ADDRESS_2 | O17: DDE037 | P17: USE | Q17: L | R17: United States | S17: USA | T17: USA | U17: 250 | V17: 0 | W17: W | Y17: NULL | Z17: M | AA17: Y | AB17: Y | AC17: ~CORE_NA~AERO_NA~ | AD17: CONTACT_ADDRESS_2 | AE17: Report Recipient Address 2 | AF17: Report Recipient Address 2 | AH17: 9th Floor | AI17: NULL | AK17: NULL
A18: A24261921654 | B18: 2025 MMPS Template | C18: SUBMISSIONCOMPANY | D18: 4 | E18: Type of Ownership | F18: N | G18: NULL | H18: Y | I18: 1291 | J18: NULL | K18: NULL | L18: NULL | M18: PICK | N18: TYPE_OWNERSHIP | O18: DDE110 | P18: USE | Q18: L | R18: United States | S18: USA | T18: USA | U18: 5 | V18: 0 | W18: W | X18: NULL | Y18: NULL | Z18: S | AA18: NULL | AB18: Y | AC18: ~XXX~ | AD18: TYPE_OWNERSHIP | AE18: Type of Ownership | AF18: Indicate if your company ownership is stock or mutual. | AG18: NULL | AH18: NULL | AI18: NULL | AJ18: NULL | AK18: NULL
A19: A24261921654 | B19: 2025 MMPS Template | C19: SUBMISSIONGRANT | D19: 4 | E19: Grant Date | F19: N | G19: ~NA:4/15/2024~APAC,EMEA,LATAM:3/1/2023~ | H19: Y | I19: 196 | J19: NULL | K19: NULL | L19: NULL | M19: DATE | N19: GRANT_DATE | O19: DDE001 | P19: USE | Q19: L | R19: United States | S19: USA | T19: USA | U19: 8 | V19: 0 | W19: W | X19: Provide date of grants in the last 12 months. Enter the date in your normal date format (DD/MM/YY or MM/DD/YY depending on user default). For special grants provided in lieu of annual grants and for multi-year or mega grants, please enter your most recent grant which could be more than 12 months ago. | Y19: NULL | Z19: M | AA19: Y | AB19: Y | AC19: DSW,INT:~CORE~AERO_NA~SSO~RCE~AGRO_ZAF~MDSUK~RENEWABLE~RENEWCLUB_FRA~AERO_EMEA~AERO_BRA~HC_GCC~HC_APAC~HIGHER_EDU~CMPIF_CHN~EDU_APAC~UPSTREAM_MYS~DRILL_GLOBAL~DRILL_NAT~CL_PS_SUPPORTSTAFF_INTL~CL_HRG~;HID:~MFG_LATAM~CYCAR~ | AD19: GRANT_DATE | AE19: Grant Date | AF19: Date the grant was made. | AG19: Provide date of grants in the last 12 months. Enter the date in your normal date format (DD/MM/YY or MM/DD/YY depending on user default). For special grants provided in lieu of annual grants and for multi-year or mega grants, please enter your most recent grant which could be more than 12 months ago. | AH19: ~NA:4/15/2024~APAC,EMEA,LATAM:3/1/2023~ | AI19: NULL | AK19: NULL
A20: A24261921654 | B20: 2025 MMPS Template | C20: SUBMISSIONINCUMBENT | D20: 4 | E20: Reports to Case Number | F20: Y | G20: 1 | H20: Y | I20: 20 | J20: NULL | K20: NULL | L20: NULL | M20: CHAR | N20: SUPERVISORCASEID | O20: SUPERVISORCASEID | P20: USE | Q20: L | R20: United States | S20: USA | T20: USA | U20: 7 | V20: 0 | W20: W | X20: This should only be provided for jobs matched to the EX career band. | Y20: NULL | Z20: M | AA20: Y | AB20: Y | AC20: ADV:~CORE_EXEC~CORE_EXEC_NA~MDSUK~AERO_EMEA~AERO_BRA~CL_HRG~;DSW,INT:~CORE_NONEXEC~RENEWABLE~HIGHER_EDU~ | AD20: SUPERVISORCASEID | AE20: Reports to Case Number | AF20: Seven-digit case number of the executive to whom the incumbent reports. If that executive is not matched to this survey, leave this field blank. | AG20: This should only be provided for jobs matched to the EX career band. | AH20: 1 | AI20: NULL | AK20: If(IsNull(:SUPERVISORCASEID),Null,LPad(:SUPERVISORCASEID,6,"0"))
A21: A24261921654 | B21: 2025 MMPS Template | C21: SUBMISSIONUNIT | D21: 4 | E21: Business Unit Name | F21: Y | G21: ~CSR:Widget Division~HCNA:XYZ Corp~DEFAULT:EXAMPLE LOB~ | H21: Y | I21: 408 | J21: NULL | K21: NULL | L21: NULL | M21: CHAR | N21: L_O_B | O21: DDE010 | P21: USE | Q21: L | R21: United States | S21: USA | T21: USA | U21: 250 | V21: 0 | W21: W | X21: If the parent organization employees are included in the data submission, one of the units should be named "parent" or "corporate" for reporting incumbents with organizationwide responsibility. | Y21: NULL | Z21: M | AA21: Y | AB21: Y | AC21: ~XXX~ | AD21: L_O_B | AE21: Business Unit Name | AF21: Name of the unit for which data is reported. | AG21: If the parent organization employees are included in the data submission, one of the units should be named "parent" or "corporate" for reporting incumbents with organizationwide responsibility. | AH21: ~CSR:Widget Division~HCNA:XYZ Corp~DEFAULT:EXAMPLE LOB~ | AI21: NULL | AJ21: NULL | AK21: NULL
A22: A24261921654 | B22: 2025 MMPS Template | C22: SUBMISSIONUNIT | D22: 5 | E22: Postal/ZIP Code | F22: Y | G22: NULL | H22: Y | I22: 1074 | J22: NULL | K22: NULL | L22: NULL | M22: CHAR | N22: POSTZIPCODE | O22: DDE021 | P22: USE | Q22: L | R22: United States | S22: USA | T22: USA | U22: 12 | V22: 0 | W22: W | X22: NULL | Y22: NULL | Z22: S | AA22: Y | AB22: Y | AC22: ~XXX~ | AD22: POSTZIPCODE | AE22: Postal/ZIP Code | AF22: The Postal/ZIP code for the business unit being reported. | AG22: NULL | AH22: NULL | AI22: NULL | AJ22: NULL | AK22: NULL
A23: A24261921654 | B23: 2025 MMPS Template | C23: SUBMISSIONINCUMBENT | D23: 5 | E23: Reports to Title | F23: N | G23: NULL | H23: Y | I23: 5523 | J23: NULL | K23: NULL | L23: NULL | M23: CHAR | N23: RPT2TITLE | O23: DDE212 | P23: USE | Q23: L | R23: United States | S23: USA | T23: USA | U23: 255 | V23: 0 | W23: W | X23: NULL | Y23: NULL | Z23: M | AA23: Y | AB23: Y | AC23: ~XXX~ | AD23: RPT2TITLE | AE23: Reports to Title | AF23: 5523 | AG23: NULL | AH23: NULL | AI23: NULL | AJ23: NULL | AK23: NULL
A24: A24261921654 | B24: 2025 MMPS Template | C24: SUBMISSIONCONTACT | D24: 5 | E24: Report Recipient City | F24: N | G24: New York | H24: Y | I24: 994 | J24: NULL | K24: NULL | L24: NULL | M24: CHAR | N24: CONTACT_CITY | O24: DDE038 | P24: USE | Q24: L | R24: United States | S24: USA | T24: USA | U24: 250 | V24: 0 | W24: W | Y24: NULL | Z24: M | AA24: Y | AB24: Y | AC24: ~CORE_NA~AERO_NA~ | AD24: CONTACT_CITY | AE24: Report Recipient City | AF24: Report Recipient City | AH24: New York | AI24: NULL | AK24: NULL
A25: A24261921654 | B25: 2025 MMPS Template | C25: SUBMISSIONCOMPANY | D25: 5 | E25: Organization Classification | F25: Y | G25: 1 | H25: Y | I25: 34999 | J25: NULL | K25: NULL | L25: NULL | M25: PICK | N25: ORG_TYPE | O25: DDE206 | P25: USE | Q25: L | R25: United States | S25: USA | T25: USA | U25: 5 | V25: 0 | W25: W | X25: 1. Hospital System/Network 2. Non Hospital Organization 3. Independent Hospital/Facility 4. Subsidiary 5. Children's Hospital/Facility | Y25: NULL | Z25: M | AA25: Y | AB25: Y | AC25: ADV:~HC~ | AD25: ORG_TYPE | AE25: Organization Classification | AF25: Select the Organization Classification that best describes your organization. | AG25: 1. Hospital System/Network 2. Non Hospital Organization 3. Independent Hospital/Facility 4. Subsidiary 5. Children's Hospital/Facility | AH25: 1 | AI25: NULL | AK25: NULL
A26: A24261921654 | B26: 2025 MMPS Template | C26: SUBMISSIONGRANT | D26: 5 | E26: Grant Price Currency | F26: N | G26: ~ | H26: Y | I26: 49 | J26: 48 | K26: 48 | L26: C | M26: CHAR | N26: GRANTPRICECURR | O26: GRANTPRICECURR | P26: USE | Q26: L | R26: United States | S26: USA | T26: USA | U26: 15 | V26: 0 | W26: W | X26: Enter the currency for the grant price reported. For example, enter USD for U.S. Dollars, CAD for Canadian Dollars, EUR for Euros, CHF for Swiss Francs and GBP for Pounds Sterling. For performance cash plans this is the currency in which the cash award is expressed. | Y26: NULL | Z26: M | AA26: Y | AB26: Y | AC26: ~CORE~AERO_NA~SSO~RCE~AGRO_ZAF~MDSUK~RENEWABLE~RENEWCLUB_FRA~AERO_EMEA~AERO_BRA~HC_GCC~HC_APAC~HIGHER_EDU~CMPIF_CHN~EDU_APAC~UPSTREAM_MYS~DRILL_GLOBAL~DRILL_NAT~CL_PS_SUPPORTSTAFF_INTL~CL_HRG~;HID:~MFG_LATAM~ | AD26: GRANTPRICECURR | AE26: Grant Price Currency | AF26: The currency code for the grant. | AG26: Enter the currency for the grant price reported. For example, enter USD for U.S. Dollars, CAD for Canadian Dollars, EUR for Euros, CHF for Swiss Francs and GBP for Pounds Sterling. For performance cash plans this is the currency in which the cash award is expressed. | AH26: ~ | AI26: NULL | AK26: Trim(Upper(:GRANTPRICECURR))
A27: A24261921654 | B27: 2025 MMPS Template | C27: SUBMISSIONCOMPANY | D27: 6 | E27: Home Country Executives | F27: Y | G27: 75 | H27: Y | I27: 3165 | J27: NULL | K27: NULL | L27: NULL | M27: NUM | N27: HOME_EXECS | O27: DDE130 | P27: USE | Q27: L | R27: United States | S27: USA | T27: USA | U27: 8 | V27: 0 | W27: W | X27: NULL | Y27: NULL | Z27: M | AA27: Y | AB27: Y | AC27: ~XXX~ | AD27: HOME_EXECS | AE27: Home Country Executives | AF27: The total number of employees designated as executives in the home country. | AG27: NULL | AH27: 75 | AI27: NULL | AK27: NULL
A28: A24261921654 | B28: 2025 MMPS Template | C28: SUBMISSIONCONTACT | D28: 6 | E28: Report Recipient State/Province | F28: N | G28: NY | H28: Y | I28: 995 | J28: NULL | K28: NULL | L28: NULL | M28: CHAR | N28: CONTACT_STATE | O28: DDE039 | P28: USE | Q28: L | R28: United States | S28: USA | T28: USA | U28: 250 | V28: 0 | W28: W | Y28: NULL | Z28: M | AA28: Y | AB28: Y | AC28: ~CORE_NA~AERO_NA~ | AD28: CONTACT_STATE | AE28: Report Recipient State/Province | AF28: Report Recipient State/Province | AH28: NY | AI28: NULL | AK28: NULL
A29: A24261921654 | B29: 2025 MMPS Template | C29: SUBMISSIONGRANT | D29: 6 | E29: Grant Price Per Share/Unit | F29: N | G29: 50 | H29: Y | I29: 48 | J29: NULL | K29: NULL | L29: NULL | M29: MON | N29: GRANTPRICE | O29: GRANTPRICE | P29: USE | Q29: L | R29: United States | S29: USA | T29: USA | U29: 10 | V29: 2 | W29: W | X29: Round all prices to two decimal places (e.g., 12.125 should be entered as 12.13). If you are reporting a performance cash plan, co-investment shares and/or deferred bonus matching shares enter 1.00. | Y29: NULL | Z29: M | AA29: Y | AB29: Y | AC29: INT:~CORE~AERO_NA~SSO~RCE~AGRO_ZAF~MDSUK~RENEWABLE~RENEWCLUB_FRA~AERO_EMEA~AERO_BRA~HC_GCC~HC_APAC~HIGHER_EDU~CMPIF_CHN~EDU_APAC~UPSTREAM_MYS~DRILL_GLOBAL~DRILL_NAT~CL_PS_SUPPORTSTAFF_INTL~CL_HRG~ | AD29: GRANTPRICE | AE29: Grant Price Per Share/Unit | AF29: Price of the share or unit at the time of grant. | AG29: Round all prices to two decimal places (e.g., 12.125 should be entered as 12.13). If you are reporting a performance cash plan, co-investment shares and/or deferred bonus matching shares enter 1.00. | AH29: 50 | AI29: NULL | AK29: If(IsNull(:GRANTPRICE),Null,Round(:GRANTPRICE,2))
A30: A24261921654 | B30: 2025 MMPS Template | C30: SUBMISSIONUNIT | D30: 6 | E30: Primary Medium | F30: Y | G30: NULL | H30: Y | I30: 5377 | J30: NULL | K30: NULL | L30: NULL | M30: PICK | N30: PRIMARY_MEDIUM | O30: DDE087 | P30: USE | Q30: L | R30: United States | S30: USA | T30: USA | U30: 5 | V30: 0 | W30: W | X30: NULL | Y30: NULL | Z30: M | AA30: Y | AB30: Y | AC30: ~XXX~ | AD30: PRIMARY_MEDIUM | AE30: Primary Medium | AF30: The primary medium or business of the unit. Multiple Media Platforms is a combination of more than one medium. | AG30: NULL | AH30: NULL | AI30: NULL | AJ30: NULL | AK30: NULL
A31: A24261921654 | B31: 2025 MMPS Template | C31: SUBMISSIONINCUMBENT | D31: 6 | E31: Area/City Code | F31: Y | G31: ~DEFAULT:BR100~CHINA:CN001~EDUCATION:MY001~ | H31: Y | I31: 7966 | J31: NULL | K31: NULL | L31: NULL | M31: PICK | N31: AREACODE | O31: DDE236 | P31: USE | Q31: L | R31: United States | S31: USA | T31: USA | U31: 5 | V31: 0 | W31: W | X31: Refer to the Country Codes tab. For remote employees, report their nominal office or location to which they are assigned For all regions except Moscow, Moscow region, Saint-Petersburg and Leningrad region apply the same area/city code to incumbents based in regional capital city and outside regional capital city within a region (e.g., RU033 for Novosibirsk and Novosibirsk region/oblast). For the cities of and regions around Moscow and Saint-Petersburg, more granular codes are available and should be applied as follows: - Apply RU001 to incumbents based in Moscow - Apply RU002 to incumbents based in Moscow region/oblast - Apply RU003 to incumbents based in Saint-Petersburg - Apply RU004 to incumbents based in Leningrad region/oblast | Y31: NULL | Z31: M | AA31: Y | AB31: Y | AC31: ADV:~CORE_EMEA~CORE_LATAM~PSAR~;SCOPE:~CORE_APAC~CYCAR~ | AD31: AREACODE | AE31: Area/City Code | AF31: The area/city code of the primary office to which the incumbent is assigned. | AG31: Refer to the Country Codes tab. For remote employees, report their nominal office or location to which they are assigned For all regions except Moscow, Moscow region, Saint-Petersburg and Leningrad region apply the same area/city code to incumbents based in regional capital city and outside regional capital city within a region (e.g., RU033 for Novosibirsk and Novosibirsk region/oblast). For the cities of and regions around Moscow and Saint-Petersburg, more granular codes are available and should be applied as follows: - Apply RU001 to incumbents based in Moscow - Apply RU002 to incumbents based in Moscow region/oblast - Apply RU003 to incumbents based in Saint-Petersburg - Apply RU004 to incumbents based in Leningrad region/oblast | AH31: ~DEFAULT:BR100~CHINA:CN001~EDUCATION:MY001~ | AI31: NULL | AK31: upper(trim(:AREACODE))
A32: A24261921654 | B32: 2025 MMPS Template | C32: SUBMISSIONGRANT | D32: 7 | E32: Accounting Value per Share/Unit of Award | F32: N | G32: 52.25 | H32: Y | I32: 100 | J32: NULL | K32: NULL | L32: NULL | M32: MON | N32: ACCOUNTING | O32: ACCOUNTING | P32: USE | Q32: L | R32: United States | S32: USA | T32: USA | U32: 12 | V32: 2 | W32: W | X32: If you are reporting a performance cash award, enter 1.00. Values should reflect the grant date accounting value per unit of the award (e.g., 52.25 for a single performance share). All values should be rounded to two decimal places (e.g., 52.2512 should be entered as 52.25). The currency should be the same as the Grant Price Currency. | Y32: NULL | Z32: M | AA32: Y | AB32: Y | AC32: INT:~CORE~;HID:~MFG_LATAM~ | AD32: ACCOUNTING | AE32: Accounting Value per Share/Unit of Award | AF32: For each share-based award, please enter the Fair Value of the award at the date of grant. The Fair Value is the per share value of the award at grant as calculated under International Financial Reporting Standards - IFRS(2) or the equivalent under local country GAAP. Please note that this grant-date Fair Value may be provided by your finance department. | AG32: If you are reporting a performance cash award, enter 1.00. Values should reflect the grant date accounting value per unit of the award (e.g., 52.25 for a single performance share). All values should be rounded to two decimal places (e.g., 52.2512 should be entered as 52.25). The currency should be the same as the Grant Price Currency. | AH32: 52.25 | AI32: NULL | AK32: If(IsNull(:ACCOUNTING),Null,Round(:ACCOUNTING,2))
A33: A24261921654 | B33: 2025 MMPS Template | C33: SUBMISSIONUNIT | D33: 7 | E33: Newspaper Circulation | F33: Y | G33: NULL | H33: Y | I33: 22814 | J33: NULL | K33: NULL | L33: NULL | M33: NUM | N33: NEWSPAPER_CIRCULATION | O33: DDE098 | P33: USE | Q33: L | R33: United States | S33: USA | T33: USA | U33: 12 | V33: 0 | W33: W | X33: NULL | Y33: NULL | Z33: M | AA33: Y | AB33: Y | AC33: ~XXX~ | AD33: NEWSPAPER_CIRCULATION | AE33: Newspaper Circulation | AF33: The audited newspaper circulation (in whole numbers) for the most recent fiscal year, not including potential online audiences. | AG33: NULL | AH33: NULL | AI33: NULL | AJ33: NULL | AK33: NULL
A34: A24261921654 | B34: 2025 MMPS Template | C34: SUBMISSIONINCUMBENT | D34: 7 | E34: Reports to Job Code | F34: N | G34: NULL | H34: Y | I34: 405 | J34: NULL | K34: NULL | L34: NULL | M34: CHAR | N34: RPT2JOB | O34: DDE180 | P34: USE | Q34: L | R34: United States | S34: USA | T34: USA | U34: 255 | V34: 0 | W34: W | X34: NULL | Y34: NULL | Z34: M | AA34: Y | AB34: Y | AC34: ~XXX~ | AD34: RPT2JOB | AE34: Reports to Job Code | AF34: NULL | AG34: NULL | AH34: NULL | AI34: NULL | AJ34: NULL | AK34: NULL
A35: A24261921654 | B35: 2025 MMPS Template | C35: SUBMISSIONCONTACT | D35: 7 | E35: Report Recipient Postal/ZIP Code | F35: N | G35: 10017 | H35: Y | I35: 996 | J35: NULL | K35: NULL | L35: NULL | M35: CHAR | N35: CONTACT_ZIPCODE | O35: DDE040 | P35: USE | Q35: L | R35: United States | S35: USA | T35: USA | U35: 250 | V35: 0 | W35: W | Y35: NULL | Z35: M | AA35: Y | AB35: Y | AC35: ~CORE_NA~AERO_NA~ | AD35: CONTACT_ZIPCODE | AE35: Report Recipient Postal/ZIP Code | AF35: Report Recipient Postal/ZIP Code | AH35: 10017 | AI35: NULL | AK35: NULL
A36: A24261921654 | B36: 2025 MMPS Template | C36: SUBMISSIONCOMPANY | D36: 7 | E36: Book Publishing | F36: Y | G36: Y [Yes] | H36: Y | I36: 1118 | J36: NULL | K36: NULL | L36: NULL | M36: BOOL | N36: BOOK_PUBLISHING | O36: DDE057 | P36: USE | Q36: L | R36: United States | S36: USA | T36: USA | U36: 1 | V36: 0 | W36: W | X36: N-No Y-Yes | Y36: NULL | Z36: M | AA36: Y | AB36: Y | AC36: ADV:~TMG~ | AD36: BOOK_PUBLISHING | AE36: Book Publishing | AF36: The media industries in which the organization is involved. | AG36: N-No Y-Yes | AH36: Y [Yes] | AI36: NULL | AK36: NULL
A37: A24261921654 | B37: 2025 MMPS Template | C37: SUBMISSIONCONTACT | D37: 8 | E37: Report Recipient Country | F37: N | G37: USA | H37: Y | I37: 998 | J37: NULL | K37: NULL | L37: NULL | M37: CHAR | N37: CONTACT_COUNTRY | O37: DDE042 | P37: USE | Q37: L | R37: United States | S37: USA | T37: USA | U37: 250 | V37: 0 | W37: W | Y37: NULL | Z37: M | AA37: Y | AB37: Y | AC37: ~CORE_NA~AERO_NA~ | AD37: CONTACT_COUNTRY | AE37: Report Recipient Country | AF37: Report Recipient Country | AH37: USA | AI37: NULL | AK37: NULL
A38: A24261921654 | B38: 2025 MMPS Template | C38: SUBMISSIONGRANT | D38: 8 | E38: Accounting Value per Share/Unit of Award Curr | F38: N | G38: NULL | H38: N | I38: 101 | J38: 100 | K38: 100 | L38: C | M38: CHAR | N38: ACCOUNTINGCURR | O38: ACCOUNTINGCURR | P38: USE | Q38: L | R38: United States | S38: USA | T38: USA | U38: 12 | V38: 0 | W38: W | X38: NULL | Y38: NULL | Z38: M | AA38: Y | AB38: Y | AC38: ~CORE~;HID:~MFG_LATAM~ | AD38: ACCOUNTINGCURR | AE38: Accounting Value per Share/Unit of Award Curr | AF38: Accounting Value per Share/Unit of Award Currency | AG38: NULL | AH38: NULL | AI38: NULL | AK38: :GRANTPRICECURR
A39: A24261921654 | B39: 2025 MMPS Template | C39: SUBMISSIONCOMPANY | D39: 8 | E39: Business to Business Media | F39: Y | G39: Y [Yes] | H39: Y | I39: 1119 | J39: NULL | K39: NULL | L39: NULL | M39: BOOL | N39: B_TO_B_MEDIA | O39: DDE058 | P39: USE | Q39: L | R39: United States | S39: USA | T39: USA | U39: 1 | V39: 0 | W39: W | X39: N-No Y-Yes | Y39: NULL | Z39: M | AA39: Y | AB39: Y | AC39: ADV:~TMG~ | AD39: B_TO_B_MEDIA | AE39: Business to Business Media | AF39: The media industries in which the organization is involved. | AG39: N-No Y-Yes | AH39: Y [Yes] | AI39: NULL | AK39: NULL
A40: A24261921654 | B40: 2025 MMPS Template | C40: SUBMISSIONUNIT | D40: 8 | E40: Newspaper Format | F40: Y | G40: NULL | H40: Y | I40: 37276 | J40: NULL | K40: NULL | L40: NULL | M40: PICK | N40: NEWSPAPER_FORMAT | O40: DDE101 | P40: USE | Q40: L | R40: United States | S40: USA | T40: USA | U40: 5 | V40: 0 | W40: W | X40: 1 Daily 2 Non-Daily/Weekly/Other | Y40: NULL | Z40: M | AA40: Y | AB40: Y | AC40: ~XXX~ | AD40: NEWSPAPER_FORMAT | AE40: Newspaper Format | AF40: How often the newspaper is published. | AG40: 1 Daily 2 Non-Daily/Weekly/Other | AH40: NULL | AI40: NULL | AJ40: NULL | AK40: NULL
A41: A24261921654 | B41: 2025 MMPS Template | C41: SUBMISSIONINCUMBENT | D41: 8 | E41: Russia Region | F41: N | G41: NULL | H41: N | I41: NULL | J41: NULL | K41: NULL | L41: NULL | M41: PICK | N41: RUSSIA_REGION | O41: NULL | P41: USE | Q41: C | R41: United States | S41: USA | T41: USA | U41: 5 | V41: 0 | W41: W | X41: NULL | Y41: NULL | Z41: NULL | AA41: NULL | AB41: Y | AC41: ~CORE_NONEXEC_RUS~ | AD41: RUSSIA_REGION | AE41: Russia Region | AF41: NULL | AG41: NULL | AH41: NULL | AI41: NULL | AJ41: If(IsNull(:AREACODE),null,if(In(:AREACODE,"RU001","RU002"),"RU1",if(:AREACODE="RU003","RU2","RU3"))) | AK41: NULL
A42: A24261921654 | B42: 2025 MMPS Template | C42: SUBMISSIONCOMPANY | D42: 9 | E42: Consumer Magazine | F42: Y | G42: Y [Yes] | H42: Y | I42: 1120 | J42: NULL | K42: NULL | L42: NULL | M42: BOOL | N42: CONSUMER_MAGAZINE | O42: DDE059 | P42: USE | Q42: L | R42: United States | S42: USA | T42: USA | U42: 1 | V42: 0 | W42: W | X42: N-No Y-Yes | Y42: NULL | Z42: M | AA42: Y | AB42: Y | AC42: ADV:~TMG~ | AD42: CONSUMER_MAGAZINE | AE42: Consumer Magazine | AF42: The media industries in which the organization is involved. | AG42: N-No Y-Yes | AH42: Y [Yes] | AI42: NULL | AK42: NULL
A43: A24261921654 | B43: 2025 MMPS Template | C43: SUBMISSIONCONTACT | D43: 9 | E43: Report Recipient Phone | F43: N | G43: +1 (212) 555-5678 | H43: Y | I43: 999 | J43: NULL | K43: NULL | L43: NULL | M43: CHAR | N43: CONTACT_PHONE | O43: DDE043 | P43: USE | Q43: L | R43: United States | S43: USA | T43: USA | U43: 250 | V43: 0 | W43: W | Y43: NULL | Z43: M | AA43: Y | AB43: Y | AC43: ~CORE_NA~AERO_NA~ | AD43: CONTACT_PHONE | AE43: Report Recipient Phone | AF43: Report Recipient Phone | AH43: +1 (212) 555-5678 | AI43: NULL | AK43: NULL
A44: A24261921654 | B44: 2025 MMPS Template | C44: SUBMISSIONINCUMBENT | D44: 9 | E44: Postal/ZIP Code | F44: Y | G44: ~GI:75008~FS:75008~ENERGY:75008~PHS:75008~MDS:EC3M~PS:EC3M~CSR:10003~DEFAULT:75008~ | H44: Y | I44: 246 | J44: NULL | K44: NULL | L44: NULL | M44: CHAR | N44: POSTZIPCODE | O44: DDE145 | P44: USE | Q44: L | R44: United States | S44: USA | T44: USA | U44: 12 | V44: 0 | W44: W | X44: For home based employees or equivalent, please provide the postcode of their nominal or primary office. | Y44: NULL | Z44: M | AA44: Y | AB44: Y | AC44: INT:~CORE_APAC~CORE_EMEA~CORE_NONEXEC_NA~CYCAR_APAC~CYCAR_EMEA~ | AD44: POSTZIPCODE | AE44: Postal/ZIP Code | AF44: The Postal/ZIP code for the incumbent's primary work location. | AG44: For home based employees or equivalent, please provide the postcode of their nominal or primary office. | AH44: ~GI:75008~FS:75008~ENERGY:75008~PHS:75008~MDS:EC3M~PS:EC3M~CSR:10003~DEFAULT:75008~ | AI44: NULL | AK44: Trim(:POSTZIPCODE)
A45: A24261921654 | B45: 2025 MMPS Template | C45: SUBMISSIONUNIT | D45: 9 | E45: TV Market Rank | F45: N | G45: NULL | H45: N | I45: 37279 | J45: NULL | K45: NULL | L45: NULL | M45: PICK | N45: TV_MARKET_RANK | O45: DDE104 | P45: USE | Q45: L | R45: United States | S45: USA | T45: USA | U45: 5 | V45: 0 | W45: W | X45: NULL | Y45: NULL | Z45: M | AA45: Y | AB45: Y | AC45: ~XXX~ | AD45: TV_MARKET_RANK | AE45: TV Market Rank | AF45: Name of the business unit. | AG45: NULL | AH45: NULL | AI45: NULL | AJ45: NULL | AK45: NULL
A46: A24261921654 | B46: 2025 MMPS Template | C46: SUBMISSIONGRANT | D46: 9 | E46: Number of Shares/Units Granted | F46: N | G46: 10000 | H46: Y | I46: 47 | J46: NULL | K46: NULL | L46: NULL | M46: NUM | N46: SHARESUNITS | O46: SHARESUNITS | P46: USE | Q46: L | R46: United States | S46: USA | T46: USA | U46: 15 | V46: 0 | W46: W | X46: Do not report actual payouts or awards for the cycle that just ended. For newly hired employees or those near retirement who are long-term incentive eligible but did not receive a grant, enter an estimate. For performance unit or share plans, enter the target award opportunity (for defined target plans) or maximum award opportunity (for defined maximum plans) for the cycle that started most recently. For performance cash, co-investment shares and deferred bonus matching plans, for convenience and as a convention, report the full award value and enter 1.00 under grant price per share/unit. For Performance Cash plans, enter the target award (e.g., if an incumbent could earn 100% of base salary if target performance is achieved and the incumbent's base salary is 200,000, enter 200,000 and use the Base Salary currency as the Grant Price Currency). For Co-Investment Shares, report the maximum opportunity multiplied by the maximum share-matching on that investment. For example, if the maximum investment opportunity is 50% of a 200,000 base salary and the company will match a maximum of 50% of that investment, the award value is 50% x 200,000 x 50% = 50,000. For Deferred Bonus Matching Shares, report the maximum deferral opportunity (compulsory and/or voluntary) multiplied by the maximum company match on that deferral. For example, if the incumbent can defer up to 50% of a 100,000 target bonus and the company will match 100%, the award value is 50% x 100,000 x 100% = 50,000. | Y46: NULL | Z46: M | AA46: Y | AB46: Y | AC46: INT,DSW:~CORE~AERO_NA~SSO~RCE~AGRO_ZAF~MDSUK~RENEWABLE~RENEWCLUB_FRA~AERO_EMEA~AERO_BRA~HC_GCC~HC_APAC~HIGHER_EDU~CMPIF_CHN~EDU_APAC~UPSTREAM_MYS~DRILL_GLOBAL~DRILL_NAT~CL_PS_SUPPORTSTAFF_INTL~CL_HRG~;HID:~MFG_LATAM~ | AD46: SHARESUNITS | AE46: Number of Shares/Units Granted | AF46: The number of options, shares or units granted. For performance plans, the values provided should be shares/cash/units for the upcoming cycle, not payouts from the cycle that just ended. | AG46: Do not report actual payouts or awards for the cycle that just ended. For newly hired employees or those near retirement who are long-term incentive eligible but did not receive a grant, enter an estimate. For performance unit or share plans, enter the target award opportunity (for defined target plans) or maximum award opportunity (for defined maximum plans) for the cycle that started most recently. For performance cash, co-investment shares and deferred bonus matching plans, for convenience and as a convention, report the full award value and enter 1.00 under grant price per share/unit. For Performance Cash plans, enter the target award (e.g., if an incumbent could earn 100% of base salary if target performance is achieved and the incumbent's base salary is 200,000, enter 200,000 and use the Base Salary currency as the Grant Price Currency). For Co-Investment Shares, report the maximum opportunity multiplied by the maximum share-matching on that investment. For example, if the maximum investment opportunity is 50% of a 200,000 base salary and the company will match a maximum of 50% of that investment, the award value is 50% x 200,000 x 50% = 50,000. For Deferred Bonus Matching Shares, report the maximum deferral opportunity (compulsory and/or voluntary) multiplied by the maximum company match on that deferral. For example, if the incumbent can defer up to 50% of a 100,000 target bonus and the company will match 100%, the award value is 50% x 100,000 x 100% = 50,000. | AH46: 10000 | AI46: NULL | AK46: If(IsNull(:SHARESUNITS),Null,Round(:SHARESUNITS,0))
A47: A24261921654 | B47: 2025 MMPS Template | C47: SUBMISSIONGRANT | D47: 10 | E47: Comments | F47: N | G47: NULL | H47: N | I47: 82 | J47: NULL | K47: NULL | L47: NULL | M47: CHAR | N47: COMMENTS | O47: COMMENTS | P47: USE | Q47: L | R47: United States | S47: USA | T47: USA | U47: 255 | V47: 0 | W47: W | X47: NULL | Y47: NULL | Z47: M | AA47: Y | AB47: Y | AC47: ~ALL~CYCAR~ | AD47: COMMENTS | AE47: Comments | AF47: Comments | AG47: NULL | AH47: NULL | AI47: NULL | AK47: NULL
A48: A24261921654 | B48: 2025 MMPS Template | C48: SUBMISSIONINCUMBENT | D48: 10 | E48: Aircraft Type | F48: N | G48: A320 | H48: Y | I48: 152604 | J48: NULL | K48: NULL | L48: NULL | M48: CHAR | N48: AIRCRAFT_TYPE | O48: PLINCELEM_1 | P48: USE | Q48: L | R48: United States | S48: USA | T48: USA | U48: 256 | V48: 0 | W48: W | X48: Report for applicable incumbents only | Y48: NULL | Z48: S | AA48: N | AB48: Y | AC48: PUB:~AVIATION_GLB~ | AD48: AIRCRAFT_TYPE | AE48: Aircraft Type | AF48: Model of aircraft operated by the flight deck crew (e.g., A320, B777, ATR72) | AG48: Report for applicable incumbents only | AH48: A320 | AI48: NULL | AK48: NULL
A49: A24261921654 | B49: 2025 MMPS Template | C49: SUBMISSIONCONTACT | D49: 10 | E49: Report Recipient Fax | F49: N | G49: +1 (212) 555-1111 | H49: Y | I49: 1000 | J49: NULL | K49: NULL | L49: NULL | M49: CHAR | N49: CONTACT_FAX | O49: DDE044 | P49: USE | Q49: L | R49: United States | S49: USA | T49: USA | U49: 250 | V49: 0 | W49: W | Y49: NULL | Z49: M | AA49: Y | AB49: Y | AC49: ~CORE_NA~AERO_NA~ | AD49: CONTACT_FAX | AE49: Report Recipient Fax | AF49: Report Recipient Fax | AH49: +1 (212) 555-1111 | AI49: NULL | AK49: NULL
A50: A24261921654 | B50: 2025 MMPS Template | C50: SUBMISSIONCOMPANY | D50: 10 | E50: Event/Exhibit | F50: Y | G50: N [No] | H50: Y | I50: 1121 | J50: NULL | K50: NULL | L50: NULL | M50: BOOL | N50: EVENT_EXHIBIT | O50: DDE060 | P50: USE | Q50: L | R50: United States | S50: USA | T50: USA | U50: 1 | V50: 0 | W50: W | X50: N-No Y-Yes | Y50: NULL | Z50: M | AA50: Y | AB50: Y | AC50: ADV:~TMG~ | AD50: EVENT_EXHIBIT | AE50: Event/Exhibit | AF50: The media industries in which the organization is involved. | AG50: N-No Y-Yes | AH50: N [No] | AI50: NULL | AK50: NULL
A51: A24261921654 | B51: 2025 MMPS Template | C51: SUBMISSIONUNIT | D51: 10 | E51: Radio Market Rank | F51: N | G51: NULL | H51: N | I51: 37277 | J51: NULL | K51: NULL | L51: NULL | M51: PICK | N51: RADIO_MARKET_RANK | O51: DDE102 | P51: USE | Q51: L | R51: United States | S51: USA | T51: USA | U51: 5 | V51: 0 | W51: W | X51: NULL | Y51: NULL | Z51: M | AA51: Y | AB51: Y | AC51: ~XXX~ | AD51: RADIO_MARKET_RANK | AE51: Radio Market Rank | AF51: Organization Unit - Corporate/Noncorporate | AG51: NULL | AH51: NULL | AI51: NULL | AJ51: NULL | AK51: NULL
A52: A24261921654 | B52: 2025 MMPS Template | C52: SUBMISSIONINCUMBENT | D52: 11 | E52: Employee Manager (Job Title) | F52: N | G52: Chief Pilot | H52: Y | I52: 152605 | J52: NULL | K52: NULL | L52: NULL | M52: CHAR | N52: EMP_MNGR_TITLE | O52: TEST_CLAIRE | P52: USE | Q52: L | R52: United States | S52: USA | T52: USA | U52: 250 | V52: 0 | W52: W | X52: Do not use personal identifying data, but use job titles | Y52: NULL | Z52: S | AA52: N | AB52: Y | AC52: PUB:~AVIATION_GLB~ | AD52: EMP_MNGR_TITLE | AE52: Employee Manager (Job Title) | AF52: Who the incumbents reports to | AG52: Do not use personal identifying data, but use job titles | AH52: Chief Pilot | AI52: NULL | AK52: NULL
A53: A24261921654 | B53: 2025 MMPS Template | C53: SUBMISSIONCOMPANY | D53: 11 | E53: Information Services | F53: Y | G53: Y [Yes] | H53: Y | I53: 1122 | J53: NULL | K53: NULL | L53: NULL | M53: BOOL | N53: INFORMATION_SERVICES | O53: DDE061 | P53: USE | Q53: L | R53: United States | S53: USA | T53: USA | U53: 1 | V53: 0 | W53: W | X53: N-No Y-Yes | Y53: NULL | Z53: M | AA53: Y | AB53: Y | AC53: ADV:~TMG~ | AD53: INFORMATION_SERVICES | AE53: Information Services | AF53: The media industries in which the organization is involved. | AG53: N-No Y-Yes | AH53: Y [Yes] | AI53: NULL | AK53: NULL
A54: A24261921654 | B54: 2025 MMPS Template | C54: SUBMISSIONUNIT | D54: 11 | E54: 2020 TV Rank | F54: Y | G54: NULL | H54: Y | I54: 1080 | J54: NULL | K54: NULL | L54: NULL | M54: PICK | N54: NEXT_YEAR_TV_RANK | O54: DDE027 | P54: USE | Q54: L | R54: United States | S54: USA | T54: USA | U54: 5 | V54: 0 | W54: W | X54: NULL | Y54: NULL | Z54: S | AA54: Y | AB54: Y | AC54: ~XXX~ | AD54: NEXT_YEAR_TV_RANK | AE54: 2020 TV Rank | AF54: The appropriate TV market rank for the station. | AG54: NULL | AH54: NULL | AI54: NULL | AJ54: NULL | AK54: NULL
A55: A24261921654 | B55: 2025 MMPS Template | C55: SUBMISSIONGRANT | D55: 11 | E55: Grant Structure (SO and PP plans only) | F55: N | G55: T | H55: Y | I55: 84 | J55: NULL | K55: NULL | L55: NULL | M55: PICK | N55: VESTING | O55: VESTING | P55: USE | Q55: L | R55: United States | S55: USA | T55: USA | U55: 5 | V55: 0 | W55: W | X55: T-Defined target award (With higher/lower payout potential the emphasis to participants is on the target number of shares). M-Defined maximum award (With only lower payout potential the emphasis to participants is on the maximum number of shares). | Y55: NULL | Z55: M | AA55: Y | AB55: Y | AC55: INT,DSW:~CORE_EMEA~CORE_LATAM~CORE_APAC~ | AD55: VESTING | AE55: Grant Structure (SO and PP plans only) | AF55: The payout structure for the grant. | AG55: T-Defined target award (With higher/lower payout potential the emphasis to participants is on the target number of shares). M-Defined maximum award (With only lower payout potential the emphasis to participants is on the maximum number of shares). | AH55: T | AI55: NULL | AK55: NULL
A56: A24261921654 | B56: 2025 MMPS Template | C56: SUBMISSIONCONTACT | D56: 11 | E56: Report Recipient Email | F56: N | G56: jandoe@example.com | H56: Y | I56: 1001 | J56: NULL | K56: NULL | L56: NULL | M56: CHAR | N56: CONTACT_EMAIL | O56: DDE045 | P56: USE | Q56: L | R56: United States | S56: USA | T56: USA | U56: 250 | V56: 0 | W56: W | Y56: NULL | Z56: M | AA56: Y | AB56: Y | AC56: ~CORE_NA~AERO_NA~ | AD56: CONTACT_EMAIL | AE56: Report Recipient Email | AF56: Report Recipient Email | AH56: jandoe@example.com | AI56: NULL | AK56: NULL
A57: A24261921654 | B57: 2025 MMPS Template | C57: SUBMISSIONGRANT | D57: 12 | E57: LTI Grant Value | F57: N | G57: NULL | H57: N | I57: 31375 | J57: NULL | K57: NULL | L57: NULL | M57: NUM | N57: LTI_GRANT_VALUE | O57: DDE030 | P57: USE | Q57: L | R57: United States | S57: USA | T57: USA | U57: 18 | V57: 0 | W57: W | X57: NULL | Y57: NULL | Z57: M | AA57: Y | AB57: Y | AC57: INT:~CORE_EXEC_EMEA~CORE_EXEC_LATAM~CORE_EXEC_APAC~ | AD57: LTI_GRANT_VALUE | AE57: LTI Grant Value | AF57: NULL | AG57: NULL | AH57: NULL | AI57: NULL | AJ57: NULL | AK57: NULL
A58: A24261921654 | B58: 2025 MMPS Template | C58: SUBMISSIONCOMPANY | D58: 12 | E58: Music Label | F58: Y | G58: N [No] | H58: Y | I58: 1123 | J58: NULL | K58: NULL | L58: NULL | M58: BOOL | N58: MUSIC_LABEL | O58: DDE062 | P58: USE | Q58: L | R58: United States | S58: USA | T58: USA | U58: 1 | V58: 0 | W58: W | X58: N-No Y-Yes | Y58: NULL | Z58: M | AA58: Y | AB58: Y | AC58: ADV:~TMG~ | AD58: MUSIC_LABEL | AE58: Music Label | AF58: The media industries in which the organization is involved. | AG58: N-No Y-Yes | AH58: N [No] | AI58: NULL | AK58: NULL
A59: A24261921654 | B59: 2025 MMPS Template | C59: SUBMISSIONUNIT | D59: 12 | E59: Magazine Circulation | F59: N | G59: NULL | H59: Y | I59: 22813 | J59: NULL | K59: 22812 | L59: NULL | M59: NUM | N59: MAGAZINE_CIRCULATION | O59: DDE097 | P59: USE | Q59: L | R59: United States | S59: USA | T59: USA | U59: 12 | V59: 0 | W59: W | X59: NULL | Y59: NULL | Z59: M | AA59: Y | AB59: Y | AC59: ~XXX~ | AD59: MAGAZINE_CIRCULATION | AE59: Magazine Circulation | AF59: The audited magazine circulation (in whole numbers) per issue, not including potential online audiences. | AG59: NULL | AH59: NULL | AI59: NULL | AJ59: NULL | AK59: NULL
A60: A24261921654 | B60: 2025 MMPS Template | C60: SUBMISSIONCONTACT | D60: 12 | E60: Cash Compensation Contact Name | F60: N | G60: Mr. Mike Smith | H60: Y | I60: 982 | J60: NULL | K60: NULL | L60: NULL | M60: CHAR | N60: CASH_CONTACT_NAME | O60: DDE026 | P60: USE | Q60: L | R60: United States | S60: USA | T60: USA | U60: 250 | V60: 0 | W60: W | Y60: NULL | Z60: M | AA60: Y | AB60: Y | AC60: ~CORE~CYCAR~ | AD60: CASH_CONTACT_NAME | AE60: Cash Compensation Contact Name | AF60: Cash Compensation Contact Name | AH60: Mr. Mike Smith | AI60: NULL | AK60: NULL
A61: A24261921654 | B61: 2025 MMPS Template | C61: SUBMISSIONINCUMBENT | D61: 12 | E61: Geographic Code | F61: N | G61: 4 | H61: Y | I61: 78767 | J61: NULL | K61: NULL | L61: NULL | M61: PICK | N61: GEOGRAPHIC_CODE | O61: DDE837 | P61: USE | Q61: L | R61: United States | S61: USA | T61: USA | U61: 5 | V61: 0 | W61: W | Y61: NULL | Z61: M | AA61: Y | AB61: Y | AC61: ~E27US~ | AD61: GEOGRAPHIC_CODE | AE61: Geographic Code | AF61: Enter the Geographic Code (GEO Code) for the incumbent's primary work location. For professional employees this would most often be the incumbent's onshore office location. In situations where an incumbent has multiple work locations that would cover more than one GEO code, indicate the GEO code where the incumbent spends the majority of thier work time. The GEO code that you provide should correspond with the zip code you provide (e.g. if GEO Code = 2, then zip code should either be a West Texas or New Mexico zip code. For incumbents based on Gulf of Mexico zip code entered should be "00000" 1 = Alaska 2 = Midland/Permian/Delaware Basin 3 = Rocky Mountain Region 4 = Southeastern States 5 = West Coast 6 = Gulf of Mexico 8 = Bakken 9 = Mid Continent 10 = Utica 11 = Eagle Ford 12 = Other | AH61: 4 | AI61: NULL | AK61: NULL
A62: A24261921654 | B62: 2025 MMPS Template | C62: SUBMISSIONINCUMBENT | D62: 13 | E62: Boutique Location/Mall Name | F62: Y | G62: NULL | H62: Y | I62: 152542 | J62: NULL | K62: NULL | L62: NULL | M62: CHAR | N62: MALL_NAME | O62: DDE731 | P62: USE | Q62: L | R62: United States | S62: USA | T62: USA | U62: 255 | V62: 0 | W62: W | X62: Boutique Location/Mall Name | Y62: NULL | Z62: S | AA62: Y | AB62: Y | AC62: ~XXX~ | AD62: MALL_NAME | AE62: Boutique Location/Mall Name | AF62: Boutique Location/Mall Name | AG62: Boutique Location/Mall Name | AH62: NULL | AI62: NULL | AK62: NULL
A63: A24261921654 | B63: 2025 MMPS Template | C63: SUBMISSIONCOMPANY | D63: 13 | E63: Newspaper | F63: Y | G63: Y [Yes] | H63: Y | I63: 1124 | J63: NULL | K63: NULL | L63: NULL | M63: BOOL | N63: NEWSPAPER | O63: DDE063 | P63: USE | Q63: L | R63: United States | S63: USA | T63: USA | U63: 1 | V63: 0 | W63: W | X63: N-No Y-Yes | Y63: NULL | Z63: M | AA63: Y | AB63: Y | AC63: ADV:~TMG~ | AD63: NEWSPAPER | AE63: Newspaper | AF63: The media industries in which the organization is involved. | AG63: N-No Y-Yes | AH63: Y [Yes] | AI63: NULL | AK63: NULL
A64: A24261921654 | B64: 2025 MMPS Template | C64: SUBMISSIONGRANT | D64: 13 | E64: LTI Factor | F64: N | G64: NULL | H64: N | I64: 31380 | J64: NULL | K64: NULL | L64: NULL | M64: NUM | N64: LTI_FACTOR | O64: DDE035 | P64: USE | Q64: L | R64: United States | S64: USA | T64: USA | U64: 15 | V64: 4 | W64: W | X64: NULL | Y64: NULL | Z64: M | AA64: Y | AB64: Y | AC64: INT:~CORE_EXEC_EMEA~MDSUK~AERO_EMEA~CL_HRG~;INT:~CORE_NONEXEC_EMEA~HIGHER_EDU~ | AD64: LTI_FACTOR | AE64: LTI Factor | AF64: NULL | AG64: NULL | AH64: NULL | AI64: NULL | AK64: NULL
A65: A24261921654 | B65: 2025 MMPS Template | C65: SUBMISSIONUNIT | D65: 13 | E65: Comments | F65: N | G65: NULL | H65: N | I65: 80 | J65: NULL | K65: NULL | L65: NULL | M65: CHAR | N65: COMMENTS | O65: COMMENTS | P65: USE | Q65: L | R65: United States | S65: USA | T65: USA | U65: 255 | V65: 0 | W65: W | X65: NULL | Y65: NULL | Z65: M | AA65: Y | AB65: Y | AC65: ~ALL~CYCAR~ | AD65: COMMENTS | AE65: Comments | AF65: Unit Comments | AG65: NULL | AH65: NULL | AI65: NULL | AK65: NULL
A66: A24261921654 | B66: 2025 MMPS Template | C66: SUBMISSIONCONTACT | D66: 13 | E66: Cash Compensation Contact Title | F66: N | G66: Cash Contact | H66: Y | I66: 983 | J66: NULL | K66: NULL | L66: NULL | M66: CHAR | N66: CASH_CONTACT_TITLE | O66: DDE027 | P66: USE | Q66: L | R66: United States | S66: USA | T66: USA | U66: 250 | V66: 0 | W66: W | Y66: NULL | Z66: M | AA66: Y | AB66: Y | AC66: ~CORE~CYCAR~ | AD66: CASH_CONTACT_TITLE | AE66: Cash Compensation Contact Title | AF66: Cash Compensation Contact Title | AH66: Cash Contact | AI66: NULL | AK66: NULL
A67: A24261921654 | B67: 2025 MMPS Template | C67: SUBMISSIONCONTACT | D67: 14 | E67: Cash Compensation Contact Phone | F67: N | G67: +1 (212) 555-1111 | H67: Y | I67: 984 | J67: NULL | K67: NULL | L67: NULL | M67: CHAR | N67: CASH_CONTACT_PHONE | O67: DDE028 | P67: USE | Q67: L | R67: United States | S67: USA | T67: USA | U67: 250 | V67: 0 | W67: W | Y67: NULL | Z67: M | AA67: Y | AB67: Y | AC67: ~CORE~CYCAR~ | AD67: CASH_CONTACT_PHONE | AE67: Cash Compensation Contact Phone | AF67: Cash Compensation Contact Phone | AH67: +1 (212) 555-1111 | AI67: NULL | AK67: NULL
A68: A24261921654 | B68: 2025 MMPS Template | C68: SUBMISSIONINCUMBENT | D68: 14 | E68: Unique Incumbent Identifier | F68: Y | G68: 12345 | H68: Y | I68: 241 | J68: NULL | K68: NULL | L68: NULL | M68: CHAR | N68: IDENT | O68: DDE140 | P68: USE | Q68: L | R68: United States | S68: USA | T68: USA | U68: 60 | V68: 0 | W68: W | X68: Do not use personal identifying data (e.g., employee names, initials, or government ID such as Social Security or Social Insurance number). Use consistent identifiers year over year. | Y68: NULL | Z68: M | AA68: Y | AB68: Y | AC68: ADV:~CORE~CYCAR~ | AD68: IDENT | AE68: Unique Incumbent Identifier | AF68: Internal reference number, which is specific and unique to each individual. | AG68: Do not use personal identifying data (e.g., employee names, initials, or government ID such as Social Security or Social Insurance number). Use consistent identifiers year over year. | AH68: 12345 | AI68: NULL | AK68: NULL
A69: A24261921654 | B69: 2025 MMPS Template | C69: SUBMISSIONCOMPANY | D69: 14 | E69: Online/Digital | F69: Y | G69: Y [Yes] | H69: Y | I69: 1125 | J69: NULL | K69: NULL | L69: NULL | M69: BOOL | N69: ONLINE_DIGITAL | O69: DDE064 | P69: USE | Q69: L | R69: United States | S69: USA | T69: USA | U69: 1 | V69: 0 | W69: W | X69: N-No Y-Yes | Y69: NULL | Z69: M | AA69: Y | AB69: Y | AC69: ADV:~TMG~ | AD69: ONLINE_DIGITAL | AE69: Online/Digital | AF69: The media industries in which the organization is involved. | AG69: N-No Y-Yes | AH69: Y [Yes] | AI69: NULL | AK69: NULL
A70: A24261921654 | B70: 2025 MMPS Template | C70: SUBMISSIONGRANT | D70: 14 | E70: LTI Expected Value | F70: N | G70: NULL | H70: N | I70: 31376 | J70: NULL | K70: NULL | L70: NULL | M70: NUM | N70: LTI_EXPECTED_VALUE | O70: DDE031 | P70: USE | Q70: L | R70: United States | S70: USA | T70: USA | U70: 18 | V70: 0 | W70: W | X70: NULL | Y70: NULL | Z70: M | AA70: Y | AB70: Y | AC70: INT:~CORE_EMEA~CORE_LATAM~CORE_APAC~ | AD70: LTI_EXPECTED_VALUE | AE70: LTI Expected Value | AF70: NULL | AG70: NULL | AH70: NULL | AI70: NULL | AJ70: NULL | AK70: NULL
A71: A24261921654 | B71: 2025 MMPS Template | C71: SUBMISSIONUNIT | D71: 14 | E71: Industry Group | F71: N | G71: ~CSR:150~DEFAULT:Hospitals~ | H71: Y | I71: 5373 | J71: NULL | K71: NULL | L71: NULL | M71: PICK | N71: IND_GROUP | O71: DDE083 | P71: USE | Q71: L | R71: United States | S71: USA | T71: USA | U71: 5 | V71: 0 | W71: W | X71: NULL | Y71: NULL | Z71: M | AA71: Y | AB71: Y | AC71: ~XXX~ | AD71: IND_GROUP | AE71: Industry Group | AF71: Select the Industry Group that best describes the unit being reported. | AG71: NULL | AH71: ~CSR:150~DEFAULT:Hospitals~ | AI71: NULL | AJ71: NULL | AK71: NULL
A72: A24261921654 | B72: 2025 MMPS Template | C72: SUBMISSIONUNIT | D72: 15 | E72: Business Unit Individual Industry | F72: N | G72: ~CSR:1510~HCNA:7020~DEFAULT:805~ | H72: Y | I72: 5374 | J72: NULL | K72: NULL | L72: NULL | M72: PICK | N72: INDUSTRY_UNIT | O72: DDE084 | P72: USE | Q72: L | R72: United States | S72: USA | T72: USA | U72: 5 | V72: 0 | W72: W | X72: Refer to the Industry Groups tab. | Y72: NULL | Z72: M | AA72: Y | AB72: Y | AC72: ~XXX~ | AD72: INDUSTRY_UNIT | AE72: Business Unit Individual Industry | AF72: The Industry Classification that best describes the unit being reported. | AG72: Refer to the Industry Groups tab. | AH72: ~CSR:1510~HCNA:7020~DEFAULT:805~ | AI72: NULL | AJ72: NULL | AK72: NULL
A73: A24261921654 | B73: 2025 MMPS Template | C73: SUBMISSIONINCUMBENT | D73: 15 | E73: Reports to Unique Employee Identifier | F73: N | G73: 6789 | H73: Y | I73: 367 | J73: NULL | K73: NULL | L73: NULL | M73: CHAR | N73: REP_UNIQUE_ID | O73: DDE034 | P73: USE | Q73: L | R73: United States | S73: USA | T73: USA | U73: 60 | V73: 0 | W73: W | X73: Do not use personal identifying data (e.g., employee names, initials, or government ID such as Social Security or Social Insurance number). | Y73: NULL | Z73: S | AA73: Y | AB73: Y | AC73: ~XXX~ | AD73: REP_UNIQUE_ID | AE73: Reports to Unique Employee Identifier | AF73: Internal reference number, which is specific and unique to each individual incumbent manager. | AG73: Do not use personal identifying data (e.g., employee names, initials, or government ID such as Social Security or Social Insurance number). | AH73: 6789 | AI73: NULL | AJ73: NULL | AK73: NULL
A74: A24261921654 | B74: 2025 MMPS Template | C74: SUBMISSIONCONTACT | D74: 15 | E74: Cash Compensation Contact E-mail | F74: N | G74: mike.smith@example.com | H74: Y | I74: 985 | J74: NULL | K74: NULL | L74: NULL | M74: CHAR | N74: CASH_CONTACT_EMAIL | O74: DDE029 | P74: USE | Q74: L | R74: United States | S74: USA | T74: USA | U74: 250 | V74: 0 | W74: W | Y74: NULL | Z74: M | AA74: Y | AB74: Y | AC74: ~CORE~CYCAR~ | AD74: CASH_CONTACT_EMAIL | AE74: Cash Compensation Contact E-mail | AF74: Cash Compensation Contact E-mail | AH74: mike.smith@example.com | AI74: NULL | AK74: NULL
A75: A24261921654 | B75: 2025 MMPS Template | C75: SUBMISSIONCOMPANY | D75: 15 | E75: Radio | F75: Y | G75: N [No] | H75: Y | I75: 1126 | J75: NULL | K75: NULL | L75: NULL | M75: BOOL | N75: RADIO | O75: DDE065 | P75: USE | Q75: L | R75: United States | S75: USA | T75: USA | U75: 1 | V75: 0 | W75: W | X75: N-No Y-Yes | Y75: NULL | Z75: M | AA75: Y | AB75: Y | AC75: ADV:~TMG~ | AD75: RADIO | AE75: Radio | AF75: The media industries in which the organization is involved. | AG75: N-No Y-Yes | AH75: N [No] | AI75: NULL | AK75: NULL
A76: A24261921654 | B76: 2025 MMPS Template | C76: SUBMISSIONUNIT | D76: 16 | E76: Unit Net Operating Revenue | F76: N | G76: 999999999 | H76: Y | I76: 37284 | J76: NULL | K76: NULL | L76: NULL | M76: MON | N76: UREV | O76: DDE109 | P76: USE | Q76: L | R76: United States | S76: USA | T76: USA | U76: 12 | V76: 0 | W76: W | X76: NULL | Y76: NULL | Z76: M | AA76: Y | AB76: Y | AC76: ~XXX~ | AD76: UREV | AE76: Unit Net Operating Revenue | AF76: Net patient revenue plus other operating revenue such as government grants, endowments, and contributions for the specific unit. | AG76: NULL | AH76: 999999999 | AI76: NULL | AJ76: NULL | AK76: NULL
A77: A24261921654 | B77: 2025 MMPS Template | C77: SUBMISSIONINCUMBENT | D77: 16 | E77: Reports to Unique Incumbent Identifier | F77: N | G77: 12345 | H77: Y | I77: 333 | J77: NULL | K77: NULL | L77: NULL | M77: CHAR | N77: REP_UNIQUE_ID_BRAZIL | O77: DDE072 | P77: USE | Q77: L | R77: United States | S77: USA | T77: USA | U77: 250 | V77: 0 | W77: W | X77: Use the same Unique Incumbent Identifier informed for the incumbents | Y77: NULL | Z77: S | AA77: Y | AB77: Y | AC77: ~XXX~ | AD77: REP_UNIQUE_ID_BRAZIL | AE77: Reports to Unique Incumbent Identifier | AF77: Internal reference number to which the incumbents reports to. | AG77: Use the same Unique Incumbent Identifier informed for the incumbents | AH77: 12345 | AI77: NULL | AK77: NULL
A78: A24261921654 | B78: 2025 MMPS Template | C78: SUBMISSIONCOMPANY | D78: 16 | E78: TV/Internet Access | F78: Y | G78: Y [Yes] | H78: Y | I78: 1127 | J78: NULL | K78: NULL | L78: NULL | M78: BOOL | N78: TV_INTERNET_ACCESS | O78: DDE066 | P78: USE | Q78: L | R78: United States | S78: USA | T78: USA | U78: 1 | V78: 0 | W78: W | X78: N-No Y-Yes | Y78: NULL | Z78: M | AA78: Y | AB78: Y | AC78: ADV:~TMG~ | AD78: TV_INTERNET_ACCESS | AE78: TV/Internet Access | AF78: The media industries in which the organization is involved. | AG78: N-No Y-Yes | AH78: Y [Yes] | AI78: NULL | AK78: NULL
A79: A24261921654 | B79: 2025 MMPS Template | C79: SUBMISSIONCONTACT | D79: 16 | E79: Sales Compensation Contact Name | F79: N | G79: Ms. Lucy LaRue | H79: Y | I79: 176 | J79: NULL | K79: NULL | L79: NULL | M79: CHAR | N79: SALES_CONTACT_NAME | O79: DDE013 | P79: USE | Q79: L | R79: United States | S79: USA | T79: USA | U79: 250 | V79: 0 | W79: W | Y79: NULL | Z79: S | AA79: Y | AB79: Y | AC79: ~XXX~ | AD79: SALES_CONTACT_NAME | AE79: Sales Compensation Contact Name | AF79: Sales Compensation Contact Name | AH79: Ms. Lucy LaRue | AI79: NULL | AK79: NULL
A80: A24261921654 | B80: 2025 MMPS Template | C80: SUBMISSIONCONTACT | D80: 17 | E80: Sales Compensation Contact Title | F80: N | G80: Sales Comp Contact | H80: Y | I80: 177 | J80: NULL | K80: NULL | L80: NULL | M80: CHAR | N80: SALES_CONTACT_TITLE | O80: DDE014 | P80: USE | Q80: L | R80: United States | S80: USA | T80: USA | U80: 250 | V80: 0 | W80: W | Y80: NULL | Z80: S | AA80: Y | AB80: Y | AC80: ~XXX~ | AD80: SALES_CONTACT_TITLE | AE80: Sales Compensation Contact Title | AF80: Sales Compensation Contact Title | AH80: Sales Comp Contact | AI80: NULL | AK80: NULL
A81: A24261921654 | B81: 2025 MMPS Template | C81: SUBMISSIONUNIT | D81: 17 | E81: Unit Net Operating Revenue Curr | F81: N | G81: NULL | H81: N | I81: 37285 | J81: 37284 | K81: 37284 | L81: C | M81: CHAR | N81: UREV_CURR | O81: DDE110 | P81: USE | Q81: L | R81: United States | S81: USA | T81: USA | U81: 12 | V81: 0 | W81: W | X81: NULL | Y81: NULL | Z81: M | AA81: Y | AB81: Y | AC81: ~XXX~ | AD81: UREV_CURR | AE81: Unit Net Operating Revenue Curr | AF81: Operating Revenue Currency | AG81: NULL | AH81: NULL | AI81: NULL | AJ81: NULL | AK81: NULL
A82: A24261921654 | B82: 2025 MMPS Template | C82: SUBMISSIONINCUMBENT | D82: 17 | E82: Department Name | F82: Y | G82: Accounting Department | H82: Y | I82: 75655 | J82: NULL | K82: NULL | L82: NULL | M82: CHAR | N82: FC_DEPT_TXT | O82: DDE495 | P82: USE | Q82: L | R82: United States | S82: USA | T82: USA | U82: 255 | V82: 0 | W82: W | X82: For validation purposes only - submit if readily available from HRIS data exports. | Y82: NULL | Z82: M | AA82: Y | AB82: Y | AC82: DSW,ADV:~CORE~CYCAR~ | AD82: FC_DEPT_TXT | AE82: Department Name | AF82: The name of the department in which the incumbent has primary responsibility. | AG82: For validation purposes only - submit if readily available from HRIS data exports. | AH82: Accounting Department | AI82: NULL | AK82: NULL
A83: A24261921654 | B83: 2025 MMPS Template | C83: SUBMISSIONCOMPANY | D83: 17 | E83: TV Network | F83: Y | G83: Y [Yes] | H83: Y | I83: 1128 | J83: NULL | K83: NULL | L83: NULL | M83: BOOL | N83: TV_NETWORK | O83: DDE067 | P83: USE | Q83: L | R83: United States | S83: USA | T83: USA | U83: 1 | V83: 0 | W83: W | X83: N-No Y-Yes | Y83: NULL | Z83: M | AA83: Y | AB83: Y | AC83: ADV:~TMG~ | AD83: TV_NETWORK | AE83: TV Network | AF83: The media industries in which the organization is involved. | AG83: N-No Y-Yes | AH83: Y [Yes] | AI83: NULL | AK83: NULL
A84: A24261921654 | B84: 2025 MMPS Template | C84: SUBMISSIONCONTACT | D84: 18 | E84: Sales Compensation Contact Phone | F84: N | G84: +1 (212) 555-1111 | H84: Y | I84: 178 | J84: NULL | K84: NULL | L84: NULL | M84: CHAR | N84: SALES_CONTACT_PHONE | O84: DDE015 | P84: USE | Q84: L | R84: United States | S84: USA | T84: USA | U84: 250 | V84: 0 | W84: W | Y84: NULL | Z84: S | AA84: Y | AB84: Y | AC84: ~XXX~ | AD84: SALES_CONTACT_PHONE | AE84: Sales Compensation Contact Phone | AF84: Sales Compensation Contact Phone | AH84: +1 (212) 555-1111 | AI84: NULL | AK84: NULL
A85: A24261921654 | B85: 2025 MMPS Template | C85: SUBMISSIONINCUMBENT | D85: 18 | E85: Organization Job Code | F85: N | G85: 20005 | H85: Y | I85: 78764 | J85: NULL | K85: NULL | L85: NULL | M85: NUM | N85: ORG_JOB_CODE | O85: DDE834 | P85: USE | Q85: L | R85: United States | S85: USA | T85: USA | U85: 8 | V85: 0 | W85: W | X85: NULL | Y85: NULL | Z85: M | AA85: Y | AB85: Y | AC85: ~XXX~ | AD85: ORG_JOB_CODE | AE85: Organization Job Code | AF85: Enter your organization's job code corresponding to the job being matched. | AG85: NULL | AH85: 20005 | AI85: NULL | AK85: NULL
A86: A24261921654 | B86: 2025 MMPS Template | C86: COMPANYDATA | D86: 18 | E86: Revenues | F86: N | G86: NULL | H86: N | I86: 122 | J86: NULL | K86: NULL | L86: NULL | M86: MON | N86: REV | O86: DDE004 | P86: USE | Q86: L | R86: United States | S86: USA | T86: USA | U86: 15 | V86: 0 | W86: W | Y86: NULL | Z86: M | AA86: N | AB86: Y | AC86: ~XXX~ | AD86: REV | AE86: Revenues | AF86: Total sales and other revenue for the organization. | AH86: NULL | AI86: NULL | AK86: NULL
A87: A24261921654 | B87: 2025 MMPS Template | C87: SUBMISSIONUNIT | D87: 18 | E87: Operating Budget | F87: N | G87: 999999999 | H87: Y | I87: 410 | J87: NULL | K87: NULL | L87: NULL | M87: MON | N87: OPR_BUDGET | O87: DDE012 | P87: USE | Q87: L | R87: United States | S87: USA | T87: USA | U87: 12 | V87: 0 | W87: W | X87: NULL | Y87: NULL | Z87: M | AA87: Y | AB87: Y | AC87: ~XXX~ | AD87: OPR_BUDGET | AE87: Operating Budget | AF87: All financial expenditures made [excluding capital expenditures] by the facility during the last fiscal year. | AG87: NULL | AH87: 999999999 | AI87: NULL | AJ87: NULL | AK87: NULL
A88: A24261921654 | B88: 2025 MMPS Template | C88: SUBMISSIONCOMPANY | D88: 19 | E88: Multiple Media Platforms | F88: Y | G88: N [No] | H88: Y | I88: 1130 | J88: NULL | K88: NULL | L88: NULL | M88: BOOL | N88: MULTI_MEDIAS | O88: DDE069 | P88: USE | Q88: L | R88: United States | S88: USA | T88: USA | U88: 1 | V88: 0 | W88: W | X88: N-No Y-Yes | Y88: NULL | Z88: M | AA88: Y | AB88: Y | AC88: ADV:~TMG~ | AD88: MULTI_MEDIAS | AE88: Multiple Media Platforms | AF88: The media industries in which the organization is involved. | AG88: N-No Y-Yes | AH88: N [No] | AI88: NULL | AK88: NULL
A89: A24261921654 | B89: 2025 MMPS Template | C89: SUBMISSIONCONTACT | D89: 19 | E89: Sales Compensation Contact E-mail | F89: N | G89: lucy.larue@example.com | H89: Y | I89: 179 | J89: NULL | K89: NULL | L89: NULL | M89: CHAR | N89: SALES_CONTACT_EMAIL | O89: DDE016 | P89: USE | Q89: L | R89: United States | S89: USA | T89: USA | U89: 250 | V89: 0 | W89: W | Y89: NULL | Z89: S | AA89: Y | AB89: Y | AC89: ~XXX~ | AD89: SALES_CONTACT_EMAIL | AE89: Sales Compensation Contact E-mail | AF89: Sales Compensation Contact E-mail | AH89: lucy.larue@example.com | AI89: NULL | AK89: NULL
A90: A24261921654 | B90: 2025 MMPS Template | C90: SUBMISSIONINCUMBENT | D90: 19 | E90: Internal Position Title | F90: Y | G90: ~CSR:Your Position Title~MM:Your Position Title Sample~EXEC:SVP, HR~SALESCOMPNA:Sales Manager~DEFAULT:Accounting Manager~ | H90: Y | I90: 24 | J90: NULL | K90: NULL | L90: NULL | M90: CHAR | N90: YOURPOSITIONTITLE | O90: YOURPOSITIONTITLE | P90: USE | Q90: L | R90: United States | S90: USA | T90: USA | U90: 250 | V90: 0 | W90: W | X90: Do not provide personally identifying information. | Y90: NULL | Z90: M | AA90: Y | AB90: Y | AC90: ADV:~CORE~CYCAR~ | AD90: YOURPOSITIONTITLE | AE90: Internal Position Title | AF90: The internal job title your organization uses for this position. | AG90: Do not provide personally identifying information. | AH90: ~CSR:Your Position Title~MM:Your Position Title Sample~EXEC:SVP, HR~SALESCOMPNA:Sales Manager~DEFAULT:Accounting Manager~ | AI90: NULL | AK90: If(IsNull(:YOURPOSITIONTITLE),null,trunc(:YOURPOSITIONTITLE,200))
A91: A24261921654 | B91: 2025 MMPS Template | C91: SUBMISSIONUNIT | D91: 19 | E91: Operating Budget Curr | F91: N | G91: NULL | H91: N | I91: 411 | J91: 410 | K91: 410 | L91: C | M91: CHAR | N91: OPR_BUDGET_CURR | O91: DDE013 | P91: USE | Q91: L | R91: United States | S91: USA | T91: USA | U91: 12 | V91: 0 | W91: W | X91: NULL | Y91: NULL | Z91: M | AA91: Y | AB91: Y | AC91: ~XXX~ | AD91: OPR_BUDGET_CURR | AE91: Operating Budget Curr | AF91: Operating Budget Currency | AG91: NULL | AH91: NULL | AI91: NULL | AJ91: NULL | AK91: NULL
A92: A24261921654 | B92: 2025 MMPS Template | C92: SUBMISSIONCOMPANY | D92: 20 | E92: TV Station | F92: Y | G92: N [No] | H92: Y | I92: 1129 | J92: NULL | K92: NULL | L92: NULL | M92: BOOL | N92: TV_STATION | O92: DDE068 | P92: USE | Q92: L | R92: United States | S92: USA | T92: USA | U92: 1 | V92: 0 | W92: W | X92: N-No Y-Yes | Y92: NULL | Z92: M | AA92: Y | AB92: Y | AC92: ADV:~TMG~ | AD92: TV_STATION | AE92: TV Station | AF92: The media industries in which the organization is involved. | AG92: N-No Y-Yes | AH92: N [No] | AI92: NULL | AK92: NULL
A93: A24261921654 | B93: 2025 MMPS Template | C93: SUBMISSIONINCUMBENT | D93: 20 | E93: Reports to Position Title | F93: N | G93: Manager of XXX | H93: Y | I93: 78763 | J93: NULL | K93: NULL | L93: NULL | M93: CHAR | N93: REPORTS_POS_TITLE | O93: DDE833 | P93: USE | Q93: L | R93: United States | S93: USA | T93: USA | U93: 25 | V93: 0 | W93: W | X93: NULL | Y93: NULL | Z93: M | AA93: Y | AB93: Y | AC93: ~XXX~ | AD93: REPORTS_POS_TITLE | AE93: Reports to Position Title | AF93: Enter the title of the person to whom this position reports to. | AG93: NULL | AH93: Manager of XXX | AI93: NULL | AK93: NULL
A94: A24261921654 | B94: 2025 MMPS Template | C94: SUBMISSIONUNIT | D94: 20 | E94: Number of Full-Time Equivalent Employees | F94: N | G94: 9999 | H94: Y | I94: 421 | J94: NULL | K94: NULL | L94: NULL | M94: NUM | N94: FTE_US | O94: DDE003 | P94: USE | Q94: L | R94: United States | S94: USA | T94: USA | U94: 9 | V94: 0 | W94: W | X94: NULL | Y94: NULL | Z94: M | AA94: Y | AB94: Y | AC94: ~XXX~ | AD94: FTE_US | AE94: Number of Full-Time Equivalent Employees | AF94: Full-Time Equivalent (FTE) Employment: The number of U.S. full-time employees plus part-time employees converted to full-time equivalents. To convert part-timers to FTEs, sum all part-time hours and divide by baseline annual hours (e.g., 40 weekly hours x 52 weeks = 2,080 annual hours). This number is then added to the number of full-time employees to give you the total number of full-time equivalent (FTE) employees. | AG94: NULL | AH94: 9999 | AI94: NULL | AJ94: NULL | AK94: NULL
A95: A24261921654 | B95: 2025 MMPS Template | C95: SUBMISSIONCONTACT | D95: 20 | E95: Long-Term Incentive Plans Contact Name | F95: N | G95: Mr. Joe Brady | H95: Y | I95: 986 | J95: NULL | K95: NULL | L95: NULL | M95: CHAR | N95: LTI_CONTACT_NAME | O95: DDE030 | P95: USE | Q95: L | R95: United States | S95: USA | T95: USA | U95: 250 | V95: 0 | W95: W | Y95: NULL | Z95: M | AA95: Y | AB95: Y | AC95: ~CORE~AERO_NA~SSO~RCE~AGRO_ZAF~MDSUK~RENEWABLE~RENEWCLUB_FRA~AERO_EMEA~AERO_BRA~HC_GCC~HC_APAC~HIGHER_EDU~CMPIF_CHN~EDU_APAC~UPSTREAM_MYS~DRILL_GLOBAL~DRILL_NAT~CL_PS_SUPPORTSTAFF_INTL~CL_HRG~ | AD95: LTI_CONTACT_NAME | AE95: Long-Term Incentive Plans Contact Name | AF95: Long-Term Incentive Plans Contact Name | AH95: Mr. Joe Brady | AI95: NULL | AK95: NULL
A96: A24261921654 | B96: 2025 MMPS Template | C96: SUBMISSIONUNIT | D96: 21 | E96: Number of Beds | F96: N | G96: 100 | H96: Y | I96: 37278 | J96: NULL | K96: NULL | L96: NULL | M96: NUM | N96: BEDS | O96: DDE103 | P96: USE | Q96: L | R96: United States | S96: USA | T96: USA | U96: 9 | V96: 0 | W96: W | X96: If no licensed beds, enter "0". | Y96: NULL | Z96: M | AA96: Y | AB96: Y | AC96: ~XXX~ | AD96: BEDS | AE96: Number of Beds | AF96: Number of Licensed Beds at the location being reported. | AG96: If no licensed beds, enter "0". | AH96: 100 | AI96: NULL | AJ96: NULL | AK96: NULL
A97: A24261921654 | B97: 2025 MMPS Template | C97: SUBMISSIONCOMPANY | D97: 21 | E97: Participating Entity Currency of Organization Elements | F97: N | G97: ~NA:USD [United States Dollar]~DEFAULT:GBP [United Kingdom Pound]~APAC:JPY [Japan Yen]~LATAM:BRL [Brazil Real]~CHINA:CNY [China Yuan Renminbi]~EDUCATION:MYR [Malaysia Ringgit]~ | H97: Y | I97: 34982 | J97: NULL | K97: NULL | L97: NULL | M97: PICK | N97: ENTITY_CURR | O97: DDE191 | P97: USE | Q97: L | R97: United States | S97: USA | T97: USA | U97: 5 | V97: 0 | W97: W | X97: Refer to the Country Codes tab. | Y97: NULL | Z97: M | AA97: Y | AB97: Y | AC97: INT:~CORE~ | AD97: ENTITY_CURR | AE97: Participating Entity Currency of Organization Elements | AF97: The currency code for all Participating Entity elements (e.g., Annual Revenue). | AG97: Refer to the Country Codes tab. | AH97: ~NA:USD [United States Dollar]~DEFAULT:GBP [United Kingdom Pound]~APAC:JPY [Japan Yen]~LATAM:BRL [Brazil Real]~CHINA:CNY [China Yuan Renminbi]~EDUCATION:MYR [Malaysia Ringgit]~ | AI97: NULL | AK97: NULL
A98: A24261921654 | B98: 2025 MMPS Template | C98: SUBMISSIONCONTACT | D98: 21 | E98: Long-Term Incentive Plans Contact Title | F98: N | G98: Long Term Contact | H98: Y | I98: 987 | J98: NULL | K98: NULL | L98: NULL | M98: CHAR | N98: LTI_CONTACT_TITLE | O98: DDE031 | P98: USE | Q98: L | R98: United States | S98: USA | T98: USA | U98: 250 | V98: 0 | W98: W | Y98: NULL | Z98: M | AA98: Y | AB98: Y | AC98: ~CORE~AERO_NA~SSO~RCE~AGRO_ZAF~MDSUK~RENEWABLE~RENEWCLUB_FRA~AERO_EMEA~AERO_BRA~HC_GCC~HC_APAC~HIGHER_EDU~CMPIF_CHN~EDU_APAC~UPSTREAM_MYS~DRILL_GLOBAL~DRILL_NAT~CL_PS_SUPPORTSTAFF_INTL~CL_HRG~ | AD98: LTI_CONTACT_TITLE | AE98: Long-Term Incentive Plans Contact Title | AF98: Long-Term Incentive Plans Contact Title | AH98: Long Term Contact | AI98: NULL | AK98: NULL
A99: A24261921654 | B99: 2025 MMPS Template | C99: SUBMISSIONINCUMBENT | D99: 21 | E99: Internal Grade/Level/Band | F99: Y | G99: ~CSR:Your Grade~DEFAULT:AA~ | H99: Y | I99: 238 | J99: NULL | K99: NULL | L99: NULL | M99: CHAR | N99: GRADE | O99: DDE137 | P99: USE | Q99: L | R99: United States | S99: USA | T99: USA | U99: 100 | V99: 0 | W99: W | X99: Values can be alpha or numeric. If an incumbent is not assigned to a grade/level or the organization does not use grades or levels this field should be left blank. | Y99: NULL | Z99: M | AA99: Y | AB99: Y | AC99: ADV:~CORE~AERO_NA~SSO~RCE~AGRO_ZAF~MDSUK~RENEWABLE~RENEWCLUB_FRA~AERO_EMEA~AERO_BRA~HC_GCC~HC_APAC~HIGHER_EDU~CMPIF_CHN~EDU_APAC~UPSTREAM_MYS~DRILL_GLOBAL~DRILL_NAT~LEGAL_FEE_EARNERS~CL_PS_SUPPORTSTAFF_INTL~CL_HRG~PSAR~CYCAR~ | AD99: GRADE | AE99: Internal Grade/Level/Band | AF99: The internal grade/level/band your organization uses for this position. | AG99: Values can be alpha or numeric. If an incumbent is not assigned to a grade/level or the organization does not use grades or levels this field should be left blank. | AH99: ~CSR:Your Grade~DEFAULT:AA~ | AI99: NULL | AK99: If(IsNull(:GRADE),null,trunc(:GRADE,100))
A100: A24261921654 | B100: 2025 MMPS Template | C100: SUBMISSIONCONTACT | D100: 22 | E100: Long-Term Incentive Plans Contact Phone | F100: N | G100: +1 (212) 555-1111 | H100: Y | I100: 988 | J100: NULL | K100: NULL | L100: NULL | M100: CHAR | N100: LTI_CONTACT_PHONE | O100: DDE032 | P100: USE | Q100: L | R100: United States | S100: USA | T100: USA | U100: 250 | V100: 0 | W100: W | Y100: NULL | Z100: M | AA100: Y | AB100: Y | AC100: ~CORE~AERO_NA~SSO~RCE~AGRO_ZAF~MDSUK~RENEWABLE~RENEWCLUB_FRA~AERO_EMEA~AERO_BRA~HC_GCC~HC_APAC~HIGHER_EDU~CMPIF_CHN~EDU_APAC~UPSTREAM_MYS~DRILL_GLOBAL~DRILL_NAT~CL_PS_SUPPORTSTAFF_INTL~CL_HRG~ | AD100: LTI_CONTACT_PHONE | AE100: Long-Term Incentive Plans Contact Phone | AF100: Long-Term Incentive Plans Contact Phone | AH100: +1 (212) 555-1111 | AI100: NULL | AK100: NULL
...

Sheet CPMIF
A1: versionid | B1: versionname | C1: tablename | D1: sequence | E1: elementname | F1: turnaroundind | G1: sampledata | H1: exportind | I1: elementid | J1: parentelementid | K1: parentelementid | L1: relationshiptype | M1: elementtype | N1: fieldname | O1: columnname | P1: languagecode | Q1: ddetype | R1: countrydesc | S1: countrycode | T1: regioncode | U1: elementlength | V1: elementprecision | W1: collectionunits | X1: guidelines | Y1: csfieldname | Z1: colusage | AA1: ascentnullableind | AB1: nullableind | AC1: note | AD1: elementname | AE1: elementdesc | AF1: guidelines | AG1: sampledata | AH1: excelformula | AI1: expression | AJ1: loadrule
A2: A24149240511 | B2: 2025 Capital Market Project Investment and Financing Compensation Survey - China | C2: SUBMISSIONUNIT | D2: 1 | E2: Unit Number | F2: Y | G2: 1 | H2: N | I2: 10 | J2: NULL | K2: NULL | L2: NULL | M2: CHAR | N2: UNITNUM | O2: UNITNUM | P2: USE | Q2: L | R2: China | S2: CHN | T2: APC | U2: 12 | V2: 0 | W2: W | X2: Enter a unique three-digit code (e.g., 001, 002) to identify each unit. Unit numbers will be assigned to the corresponding incumbent in these units in the Incumbent Data worksheet. | Y2: NULL | Z2: M | AA2: N | AB2: N | AC2: HID:~CORE~AERO_NA~SSO~RCE~AGRO_ZAF~MDSUK~YOUNGGRAD~MFG_LATAM~RENEWABLE~RENEWCLUB_FRA~AERO_EMEA~AERO_BRA~HC_GCC~HC_APAC~HIGHER_EDU~CMPIF_CHN~EDU_APAC~UPSTREAM_MYS~LEGAL_FEE_EARNERS~CL_PS_SUPPORTSTAFF_INTL~CL_HRG~ | AD2: Unit Number | AE2: The unit number for the incumbent's unit. | AF2: Enter a unique three-digit code (e.g., 001, 002) to identify each unit. Unit numbers will be assigned to the corresponding incumbent in these units in the Incumbent Data worksheet. | AG2: 1 | AH2: NULL | AJ2: NULL
A3: A24149240511 | B3: 2025 Capital Market Project Investment and Financing Compensation Survey - China | C3: SUBMISSIONINCUMBENT | D3: 1 | E3: Country Code | F3: Y | G3: JPN | H3: Y | I3: 14 | J3: NULL | K3: NULL | L3: NULL | M3: CHAR | N3: COUNTRYCODE | O3: COUNTRYCODE | P3: USE | Q3: L | R3: China | S3: CHN | T3: APC | U3: 5 | V3: 0 | W3: W | X3: Refer to the Country Codes tab. | Y3: NULL | Z3: M | AA3: N | AB3: N | AC3: INT:~CORE~AERO_NA~SSO~RCE~AGRO_ZAF~MDSUK~YOUNGGRAD~MFG_LATAM~RENEWABLE~RENEWCLUB_FRA~AERO_EMEA~AERO_BRA~HC_GCC~HC_APAC~HIGHER_EDU~CMPIF_CHN~EDU_APAC~UPSTREAM_MYS~DRILL_GLOBAL~DRILL_NAT~LEGAL_FEE_EARNERS~CL_PS_SUPPORTSTAFF_INTL~CL_HRG~PSAR~INT~ | AD3: Country Code | AE3: The country code of the primary office to which they are assigned. | AF3: Refer to the Country Codes tab. | AG3: JPN | AH3: NULL | AJ3: If(:COUNTRYCODE="xx",null,Trim(Upper(:COUNTRYCODE)))
A4: A24149240511 | B4: 2025 Capital Market Project Investment and Financing Compensation Survey - China | C4: SUBMISSIONGRANT | D4: 1 | E4: Case Number | F4: N | G4: NULL | H4: N | I4: 22 | J4: NULL | K4: NULL | L4: NULL | M4: CHAR | N4: CASEID | O4: CASEID | P4: USE | Q4: L | R4: China | S4: CHN | T4: APC | U4: 7 | V4: 0 | W4: W | Y4: NULL | Z4: M | AA4: N | AB4: N | AC4: ~CORE~AERO_NA~;HID:RCE~AGRO_ZAF~MDSUK~YOUNGGRAD~SSO~MFG_LATAM~RENEWABLE~RENEWCLUB_FRA~AERO_EMEA~AERO_BRA~HC_GCC~HC_APAC~HIGHER_EDU~CMPIF_CHN~EDU_APAC~UPSTREAM_MYS~DRILL_GLOBAL~DRIL_NAT~LEGAL_FEE_EARNERS~CL_PS_SUPPORTSTAFF_INTL~ | AD4: Case Number | AE4: Seven-digit case number to uniquely identify each incumbent. | AG4: NULL | AH4: NULL | AJ4: If(:CASEID="XXXX",null,LPad(:CASEID,6,"0"))
A5: A24149240511 | B5: 2025 Capital Market Project Investment and Financing Compensation Survey - China | C5: SUBMISSIONCOMPANY | D5: 1 | E5: Participating Entity Name | F5: N | G5: Your Company Name | H5: Y | I5: 566 | J5: NULL | K5: NULL | L5: NULL | M5: CHAR | N5: COMPANY_NAME | O5: DDE038 | P5: USE | Q5: L | R5: China | S5: CHN | T5: APC | U5: 255 | V5: 0 | W5: W | X5: NULL | Y5: NULL | Z5: M | AA5: Y | AB5: Y | AC5: ~CORE~AERO_NA~SSO~RCE~AGRO_ZAF~MDSUK~YOUNGGRAD~MFG_LATAM~RENEWABLE~RENEWCLUB_FRA~AERO_EMEA~AERO_BRA~HC_GCC~HC_APAC~HIGHER_EDU~CMPIF_CHN~EDU_APAC~UPSTREAM_MYS~DRILL_GLOBAL~DRILL_NAT~LEGAL_FEE_EARNERS~CL_PS_SUPPORTSTAFF_INTL~CL_HRG~PSAR~INT~ | AD5: Participating Entity Name | AE5: The name of your organization. | AF5: NULL | AG5: Your Company Name | AH5: NULL | AJ5: NULL
A6: A24149240511 | B6: 2025 Capital Market Project Investment and Financing Compensation Survey - China | C6: SUBMISSIONCONTACT | D6: 1 | E6: Cash Compensation Contact Name | F6: N | G6: Mr. Mike Smith | H6: Y | I6: 982 | J6: NULL | K6: NULL | L6: NULL | M6: CHAR | N6: CASH_CONTACT_NAME | O6: DDE026 | P6: USE | Q6: L | R6: China | S6: CHN | T6: APC | U6: 250 | V6: 0 | W6: W | Y6: NULL | Z6: M | AA6: Y | AB6: Y | AC6: ~CORE~AERO_NA~SSO~RCE~AGRO_ZAF~MDSUK~YOUNGGRAD~MFG_LATAM~RENEWABLE~RENEWCLUB_FRA~AERO_EMEA~AERO_BRA~HC_GCC~HC_APAC~HIGHER_EDU~CMPIF_CHN~EDU_APAC~UPSTREAM_MYS~DRILL_GLOBAL~DRILL_NAT~LEGAL_FEE_EARNERS~CL_PS_SUPPORTSTAFF_INTL~CL_HRG~PSAR~INT~ | AD6: Cash Compensation Contact Name | AE6: Cash Compensation Contact Name | AG6: Mr. Mike Smith | AH6: NULL | AJ6: NULL
A7: A24149240511 | B7: 2025 Capital Market Project Investment and Financing Compensation Survey - China | C7: SUBMISSIONGRANT | D7: 2 | E7: Long-Term Incentive Plan Type | F7: N | G7: PP | H7: Y | I7: 83 | J7: NULL | K7: NULL | L7: NULL | M7: PICK | N7: PLANTYPE | O7: PLANTYPE | P7: USE | Q7: L | R7: China | S7: CHN | T7: APC | U7: 5 | V7: 0 | W7: W | X7: PP-Performance Plan Awards: Performance Plan Awards are contingent grants of cash or stock that are earned in whole or in part according to the degree of achievement of performance goals over a defined period (usually three years). RS-Restricted Stock/Stock Units: Restricted Stock/Stock Units are grants of stock or stock units at no or nominal cost. The restrictions and risk of forfeiture lapse with continued employment over a period of years. If vesting also includes a performance condition, such condition is considered to be nominal with a high likelihood of being attained. Dividends or dividend equivalents may be paid or accrued during the restricted period. SO-Stock Options/SARs: Stock Options are rights to purchase a fixed number of shares of a company's stock, at a stated price for a specified period of time. Stock Appreciation Rights (SARs) are rights to receive payment equal in value to the appreciation on a share of stock between the date on which the SAR was granted and the date on which the employee exercises his/her appreciation rights. | Y7: NULL | Z7: M | AA7: Y | AB7: Y | AC7: INT:~CORE~AERO_NA~SSO~RCE~AGRO_ZAF~MDSUK~MFG_LATAM~RENEWABLE~RENEWCLUB_FRA~AERO_EMEA~AERO_BRA~HC_GCC~HC_APAC~HIGHER_EDU~CMPIF_CHN~EDU_APAC~UPSTREAM_MYS~DRILL_GLOBAL~DRILL_NAT~CL_PS_SUPPORTSTAFF_INTL~CL_HRG~;HID:~PSAR~INT~ | AD7: Long-Term Incentive Plan Type | AE7: Type of long-term grant data being reported. | AF7: PP-Performance Plan Awards: Performance Plan Awards are contingent grants of cash or stock that are earned in whole or in part according to the degree of achievement of performance goals over a defined period (usually three years). RS-Restricted Stock/Stock Units: Restricted Stock/Stock Units are grants of stock or stock units at no or nominal cost. The restrictions and risk of forfeiture lapse with continued employment over a period of years. If vesting also includes a performance condition, such condition is considered to be nominal with a high likelihood of being attained. Dividends or dividend equivalents may be paid or accrued during the restricted period. SO-Stock Options/SARs: Stock Options are rights to purchase a fixed number of shares of a company's stock, at a stated price for a specified period of time. Stock Appreciation Rights (SARs) are rights to receive payment equal in value to the appreciation on a share of stock between the date on which the SAR was granted and the date on which the employee exercises his/her appreciation rights. | AG7: PP | AH7: NULL | AJ7: UPPER(TRIM(:PLANTYPE))
A8: A24149240511 | B8: 2025 Capital Market Project Investment and Financing Compensation Survey - China | C8: SUBMISSIONCOMPANY | D8: 2 | E8: Participating Entity Country | F8: Y | G8: JPN [Japan] | H8: Y | I8: 35000 | J8: NULL | K8: NULL | L8: NULL | M8: PICK | N8: ISO3 | O8: DDE207 | P8: USE | Q8: L | R8: China | S8: CHN | T8: APC | U8: 5 | V8: 0 | W8: W | X8: Refer to the Country Codes tab. | Y8: NULL | Z8: M | AA8: N | AB8: Y | AC8: DSW:~CORE~AERO_NA~SSO~RCE~AGRO_ZAF~MDSUK~YOUNGGRAD~MFG_LATAM~RENEWABLE~RENEWCLUB_FRA~AERO_EMEA~AERO_BRA~HC_GCC~HC_APAC~HIGHER_EDU~CMPIF_CHN~EDU_APAC~UPSTREAM_MYS~DRILL_GLOBAL~DRILL_NAT~LEGAL_FEE_EARNERS~CL_PS_SUPPORTSTAFF_INTL~CL_HRG~PSAR~ | AD8: Participating Entity Country | AE8: The country where the participating entity is based/headquartered. | AF8: Refer to the Country Codes tab. | AG8: JPN [Japan] | AH8: NULL | AJ8: NULL
A9: A24149240511 | B9: 2025 Capital Market Project Investment and Financing Compensation Survey - China | C9: SUBMISSIONUNIT | D9: 2 | E9: Comments | F9: N | G9: NULL | H9: N | I9: 80 | J9: NULL | K9: NULL | L9: NULL | M9: CHAR | N9: COMMENTS | O9: COMMENTS | P9: USE | Q9: L | R9: China | S9: CHN | T9: APC | U9: 255 | V9: 0 | W9: W | X9: NULL | Y9: NULL | Z9: M | AA9: Y | AB9: Y | AC9: ~CORE~AERO_NA~SSO~RCE~AGRO_ZAF~MDSUK~YOUNGGRAD~MFG_LATAM~RENEWABLE~RENEWCLUB_FRA~AERO_EMEA~AERO_BRA~HC_GCC~HC_APAC~HIGHER_EDU~CMPIF_CHN~EDU_APAC~UPSTREAM_MYS~DRILL_GLOBAL~DRILL_NAT~LEGAL_FEE_EARNERS~CL_PS_SUPPORTSTAFF_INTL~PSAR~INT~ | AD9: Comments | AE9: Unit Comments | AF9: NULL | AG9: NULL | AH9: NULL | AJ9: NULL
A10: A24149240511 | B10: 2025 Capital Market Project Investment and Financing Compensation Survey - China | C10: SUBMISSIONCONTACT | D10: 2 | E10: Cash Compensation Contact Title | F10: N | G10: Cash Contact | H10: Y | I10: 983 | J10: NULL | K10: NULL | L10: NULL | M10: CHAR | N10: CASH_CONTACT_TITLE | O10: DDE027 | P10: USE | Q10: L | R10: China | S10: CHN | T10: APC | U10: 250 | V10: 0 | W10: W | Y10: NULL | Z10: M | AA10: Y | AB10: Y | AC10: ~CORE~AERO_NA~SSO~RCE~AGRO_ZAF~MDSUK~YOUNGGRAD~MFG_LATAM~RENEWABLE~RENEWCLUB_FRA~AERO_EMEA~AERO_BRA~HC_GCC~HC_APAC~HIGHER_EDU~CMPIF_CHN~EDU_APAC~UPSTREAM_MYS~DRILL_GLOBAL~DRILL_NAT~LEGAL_FEE_EARNERS~CL_PS_SUPPORTSTAFF_INTL~CL_HRG~PSAR~INT~ | AD10: Cash Compensation Contact Title | AE10: Cash Compensation Contact Title | AG10: Cash Contact | AH10: NULL | AJ10: NULL
A11: A24149240511 | B11: 2025 Capital Market Project Investment and Financing Compensation Survey - China | C11: SUBMISSIONINCUMBENT | D11: 2 | E11: Case Number | F11: Y | G11: 1 | H11: N | I11: 12 | J11: NULL | K11: NULL | L11: NULL | M11: CHAR | N11: CASEID | O11: CASEID | P11: USE | Q11: L | R11: China | S11: CHN | T11: APC | U11: 7 | V11: 0 | W11: W | X11: Number the cases starting with 0000001. | Y11: NULL | Z11: M | AA11: N | AB11: N | AC11: ADV,DSW:~CORE~AERO_NA~RENEWABLE~RENEWCLUB_FRA~RCE~MDSUK~AERO_EMEA~AERO_BRA~CL_HRG~PSAR~;HID:~AGRO_ZAF~YOUNGGRAD~SSO~MFG_LATAM~HC_GCC~HC_APAC~HIGHER_EDU~CMPIF_CHN~EDU_APAC~UPSTREAM_MYS~DRILL_GLOBAL~DRILL_NAT~LEGAL_FEE_EARNERS~CL_PS_SUPPORTSTAFF_INTL~ | AD11: Case Number | AE11: Seven-digit case number to uniquely identify each incumbent. | AF11: Number the cases starting with 0000001. | AG11: 1 | AH11: NULL | AJ11: If(:CASEID="XXXX",null,LPad(:CASEID,6,"0"))
A12: A24149240511 | B12: 2025 Capital Market Project Investment and Financing Compensation Survey - China | C12: SUBMISSIONGRANT | D12: 3 | E12: Long-Term Incentive Plan Number | F12: N | G12: PP01 | H12: N | I12: 23 | J12: NULL | K12: NULL | L12: NULL | M12: CHAR | N12: PLANCODE | O12: PLANCODE | P12: USE | Q12: L | R12: China | S12: CHN | T12: APC | U12: 12 | V12: 0 | W12: W | X12: If under the same plan different incumbents have different vesting arrangements, report each plan separately. For example, if a performance cash plan has a TSR performance condition applicable to board member and an EPS performance condition applicable to all other incumbents, code each as a separate plan. | Y12: NULL | Z12: M | AA12: Y | AB12: Y | AC12: INT:~CORE~AERO_NA~RENEWABLE~AERO_EMEA~AERO_BRA~MDSUK~CL_HRG~;HID:~RCE~AGRO_ZAF~YOUNGGRAD~SSO~MFG_LATAM~HC_GCC~HC_APAC~HIGHER_EDU~CMPIF_CHN~EDU_APAC~UPSTREAM_MYS~RENEWCLUB_FRA~DRILL_GLOBAL~DRILL_NAT~CL_PS_SUPPORTSTAFF_INTL~ | AD12: Long-Term Incentive Plan Number | AE12: The plan number is located on each plan type worksheet on the data submission spreadsheet and is required for each grant. The Long-Term Plan Number (e.g., PP01) ties the shares granted with the plan data. | AF12: If under the same plan different incumbents have different vesting arrangements, report each plan separately. For example, if a performance cash plan has a TSR performance condition applicable to board member and an EPS performance condition applicable to all other incumbents, code each as a separate plan. | AG12: PP01 | AH12: NULL | AJ12: TRIM(UPPER(:PLANCODE))
A13: A24149240511 | B13: 2025 Capital Market Project Investment and Financing Compensation Survey - China | C13: SUBMISSIONCONTACT | D13: 3 | E13: Cash Compensation Contact Phone | F13: N | G13: +1 (212) 555-1111 | H13: Y | I13: 984 | J13: NULL | K13: NULL | L13: NULL | M13: CHAR | N13: CASH_CONTACT_PHONE | O13: DDE028 | P13: USE | Q13: L | R13: China | S13: CHN | T13: APC | U13: 250 | V13: 0 | W13: W | Y13: NULL | Z13: M | AA13: Y | AB13: Y | AC13: ~CORE~AERO_NA~SSO~RCE~AGRO_ZAF~MDSUK~YOUNGGRAD~MFG_LATAM~RENEWABLE~RENEWCLUB_FRA~AERO_EMEA~AERO_BRA~HC_GCC~HC_APAC~HIGHER_EDU~CMPIF_CHN~EDU_APAC~UPSTREAM_MYS~DRILL_GLOBAL~DRILL_NAT~LEGAL_FEE_EARNERS~CL_PS_SUPPORTSTAFF_INTL~CL_HRG~PSAR~INT~ | AD13: Cash Compensation Contact Phone | AE13: Cash Compensation Contact Phone | AG13: +1 (212) 555-1111 | AH13: NULL | AJ13: NULL
A14: A24149240511 | B14: 2025 Capital Market Project Investment and Financing Compensation Survey - China | C14: SUBMISSIONCOMPANY | D14: 3 | E14: Participating Entity Currency of Organization Elements | F14: N | G14: JPY [Japan Yen] | H14: Y | I14: 34982 | J14: NULL | K14: NULL | L14: NULL | M14: PICK | N14: ENTITY_CURR | O14: DDE191 | P14: USE | Q14: L | R14: China | S14: CHN | T14: APC | U14: 5 | V14: 0 | W14: W | X14: Refer to the Country Codes tab. | Y14: NULL | Z14: M | AA14: Y | AB14: Y | AC14: INT:~CORE~AERO_NA~SSO~RCE~AGRO_ZAF~MDSUK~YOUNGGRAD~MFG_LATAM~RENEWABLE~RENEWCLUB_FRA~AERO_EMEA~AERO_BRA~HC_GCC~HC_APAC~HIGHER_EDU~CMPIF_CHN~EDU_APAC~UPSTREAM_MYS~DRILL_GLOBAL~DRILL_NAT~LEGAL_FEE_EARNERS~CL_PS_SUPPORTSTAFF_INTL~CL_HRG~PSAR~INT~ | AD14: Participating Entity Currency of Organization Elements | AE14: The currency code for all Participating Entity elements (e.g., Annual Revenue). | AF14: Refer to the Country Codes tab. | AG14: JPY [Japan Yen] | AH14: NULL | AJ14: NULL
A15: A24149240511 | B15: 2025 Capital Market Project Investment and Financing Compensation Survey - China | C15: SUBMISSIONINCUMBENT | D15: 3 | E15: Area/City Code | F15: Y | G15: JP001 | H15: Y | I15: 7966 | J15: NULL | K15: NULL | L15: NULL | M15: PICK | N15: AREACODE | O15: DDE236 | P15: USE | Q15: L | R15: China | S15: CHN | T15: APC | U15: 5 | V15: 0 | W15: W | X15: Refer to the Country Codes tab. For remote employees, report their nominal office or location to which they are assigned For all regions except Moscow, Moscow region, Saint-Petersburg and Leningrad region apply the same area/city code to incumbents based in regional capital city and outside regional capital city within a region (e.g., RU033 for Novosibirsk and Novosibirsk region/oblast). For the cities of and regions around Moscow and Saint-Petersburg, more granular codes are available and should be applied as follows: - Apply RU001 to incumbents based in Moscow - Apply RU002 to incumbents based in Moscow region/oblast - Apply RU003 to incumbents based in Saint-Petersburg - Apply RU004 to incumbents based in Leningrad region/oblast | Y15: NULL | Z15: M | AA15: Y | AB15: Y | AC15: ADV:~CORE_EMEA~CORE_LATAM~SSO~RCE~AGRO_ZAF~MDSUK~YOUNGGRAD~MFG_LATAM~RENEWABLE~RENEWCLUB_FRA~AERO_EMEA~AERO_BRA~HC_GCC~HIGHER_EDU~DRILL_GLOBAL~DRILL_NAT_INTL~LEGAL_FEE_EARNERS~CL_PS_SUPPORTSTAFF_INTL~CL_HRG~;PUB:~PSAR~;SCOPE:~CORE_APAC~CMPIF_CHN~EDU_APAC~UPSTREAM_MYS~SSO_APAC~RCE_APAC~RENEWABLE_APAC~HC_APAC~ | AD15: Area/City Code | AE15: The area/city code of the primary office to which the incumbent is assigned. | AF15: Refer to the Country Codes tab. For remote employees, report their nominal office or location to which they are assigned For all regions except Moscow, Moscow region, Saint-Petersburg and Leningrad region apply the same area/city code to incumbents based in regional capital city and outside regional capital city within a region (e.g., RU033 for Novosibirsk and Novosibirsk region/oblast). For the cities of and regions around Moscow and Saint-Petersburg, more granular codes are available and should be applied as follows: - Apply RU001 to incumbents based in Moscow - Apply RU002 to incumbents based in Moscow region/oblast - Apply RU003 to incumbents based in Saint-Petersburg - Apply RU004 to incumbents based in Leningrad region/oblast | AG15: JP001 | AH15: NULL | AJ15: upper(trim(:AREACODE))
A16: A24149240511 | B16: 2025 Capital Market Project Investment and Financing Compensation Survey - China | C16: SUBMISSIONCONTACT | D16: 4 | E16: Cash Compensation Contact E-mail | F16: N | G16: mike.smith@example.com | H16: Y | I16: 985 | J16: NULL | K16: NULL | L16: NULL | M16: CHAR | N16: CASH_CONTACT_EMAIL | O16: DDE029 | P16: USE | Q16: L | R16: China | S16: CHN | T16: APC | U16: 250 | V16: 0 | W16: W | Y16: NULL | Z16: M | AA16: Y | AB16: Y | AC16: ~CORE~AERO_NA~SSO~RCE~AGRO_ZAF~MDSUK~YOUNGGRAD~MFG_LATAM~RENEWABLE~RENEWCLUB_FRA~AERO_EMEA~AERO_BRA~HC_GCC~HC_APAC~HIGHER_EDU~CMPIF_CHN~EDU_APAC~UPSTREAM_MYS~DRILL_GLOBAL~DRILL_NAT~LEGAL_FEE_EARNERS~CL_PS_SUPPORTSTAFF_INTL~CL_HRG~PSAR~INT~ | AD16: Cash Compensation Contact E-mail | AE16: Cash Compensation Contact E-mail | AG16: mike.smith@example.com | AH16: NULL | AJ16: NULL
A17: A24149240511 | B17: 2025 Capital Market Project Investment and Financing Compensation Survey - China | C17: SUBMISSIONCOMPANY | D17: 4 | E17: Participating Entity Annual Revenue | F17: N | G17: 76000000 | H17: Y | I17: 172 | J17: NULL | K17: NULL | L17: NULL | M17: MON | N17: ENTITY_REV | O17: DDE005 | P17: USE | Q17: L | R17: China | S17: CHN | T17: APC | U17: 15 | V17: 0 | W17: W | X17: For the headquarter country, enter global revenue. For banks this is usually net interest income plus (where relevant/quantifiable) other revenue such as investment and fee income. For insurance companies, this is usually gross premium income (a.k.a. "gross written premiums") plus (where relevant/quantifiable) other revenue such as investment and fee income. Do not deduct premiums ceded to reinsurers for de-risking purposes. Note: enter all financial data in whole numbers. | Y17: NULL | Z17: M | AA17: Y | AB17: Y | AC17: INT:~CORE_APAC~CORE_EMEA~CORE_LATAM~SSO~RCE~AGRO_ZAF~RENEWABLE~RENEWCLUB_FRA~AERO_EMEA~AERO_BRA~HC_GCC~HC_APAC~HIGHER_EDU~CMPIF_CHN~EDU_APAC~UPSTREAM_MYS~DRILL_GLOBAL~DRILL_NAT_INTL~DRILL_NAT_NA~CL_PS_SUPPORTSTAFF_INTL~CL_HRG~;ADV:~CORE_NA~AERO_NA~MDSUK~YOUNGGRAD~MFG_LATAM~LEGAL_FEE_EARNERS~PSAR~INT~ | AD17: Participating Entity Annual Revenue | AE17: The participating entity's total annual gross revenue for the most recent fiscal year. | AF17: For the headquarter country, enter global revenue. For banks this is usually net interest income plus (where relevant/quantifiable) other revenue such as investment and fee income. For insurance companies, this is usually gross premium income (a.k.a. "gross written premiums") plus (where relevant/quantifiable) other revenue such as investment and fee income. Do not deduct premiums ceded to reinsurers for de-risking purposes. Note: enter all financial data in whole numbers. | AG17: 76000000 | AH17: NULL | AJ17: NULL
A18: A24149240511 | B18: 2025 Capital Market Project Investment and Financing Compensation Survey - China | C18: SUBMISSIONGRANT | D18: 4 | E18: Grant Date | F18: N | G18: 44929 | H18: Y | I18: 196 | J18: NULL | K18: NULL | L18: NULL | M18: DATE | N18: GRANT_DATE | O18: DDE001 | P18: USE | Q18: L | R18: China | S18: CHN | T18: APC | U18: 8 | V18: 0 | W18: W | X18: Provide date of grants in the last 12 months. Enter the date in your normal date format (DD/MM/YY or MM/DD/YY depending on user default). For special grants provided in lieu of annual grants and for multi-year or mega grants, please enter your most recent grant which could be more than 12 months ago. | Y18: NULL | Z18: M | AA18: Y | AB18: Y | AC18: DSW,INT:~CORE~AERO_NA~SSO~RCE~AGRO_ZAF~MDSUK~MFG_LATAM~RENEWABLE~RENEWCLUB_FRA~AERO_EMEA~AERO_BRA~HC_GCC~HC_APAC~HIGHER_EDU~CMPIF_CHN~EDU_APAC~UPSTREAM_MYS~DRILL_GLOBAL~DRILL_NAT~CL_PS_SUPPORTSTAFF_INTL~CL_HRG~INT~ | AD18: Grant Date | AE18: Date the grant was made. | AF18: Provide date of grants in the last 12 months. Enter the date in your normal date format (DD/MM/YY or MM/DD/YY depending on user default). For special grants provided in lieu of annual grants and for multi-year or mega grants, please enter your most recent grant which could be more than 12 months ago. | AG18: 44929 | AH18: NULL | AJ18: NULL
A19: A24149240511 | B19: 2025 Capital Market Project Investment and Financing Compensation Survey - China | C19: SUBMISSIONINCUMBENT | D19: 4 | E19: Postal/ZIP Code | F19: Y | G19: 75008 | H19: Y | I19: 246 | J19: NULL | K19: NULL | L19: NULL | M19: CHAR | N19: POSTZIPCODE | O19: DDE145 | P19: USE | Q19: L | R19: China | S19: CHN | T19: APC | U19: 12 | V19: 0 | W19: W | X19: For home based employees or equivalent, please provide the postcode of their nominal or primary office. | Y19: NULL | Z19: M | AA19: Y | AB19: Y | AC19: ~CORE_APAC~CORE_EMEA~CORE_NA~AERO_NA~CORE_BMU~SSO_APAC~SSO_EMEA~RCE_APAC~RCE_EMEA~AGRO_ZAF~MDSUK~YOUNGGRAD~RENEWABLE_APAC~RENEWABLE_EMEA~RENEWCLUB_FRA~AERO_EMEA~HC_GCC~HC_APAC~HIGHER_EDU~CMPIF_CHN~EDU_APAC~UPSTREAM_MYS~DRILL_GLOBAL~DRILL_NAT_APAC~DRILL_NAT_EMEA~DRILL_NAT_NA~LEGAL_FEE_EARNERS~CL_PS_SUPPORTSTAFF_INTL~CL_HRG~PSAR~INT~ | AD19: Postal/ZIP Code | AE19: The Postal/ZIP code for the incumbent's primary work location. | AF19: For home based employees or equivalent, please provide the postcode of their nominal or primary office. | AG19: 75008 | AH19: NULL | AJ19: Trim(:POSTZIPCODE)
A20: A24149240511 | B20: 2025 Capital Market Project Investment and Financing Compensation Survey - China | C20: SUBMISSIONINCUMBENT | D20: 5 | E20: Unique Incumbent Identifier | F20: Y | G20: 12345 | H20: Y | I20: 241 | J20: NULL | K20: NULL | L20: NULL | M20: CHAR | N20: IDENT | O20: DDE140 | P20: USE | Q20: L | R20: China | S20: CHN | T20: APC | U20: 60 | V20: 0 | W20: W | X20: Do not use personal identifying data (e.g., employee names, initials, or government ID such as Social Security or Social Insurance number). Use consistent identifiers year over year. | Y20: NULL | Z20: M | AA20: Y | AB20: Y | AC20: ADV:~CORE~AERO_NA~SSO~RCE~AGRO_ZAF~MDSUK~YOUNGGRAD~MFG_LATAM~RENEWABLE~RENEWCLUB_FRA~AERO_EMEA~AERO_BRA~HC_GCC~HC_APAC~HIGHER_EDU~CMPIF_CHN~EDU_APAC~UPSTREAM_MYS~DRILL_GLOBAL~DRILL_NAT~LEGAL_FEE_EARNERS~CL_PS_SUPPORTSTAFF_INTL~CL_HRG~PSAR~ADV~ | AD20: Unique Incumbent Identifier | AE20: Internal reference number, which is specific and unique to each individual. | AF20: Do not use personal identifying data (e.g., employee names, initials, or government ID such as Social Security or Social Insurance number). Use consistent identifiers year over year. | AG20: 12345 | AH20: NULL | AJ20: NULL
A21: A24149240511 | B21: 2025 Capital Market Project Investment and Financing Compensation Survey - China | C21: SUBMISSIONCOMPANY | D21: 5 | E21: Participating Entity Annual Revenue Curr | F21: N | G21: NULL | H21: N | I21: 173 | J21: 172 | K21: 172 | L21: C | M21: CHAR | N21: ENTITY_REV_CURR | O21: DDE006 | P21: USE | Q21: L | R21: China | S21: CHN | T21: APC | U21: 12 | V21: 0 | W21: W | X21: Note: enter all financial data in whole numbers. | Y21: NULL | Z21: M | AA21: Y | AB21: Y | AC21: ~CORE~AERO_NA~SSO~RCE~AGRO_ZAF~MDSUK~YOUNGGRAD~MFG_LATAM~RENEWABLE~RENEWCLUB_FRA~AERO_EMEA~AERO_BRA~HC_GCC~HC_APAC~HIGHER_EDU~CMPIF_CHN~EDU_APAC~UPSTREAM_MYS~LEGAL_FEE_EARNERS~CL_PS_SUPPORTSTAFF_INTL~CL_HRG~DRILL_GLOBAL~DRILL_NAT_INTL~DRILL_NAT_NA~PSAR~INT~ | AD21: Participating Entity Annual Revenue Curr | AE21: Participating Entity Annual Revenue Currency | AF21: Note: enter all financial data in whole numbers. | AG21: NULL | AH21: NULL | AJ21: NULL
A22: A24149240511 | B22: 2025 Capital Market Project Investment and Financing Compensation Survey - China | C22: SUBMISSIONCONTACT | D22: 5 | E22: Long-Term Incentive Plans Contact Name | F22: N | G22: Mr. Joe Brady | H22: Y | I22: 986 | J22: NULL | K22: NULL | L22: NULL | M22: CHAR | N22: LTI_CONTACT_NAME | O22: DDE030 | P22: USE | Q22: L | R22: China | S22: CHN | T22: APC | U22: 250 | V22: 0 | W22: W | Y22: NULL | Z22: M | AA22: Y | AB22: Y | AC22: ~CORE~AERO_NA~SSO~RCE~AGRO_ZAF~MDSUK~MFG_LATAM~RENEWABLE~RENEWCLUB_FRA~AERO_EMEA~AERO_BRA~HC_GCC~HC_APAC~HIGHER_EDU~CMPIF_CHN~EDU_APAC~UPSTREAM_MYS~DRILL_GLOBAL~DRILL_NAT~CL_PS_SUPPORTSTAFF_INTL~CL_HRG~INT~ | AD22: Long-Term Incentive Plans Contact Name | AE22: Long-Term Incentive Plans Contact Name | AG22: Mr. Joe Brady | AH22: NULL | AJ22: NULL
A23: A24149240511 | B23: 2025 Capital Market Project Investment and Financing Compensation Survey - China | C23: SUBMISSIONGRANT | D23: 5 | E23: Grant Price Currency | F23: N | G23: JPY | H23: Y | I23: 49 | J23: 48 | K23: 48 | L23: C | M23: CHAR | N23: GRANTPRICECURR | O23: GRANTPRICECURR | P23: USE | Q23: L | R23: China | S23: CHN | T23: APC | U23: 15 | V23: 0 | W23: W | X23: Enter the currency for the grant price reported. For example, enter USD for U.S. Dollars, CAD for Canadian Dollars, EUR for Euros, CHF for Swiss Francs and GBP for Pounds Sterling. For performance cash plans this is the currency in which the cash award is expressed. | Y23: NULL | Z23: M | AA23: Y | AB23: Y | AC23: ~CORE~AERO_NA~SSO~RCE~AGRO_ZAF~MDSUK~MFG_LATAM~RENEWABLE~RENEWCLUB_FRA~AERO_EMEA~AERO_BRA~HC_GCC~HC_APAC~HIGHER_EDU~CMPIF_CHN~EDU_APAC~UPSTREAM_MYS~DRILL_GLOBAL~DRILL_NAT~CL_PS_SUPPORTSTAFF_INTL~CL_HRG~INT~ | AD23: Grant Price Currency | AE23: The currency code for the grant. | AF23: Enter the currency for the grant price reported. For example, enter USD for U.S. Dollars, CAD for Canadian Dollars, EUR for Euros, CHF for Swiss Francs and GBP for Pounds Sterling. For performance cash plans this is the currency in which the cash award is expressed. | AG23: JPY | AH23: NULL | AJ23: Trim(Upper(:GRANTPRICECURR))
A24: A24149240511 | B24: 2025 Capital Market Project Investment and Financing Compensation Survey - China | C24: SUBMISSIONINCUMBENT | D24: 6 | E24: Department Name | F24: Y | G24: Accounting Department | H24: Y | I24: 75655 | J24: NULL | K24: NULL | L24: NULL | M24: CHAR | N24: FC_DEPT_TXT | O24: DDE495 | P24: USE | Q24: L | R24: China | S24: CHN | T24: APC | U24: 255 | V24: 0 | W24: W | X24: For validation purposes only - submit if readily available from HRIS data exports. | Y24: NULL | Z24: M | AA24: Y | AB24: Y | AC24: ADV:~CORE~AERO_NA~SSO~RCE~AGRO_ZAF~MDSUK~MFG_LATAM~RENEWABLE~RENEWCLUB_FRA~AERO_EMEA~AERO_BRA~HC_GCC~HC_APAC~HIGHER_EDU~CMPIF_CHN~EDU_APAC~UPSTREAM_MYS~DRILL_GLOBAL~DRILL_NAT~LEGAL_FEE_EARNERS~CL_PS_SUPPORTSTAFF_INTL~CL_HRG~PSAR~ADV~ | AD24: Department Name | AE24: The name of the department in which the incumbent has primary responsibility. | AF24: For validation purposes only - submit if readily available from HRIS data exports. | AG24: Accounting Department | AH24: NULL | AJ24: NULL
A25: A24149240511 | B25: 2025 Capital Market Project Investment and Financing Compensation Survey - China | C25: SUBMISSIONCONTACT | D25: 6 | E25: Long-Term Incentive Plans Contact Title | F25: N | G25: Long Term Contact | H25: Y | I25: 987 | J25: NULL | K25: NULL | L25: NULL | M25: CHAR | N25: LTI_CONTACT_TITLE | O25: DDE031 | P25: USE | Q25: L | R25: China | S25: CHN | T25: APC | U25: 250 | V25: 0 | W25: W | Y25: NULL | Z25: M | AA25: Y | AB25: Y | AC25: ~CORE~AERO_NA~SSO~RCE~AGRO_ZAF~MDSUK~MFG_LATAM~RENEWABLE~RENEWCLUB_FRA~AERO_EMEA~AERO_BRA~HC_GCC~HC_APAC~HIGHER_EDU~CMPIF_CHN~EDU_APAC~UPSTREAM_MYS~DRILL_GLOBAL~DRILL_NAT~CL_PS_SUPPORTSTAFF_INTL~CL_HRG~INT~ | AD25: Long-Term Incentive Plans Contact Title | AE25: Long-Term Incentive Plans Contact Title | AG25: Long Term Contact | AH25: NULL | AJ25: NULL
A26: A24149240511 | B26: 2025 Capital Market Project Investment and Financing Compensation Survey - China | C26: SUBMISSIONCOMPANY | D26: 6 | E26: Participating Entity Annual Revenue Range (USD) | F26: Y | G26: B [5M to 10M USD] | H26: Y | I26: 34984 | J26: NULL | K26: NULL | L26: NULL | M26: PICK | N26: FC_RESTIR_T | O26: DDE193 | P26: USE | Q26: L | R26: China | S26: CHN | T26: APC | U26: 5 | V26: 0 | W26: W | X26: A Less than 5M USD B 5M to 10M USD C 10M to 25M USD D 25M to 75M USD E 75M to 150M USD F 150M to 300M USD G 300M to 500M USD H 500M to 1BN USD I 1BN to 2BN USD J 2BN to 5BN USD K 5BN to 10BN USD L 10BN to 50BN USD M 50BN to 100BN USD N Greater than 100BN USD For the headquarter country, this is the range corresponding to global revenue. | Y26: NULL | Z26: M | AA26: Y | AB26: Y | AC26: ADV:~CORE~AERO_NA~SSO~RCE~AGRO_ZAF~MDSUK~YOUNGGRAD~MFG_LATAM~RENEWABLE~RENEWCLUB_FRA~AERO_EMEA~AERO_BRA~HC_GCC~HC_APAC~HIGHER_EDU~CMPIF_CHN~EDU_APAC~UPSTREAM_MYS~DRILL_GLOBAL~DRILL_NAT~LEGAL_FEE_EARNERS~CL_PS_SUPPORTSTAFF_INTL~CL_HRG~PSAR~ADV~ | AD26: Participating Entity Annual Revenue Range (USD) | AE26: The annual revenue range that best matches the country's USD annual revenue. | AF26: A Less than 5M USD B 5M to 10M USD C 10M to 25M USD D 25M to 75M USD E 75M to 150M USD F 150M to 300M USD G 300M to 500M USD H 500M to 1BN USD I 1BN to 2BN USD J 2BN to 5BN USD K 5BN to 10BN USD L 10BN to 50BN USD M 50BN to 100BN USD N Greater than 100BN USD For the headquarter country, this is the range corresponding to global revenue. | AG26: B [5M to 10M USD] | AH26: NULL | AJ26: NULL
A27: A24149240511 | B27: 2025 Capital Market Project Investment and Financing Compensation Survey - China | C27: SUBMISSIONGRANT | D27: 6 | E27: Grant Price Per Share/Unit | F27: N | G27: 50 | H27: Y | I27: 48 | J27: NULL | K27: NULL | L27: NULL | M27: MON | N27: GRANTPRICE | O27: GRANTPRICE | P27: USE | Q27: L | R27: China | S27: CHN | T27: APC | U27: 10 | V27: 2 | W27: W | X27: Round all prices to two decimal places (e.g., 12.125 should be entered as 12.13). If you are reporting a performance cash plan, co-investment shares and/or deferred bonus matching shares enter 1.00. | Y27: NULL | Z27: M | AA27: Y | AB27: Y | AC27: INT:~CORE~AERO_NA~SSO~RCE~AGRO_ZAF~MDSUK~MFG_LATAM~RENEWABLE~RENEWCLUB_FRA~AERO_EMEA~AERO_BRA~HC_GCC~HC_APAC~HIGHER_EDU~CMPIF_CHN~EDU_APAC~UPSTREAM_MYS~DRILL_GLOBAL~DRILL_NAT~CL_PS_SUPPORTSTAFF_INTL~CL_HRG~INT~ | AD27: Grant Price Per Share/Unit | AE27: Price of the share or unit at the time of grant. | AF27: Round all prices to two decimal places (e.g., 12.125 should be entered as 12.13). If you are reporting a performance cash plan, co-investment shares and/or deferred bonus matching shares enter 1.00. | AG27: 50 | AH27: NULL | AJ27: If(IsNull(:GRANTPRICE),Null,Round(:GRANTPRICE,2))
A28: A24149240511 | B28: 2025 Capital Market Project Investment and Financing Compensation Survey - China | C28: SUBMISSIONINCUMBENT | D28: 7 | E28: Internal Position Title | F28: Y | G28: Accounting Manager | H28: Y | I28: 24 | J28: NULL | K28: NULL | L28: NULL | M28: CHAR | N28: YOURPOSITIONTITLE | O28: YOURPOSITIONTITLE | P28: USE | Q28: L | R28: China | S28: CHN | T28: APC | U28: 250 | V28: 0 | W28: W | X28: Do not provide personally identifying information. | Y28: NULL | Z28: M | AA28: Y | AB28: Y | AC28: ADV:~CORE~AERO_NA~SSO~RCE~AGRO_ZAF~MDSUK~YOUNGGRAD~MFG_LATAM~RENEWABLE~RENEWCLUB_FRA~AERO_EMEA~AERO_BRA~HC_GCC~HC_APAC~HIGHER_EDU~CMPIF_CHN~EDU_APAC~UPSTREAM_MYS~DRILL_GLOBAL~DRILL_NAT~LEGAL_FEE_EARNERS~CL_PS_SUPPORTSTAFF_INTL~CL_HRG~PSAR~ADV~ | AD28: Internal Position Title | AE28: The internal job title your organization uses for this position. | AF28: Do not provide personally identifying information. | AG28: Accounting Manager | AH28: NULL | AJ28: If(IsNull(:YOURPOSITIONTITLE),null,trunc(:YOURPOSITIONTITLE,200))
A29: A24149240511 | B29: 2025 Capital Market Project Investment and Financing Compensation Survey - China | C29: SUBMISSIONGRANT | D29: 7 | E29: Accounting Value per Share/Unit of Award | F29: N | G29: 52.25 | H29: Y | I29: 100 | J29: NULL | K29: NULL | L29: NULL | M29: MON | N29: ACCOUNTING | O29: ACCOUNTING | P29: USE | Q29: L | R29: China | S29: CHN | T29: APC | U29: 12 | V29: 2 | W29: W | X29: If you are reporting a performance cash award, enter 1.00. Values should reflect the grant date accounting value per unit of the award (e.g., 52.25 for a single performance share). All values should be rounded to two decimal places (e.g., 52.2512 should be entered as 52.25). The currency should be the same as the Grant Price Currency. | Y29: NULL | Z29: M | AA29: Y | AB29: Y | AC29: INT:~CORE~AERO_NA~SSO~RCE~AGRO_ZAF~MDSUK~MFG_LATAM~RENEWABLE~RENEWCLUB_FRA~AERO_EMEA~AERO_BRA~HC_GCC~HC_APAC~HIGHER_EDU~CMPIF_CHN~EDU_APAC~UPSTREAM_MYS~DRILL_GLOBAL~DRILL_NAT~CL_PS_SUPPORTSTAFF_INTL~CL_HRG~INT~ | AD29: Accounting Value per Share/Unit of Award | AE29: For each share-based award, please enter the Fair Value of the award at the date of grant. The Fair Value is the per share value of the award at grant as calculated under International Financial Reporting Standards - IFRS(2) or the equivalent under local country GAAP. Please note that this grant-date Fair Value may be provided by your finance department. | AF29: If you are reporting a performance cash award, enter 1.00. Values should reflect the grant date accounting value per unit of the award (e.g., 52.25 for a single performance share). All values should be rounded to two decimal places (e.g., 52.2512 should be entered as 52.25). The currency should be the same as the Grant Price Currency. | AG29: 52.25 | AH29: NULL | AJ29: If(IsNull(:ACCOUNTING),Null,Round(:ACCOUNTING,2))
A30: A24149240511 | B30: 2025 Capital Market Project Investment and Financing Compensation Survey - China | C30: SUBMISSIONCONTACT | D30: 7 | E30: Long-Term Incentive Plans Contact Phone | F30: N | G30: +1 (212) 555-1111 | H30: Y | I30: 988 | J30: NULL | K30: NULL | L30: NULL | M30: CHAR | N30: LTI_CONTACT_PHONE | O30: DDE032 | P30: USE | Q30: L | R30: China | S30: CHN | T30: APC | U30: 250 | V30: 0 | W30: W | Y30: NULL | Z30: M | AA30: Y | AB30: Y | AC30: ~CORE~AERO_NA~SSO~RCE~AGRO_ZAF~MDSUK~MFG_LATAM~RENEWABLE~RENEWCLUB_FRA~AERO_EMEA~AERO_BRA~HC_GCC~HC_APAC~HIGHER_EDU~CMPIF_CHN~EDU_APAC~UPSTREAM_MYS~DRILL_GLOBAL~DRILL_NAT~CL_PS_SUPPORTSTAFF_INTL~CL_HRG~INT~ | AD30: Long-Term Incentive Plans Contact Phone | AE30: Long-Term Incentive Plans Contact Phone | AG30: +1 (212) 555-1111 | AH30: NULL | AJ30: NULL
A31: A24149240511 | B31: 2025 Capital Market Project Investment and Financing Compensation Survey - China | C31: SUBMISSIONCOMPANY | D31: 7 | E31: Participating Entity FTE Employee Range | F31: Y | G31: D [620 to 1,600] | H31: Y | I31: 34979 | J31: NULL | K31: NULL | L31: NULL | M31: PICK | N31: FC_EMPLREST_T | O31: DDE188 | P31: USE | Q31: L | R31: China | S31: CHN | T31: APC | U31: 5 | V31: 0 | W31: W | X31: To convert part-timers to FTEs, sum all part-time hours and divide by baseline annual hours (e.g., 40 weekly hours X 52 weeks = 2,080 annual hours). Add this to the number of full-time employees to calculate the total number of FTE employees. A-Under 90 B-90 to 240 C-240 to 620 D-620 to 1,600 E-1,600 to 4,100 F-4,100 to 10,600 G-10,600 to 27,500 H-27,500 to 75,000 I-75,000 to 200,000 J-Greater than 200,000 For the headquarter entity, enter global full-time equivalent (FTE) employees. | Y31: NULL | Z31: M | AA31: Y | AB31: Y | AC31: ADV:~CORE~AERO_NA~SSO~RCE~AGRO_ZAF~MDSUK~YOUNGGRAD~MFG_LATAM~RENEWABLE~RENEWCLUB_FRA~AERO_EMEA~AERO_BRA~HC_GCC~HC_APAC~HIGHER_EDU~CMPIF_CHN~EDU_APAC~UPSTREAM_MYS~UPSTREAM_MYS~DRILL_GLOBAL~DRILL_NAT~LEGAL_FEE_EARNERS~CL_PS_SUPPORTSTAFF_INTL~CL_HRG~PSAR~ADV~ | AD31: Participating Entity FTE Employee Range | AE31: The full-time equivalent (FTE) employee range that best matches the country's total FTE employees. | AF31: To convert part-timers to FTEs, sum all part-time hours and divide by baseline annual hours (e.g., 40 weekly hours X 52 weeks = 2,080 annual hours). Add this to the number of full-time employees to calculate the total number of FTE employees. A-Under 90 B-90 to 240 C-240 to 620 D-620 to 1,600 E-1,600 to 4,100 F-4,100 to 10,600 G-10,600 to 27,500 H-27,500 to 75,000 I-75,000 to 200,000 J-Greater than 200,000 For the headquarter entity, enter global full-time equivalent (FTE) employees. | AG31: D [620 to 1,600] | AH31: NULL | AJ31: NULL
A32: A24149240511 | B32: 2025 Capital Market Project Investment and Financing Compensation Survey - China | C32: SUBMISSIONCONTACT | D32: 8 | E32: Long-Term Incentive Plans Contact E-mail | F32: N | G32: joe.brady@example.com | H32: Y | I32: 989 | J32: NULL | K32: NULL | L32: NULL | M32: CHAR | N32: LTI_CONTACT_EMAIL | O32: DDE033 | P32: USE | Q32: L | R32: China | S32: CHN | T32: APC | U32: 250 | V32: 0 | W32: W | Y32: NULL | Z32: M | AA32: Y | AB32: Y | AC32: ~CORE~AERO_NA~SSO~RCE~AGRO_ZAF~MDSUK~MFG_LATAM~RENEWABLE~RENEWCLUB_FRA~AERO_EMEA~AERO_BRA~HC_GCC~HC_APAC~HIGHER_EDU~CMPIF_CHN~EDU_APAC~UPSTREAM_MYS~DRILL_GLOBAL~DRILL_NAT~CL_PS_SUPPORTSTAFF_INTL~CL_HRG~INT~ | AD32: Long-Term Incentive Plans Contact E-mail | AE32: Long-Term Incentive Plans Contact E-mail | AG32: joe.brady@example.com | AH32: NULL | AJ32: NULL
A33: A24149240511 | B33: 2025 Capital Market Project Investment and Financing Compensation Survey - China | C33: SUBMISSIONCOMPANY | D33: 8 | E33: Industry Group | F33: N | G33: NULL | H33: N | I33: NULL | J33: NULL | K33: NULL | L33: NULL | M33: PICK | N33: INDUSTRYGROUP_SIC | O33: NULL | P33: USE | Q33: C | R33: China | S33: CHN | T33: APC | U33: 5 | V33: 0 | W33: W | Y33: NULL | Z33: NULL | AA33: Y | AB33: Y | AC33: ADV,HID:~CORE~AERO_NA~RCE~AGRO_ZAF~MDSUK~HC_GCC~HC_APAC~HIGHER_EDU~CMPIF_CHN~AERO_BRA~AERO_EMEA~UPSTREAM_MYS~LEGAL_FEE_EARNERS~CL_HRG~PSAR~ADV~ | AD33: Industry Group | AG33: NULL | AH33: NULL | AI33: If(In(:PRIMARY_IND,"001,003"),"01", If(In(:PRIMARY_IND,"004"),"02", If(In(:PRIMARY_IND,"005,031"),"03", If(In(:PRIMARY_IND,"006,007,008,009,010,018,047"),"04", If(In(:PRIMARY_IND,"011,012,013,079,095"),"05", If(In(:PRIMARY_IND,"014,015"),"06", If(In(:PRIMARY_IND,"016"),"07", If(In(:PRIMARY_IND,"017,024,036,037"),"08", If(In(:PRIMARY_IND,"019"),"09", If(In(:PRIMARY_IND,"020,172"),"10", If(In(:PRIMARY_IND,"021,022,023"),"11", If(In(:PRIMARY_IND,"025"),"12", If(In(:PRIMARY_IND,"026,027,043"),"13", If(In(:PRIMARY_IND,"028,045,052"),"14", If(In(:PRIMARY_IND,"029"),"15", If(In(:PRIMARY_IND,"030"),"16", If(In(:PRIMARY_IND,"032,044"),"17", If(In(:PRIMARY_IND,"033"),"18", If(In(:PRIMARY_IND,"034,067,083,084,145,157"),"19", If(In(:PRIMARY_IND,"035"),"20", If(In(:PRIMARY_IND,"038,040"),"21", If(In(:PRIMARY_IND,"039,135,140,148,149,155"),"22", If(In(:PRIMARY_IND,"041"),"23", If(In(:PRIMARY_IND,"046,050"),"24", If(In(:PRIMARY_IND,"048,051,053"),"25", If(In(:PRIMARY_IND,"049"),"26", If(In(:PRIMARY_IND,"054"),"27", If(In(:PRIMARY_IND,"055"),"28", If(In(:PRIMARY_IND,"056"),"29", If(In(:PRIMARY_IND,"057,141,142"),"30", If(In(:PRIMARY_IND,"058"),"31", If(In(:PRIMARY_IND,"059"),"32", If(In(:PRIMARY_IND,"060"),"33", If(In(:PRIMARY_IND,"061"),"34", If(In(:PRIMARY_IND,"062,063"),"35", If(In(:PRIMARY_IND,"064,065"),"36", If(In(:PRIMARY_IND,"066"),"37", If(In(:PRIMARY_IND,"068"),"38", If(In(:PRIMARY_IND,"069,070,072"),"39", If(In(:PRIMARY_IND,"071,076,078"),"40", If(In(:PRIMARY_IND,"073"),"41", If(In(:PRIMARY_IND,"074,147"),"42", If(In(:PRIMARY_IND,"075"),"43", If(In(:PRIMARY_IND,"077"),"44", If(In(:PRIMARY_IND,"080,104,129"),"45", If(In(:PRIMARY_IND,"081"),"46", If(In(:PRIMARY_IND,"082,085"),"47", If(In(:PRIMARY_IND,"086,185"),"48", If(In(:PRIMARY_IND,"087"),"49", If(In(:PRIMARY_IND,"088"),"50", If(In(:PRIMARY_IND,"089,164"),"51", If(In(:PRIMARY_IND,"090"),"52", If(In(:PRIMARY_IND,"091"),"53", If(In(:PRIMARY_IND,"092"),"54", If(In(:PRIMARY_IND,"093"),"55", If(In(:PRIMARY_IND,"094,099,105"),"56", If(In(:PRIMARY_IND,"096,097,100,101,102,103"),"57", If(In(:PRIMARY_IND,"098"),"58", If(In(:PRIMARY_IND,"106,109,111"),"59", If(In(:PRIMARY_IND,"107,108"),"60", If(In(:PRIMARY_IND,"110"),"61", If(In(:PRIMARY_IND,"112,113,114,173,174,175"),"62", If(In(:PRIMARY_IND,"115,116,117,184"),"63", If(In(:PRIMARY_IND,"118,119,120"),"64", If(In(:PRIMARY_IND,"121"),"65", If(In(:PRIMARY_IND,"122,123,126,168,169,170,171,186"),"66", If(In(:PRIMARY_IND,"124,127,143"),"67", If(In(:PRIMARY_IND,"125"),"68", If(In(:PRIMARY_IND,"128,153,159,161"),"69", If(In(:PRIMARY_IND,"130,150"),"70", If(In(:PRIMARY_IND,"131"),"71", If(In(:PRIMARY_IND,"133,134"),"73", If(In(:PRIMARY_IND,"146"),"74", If(In(:PRIMARY_IND,"151"),"75", If(In(:PRIMARY_IND,"152"),"76", If(In(:PRIMARY_IND,"156"),"77", If(In(:PRIMARY_IND,"158"),"78", If(In(:PRIMARY_IND,"160"),"79", If(In(:PRIMARY_IND,"162"),"80", If(In(:PRIMARY_IND,"163"),"81", If(In(:PRIMARY_IND,"165"),"82", If(In(:PRIMARY_IND,"166"),"83", If(In(:PRIMARY_IND,"167"),"84", If(In(:PRIMARY_IND,"176,177,178,179,180,181,182,183"),"85", NULL)))))))))))))))))))))))))))))))))))))))))))))))))))))))))))))))))))))))))))))))))))) | AJ33: NULL
A34: A24149240511 | B34: 2025 Capital Market Project Investment and Financing Compensation Survey - China | C34: SUBMISSIONGRANT | D34: 8 | E34: Accounting Value per Share/Unit of Award Curr | F34: N | G34: NULL | H34: N | I34: 101 | J34: 100 | K34: 100 | L34: C | M34: CHAR | N34: ACCOUNTINGCURR | O34: ACCOUNTINGCURR | P34: USE | Q34: L | R34: China | S34: CHN | T34: APC | U34: 12 | V34: 0 | W34: W | Y34: NULL | Z34: M | AA34: Y | AB34: Y | AC34: ~CORE~AERO_NA~SSO~RCE~AGRO_ZAF~MDSUK~MFG_LATAM~RENEWABLE~RENEWCLUB_FRA~AERO_EMEA~AERO_BRA~HC_GCC~HC_APAC~HIGHER_EDU~CMPIF_CHN~EDU_APAC~UPSTREAM_MYS~CL_PS_SUPPORTSTAFF_INTL~CL_HRG~INT~ | AD34: Accounting Value per Share/Unit of Award Curr | AE34: Accounting Value per Share/Unit of Award Currency | AG34: NULL | AH34: NULL | AJ34: :GRANTPRICECURR
A35: A24149240511 | B35: 2025 Capital Market Project Investment and Financing Compensation Survey - China | C35: SUBMISSIONINCUMBENT | D35: 8 | E35: Internal Grade/Level/Band | F35: Y | G35: AA | H35: Y | I35: 238 | J35: NULL | K35: NULL | L35: NULL | M35: CHAR | N35: GRADE | O35: DDE137 | P35: USE | Q35: L | R35: China | S35: CHN | T35: APC | U35: 100 | V35: 0 | W35: W | X35: Values can be alpha or numeric. If an incumbent is not assigned to a grade/level or the organization does not use grades or levels this field should be left blank. | Y35: NULL | Z35: M | AA35: Y | AB35: Y | AC35: ADV:~CORE~AERO_NA~SSO~RCE~AGRO_ZAF~MDSUK~MFG_LATAM~RENEWABLE~RENEWCLUB_FRA~AERO_EMEA~AERO_BRA~HC_GCC~HC_APAC~HIGHER_EDU~CMPIF_CHN~EDU_APAC~UPSTREAM_MYS~DRILL_GLOBAL~DRILL_NAT~LEGAL_FEE_EARNERS~CL_PS_SUPPORTSTAFF_INTL~CL_HRG~PSAR~ADV~ | AD35: Internal Grade/Level/Band | AE35: The internal grade/level/band your organization uses for this position. | AF35: Values can be alpha or numeric. If an incumbent is not assigned to a grade/level or the organization does not use grades or levels this field should be left blank. | AG35: AA | AH35: NULL | AJ35: If(IsNull(:GRADE),null,trunc(:GRADE,100))
A36: A24149240511 | B36: 2025 Capital Market Project Investment and Financing Compensation Survey - China | C36: SUBMISSIONINCUMBENT | D36: 9 | E36: Education Level | F36: Y | G36: E60 | H36: Y | I36: 13046 | J36: NULL | K36: NULL | L36: NULL | M36: PICK | N36: FC_EDULEVEL_ITM | O36: DDE266 | P36: USE | Q36: L | R36: China | S36: CHN | T36: APC | U36: 5 | V36: 0 | W36: W | X36: E00-Below Secondary School or Vocational Training E10-High/Secondary School E20-Junior College (typically 2 years post-secondary school) E30-Bachelor's Degree (typically 3-4 years post-secondary school) E40-Specialized Diploma (e.g., Engineering or Business Schools) E45-Specialized Diploma - Top Tier Schools E60-Master's Degree E70-Doctorate | Y36: NULL | Z36: M | AA36: Y | AB36: Y | AC36: ADV,SCOPE:~CORE_NONEXEC_APAC~CORE_NONEXEC_SSA~CORE_NONEXEC_FRA~CORE_NONEXEC_CHE~SSO_APAC~RCE_APAC~RCE_SSA~RCE_FRA~RCE_CHE~AGRO_ZAF~AERO_FRA~HIGHER_EDU~CMPIF_CHN~EDU_APAC~UPSTREAM_MYS~RENEWCLUB_FRA~LEGAL_FEE_EARNERS_APAC~LEGAL_FEE_EARNERS_FRANCE~;INT~CORE_ADV~ | AD36: Education Level | AE36: The education level of the incumbent. | AF36: E00-Below Secondary School or Vocational Training E10-High/Secondary School E20-Junior College (typically 2 years post-secondary school) E30-Bachelor's Degree (typically 3-4 years post-secondary school) E40-Specialized Diploma (e.g., Engineering or Business Schools) E45-Specialized Diploma - Top Tier Schools E60-Master's Degree E70-Doctorate | AG36: E60 | AH36: NULL | AJ36: upper(trim(:FC_EDULEVEL_ITM))
A37: A24149240511 | B37: 2025 Capital Market Project Investment and Financing Compensation Survey - China | C37: SUBMISSIONCOMPANY | D37: 9 | E37: Industry | F37: N | G37: NULL | H37: N | I37: NULL | J37: NULL | K37: NULL | L37: NULL | M37: PICK | N37: INDUSTRY_SIC | O37: NULL | P37: USE | Q37: C | R37: China | S37: CHN | T37: APC | U37: 5 | V37: 0 | W37: W | Y37: NULL | Z37: NULL | AA37: Y | AB37: Y | AC37: ADV:~CORE~AERO_NA~RCE~AGRO-ZAF~MDSUK~HC_GCC~HC_APAC~HIGHER_EDU~CMPIF_CHN~AERO_EMEA~AERO_BRA~UPSTREAM_MYS~LEGAL_FEE_EARNERS~CL_HRG~PSAR~ADV~ | AD37: Industry | AE37: The industry (GIC) reported by the organization. | AG37: NULL | AH37: NULL | AI37: If(In(:PRIMARY_IND,"001,003,004,021,022,023,025,152"),"01", If(In(:PRIMARY_IND,"005,026,027,028,029,030,031,032,033,041,043,044,045,046,048,049,050,051,052,053,055,066,151,158,166"),"02", If(In(:PRIMARY_IND,"006,007,008,009,010,011,012,013,014,015,017,018,024,036,037,047,079,086,087,088,089,095,163,164,185"),"03", If(In(:PRIMARY_IND,"016,019,020,172"),"04", If(In(:PRIMARY_IND,"034,035,054,056,057,058,059,060,061,067,081,082,083,084,085,124,125,127,141,142,143,145,157"),"05", If(In(:PRIMARY_IND,"038,039,040,133,134,135,140,148,149,155"),"06", If(In(:PRIMARY_IND,"062,063"),"07", If(In(:PRIMARY_IND,"064,065,130,150,160"),"08", If(In(:PRIMARY_IND,"069,070,071,072,073,075,076,077,078,162"),"10", If(In(:PRIMARY_IND,"074,131,147,165"),"11", If(In(:PRIMARY_IND,"080,104,129,156"),"12", If(In(:PRIMARY_IND,"090,091,092,093,094,096,097,098,099,100,101,102,103,105"),"13", If(In(:PRIMARY_IND,"106,107,108,109,110,111,112,113,114,115,116,117,167,173,174,175,176,177,178,179,180,181,182,183,184"),"14", If(In(:PRIMARY_IND,"118,119,120,121"),"15", If(In(:PRIMARY_IND,"122,123,126,128,153,159,161,168,169,170,171,186"),"16", NULL))))))))))))))) | AJ37: NULL
A38: A24149240511 | B38: 2025 Capital Market Project Investment and Financing Compensation Survey - China | C38: SUBMISSIONGRANT | D38: 9 | E38: Number of Shares/Units Granted | F38: N | G38: 10000 | H38: Y | I38: 47 | J38: NULL | K38: NULL | L38: NULL | M38: NUM | N38: SHARESUNITS | O38: SHARESUNITS | P38: USE | Q38: L | R38: China | S38: CHN | T38: APC | U38: 15 | V38: 0 | W38: W | X38: Do not report actual payouts or awards for the cycle that just ended. For newly hired employees or those near retirement who are long-term incentive eligible but did not receive a grant, enter an estimate. For performance unit or share plans, enter the target award opportunity (for defined target plans) or maximum award opportunity (for defined maximum plans) for the cycle that started most recently. For performance cash, co-investment shares and deferred bonus matching plans, for convenience and as a convention, report the full award value and enter 1.00 under grant price per share/unit. For Performance Cash plans, enter the target award (e.g., if an incumbent could earn 100% of base salary if target performance is achieved and the incumbent's base salary is 200,000, enter 200,000 and use the Base Salary currency as the Grant Price Currency). For Co-Investment Shares, report the maximum opportunity multiplied by the maximum share-matching on that investment. For example, if the maximum investment opportunity is 50% of a 200,000 base salary and the company will match a maximum of 50% of that investment, the award value is 50% x 200,000 x 50% = 50,000. For Deferred Bonus Matching Shares, report the maximum deferral opportunity (compulsory and/or voluntary) multiplied by the maximum company match on that deferral. For example, if the incumbent can defer up to 50% of a 100,000 target bonus and the company will match 100%, the award value is 50% x 100,000 x 100% = 50,000. | Y38: NULL | Z38: M | AA38: Y | AB38: Y | AC38: INT,DSW:~CORE~AERO_NA~SSO~RCE~AGRO_ZAF~MDSUK~MFG_LATAM~RENEWABLE~RENEWCLUB_FRA~AERO_EMEA~AERO_BRA~HC_GCC~HC_APAC~HIGHER_EDU~CMPIF_CHN~EDU_APAC~UPSTREAM_MYS~DRILL_GLOBAL~DRILL_NAT~CL_PS_SUPPORTSTAFF_INTL~CL_HRG~INT~ | AD38: Number of Shares/Units Granted | AE38: The number of options, shares or units granted. For performance plans, the values provided should be shares/cash/units for the upcoming cycle, not payouts from the cycle that just ended. | AF38: Do not report actual payouts or awards for the cycle that just ended. For newly hired employees or those near retirement who are long-term incentive eligible but did not receive a grant, enter an estimate. For performance unit or share plans, enter the target award opportunity (for defined target plans) or maximum award opportunity (for defined maximum plans) for the cycle that started most recently. For performance cash, co-investment shares and deferred bonus matching plans, for convenience and as a convention, report the full award value and enter 1.00 under grant price per share/unit. For Performance Cash plans, enter the target award (e.g., if an incumbent could earn 100% of base salary if target performance is achieved and the incumbent's base salary is 200,000, enter 200,000 and use the Base Salary currency as the Grant Price Currency). For Co-Investment Shares, report the maximum opportunity multiplied by the maximum share-matching on that investment. For example, if the maximum investment opportunity is 50% of a 200,000 base salary and the company will match a maximum of 50% of that investment, the award value is 50% x 200,000 x 50% = 50,000. For Deferred Bonus Matching Shares, report the maximum deferral opportunity (compulsory and/or voluntary) multiplied by the maximum company match on that deferral. For example, if the incumbent can defer up to 50% of a 100,000 target bonus and the company will match 100%, the award value is 50% x 100,000 x 100% = 50,000. | AG38: 10000 | AH38: NULL | AJ38: If(IsNull(:SHARESUNITS),Null,Round(:SHARESUNITS,0))
A39: A24149240511 | B39: 2025 Capital Market Project Investment and Financing Compensation Survey - China | C39: SUBMISSIONCONTACT | D39: 9 | E39: Comments | F39: N | G39: NULL | H39: N | I39: 79 | J39: NULL | K39: NULL | L39: NULL | M39: CHAR | N39: COMMENTS | O39: COMMENTS | P39: USE | Q39: L | R39: China | S39: CHN | T39: APC | U39: 255 | V39: 0 | W39: W | Y39: NULL | Z39: M | AA39: Y | AB39: Y | AC39: ~CORE~AERO_NA~SSO~RCE~AGRO_ZAF~MDSUK~YOUNGGRAD~MFG_LATAM~RENEWABLE~RENEWCLUB_FRA~AERO_EMEA~AERO_BRA~HC_GCC~HC_APAC~HIGHER_EDU~CMPIF_CHN~EDU_APAC~UPSTREAM_MYS~DRILL_GLOBAL~DRILL_NAT~LEGAL_FEE_EARNERS~CL_PS_SUPPORTSTAFF_INTL~PSAR~INT~ | AD39: Comments | AE39: Contact Comments | AG39: NULL | AH39: NULL | AJ39: NULL
A40: A24149240511 | B40: 2025 Capital Market Project Investment and Financing Compensation Survey - China | C40: SUBMISSIONGRANT | D40: 10 | E40: Comments | F40: N | G40: NULL | H40: N | I40: 82 | J40: NULL | K40: NULL | L40: NULL | M40: CHAR | N40: COMMENTS | O40: COMMENTS | P40: USE | Q40: L | R40: China | S40: CHN | T40: APC | U40: 255 | V40: 0 | W40: W | X40: NULL | Y40: NULL | Z40: M | AA40: Y | AB40: Y | AC40: ~CORE~AERO_NA~SSO~RCE~AGRO_ZAF~MDSUK~YOUNGGRAD~MFG_LATAM~RENEWABLE~RENEWCLUB_FRA~AERO_EMEA~AERO_BRA~HC_GCC~HC_APAC~HIGHER_EDU~CMPIF_CHN~EDU_APAC~UPSTREAM_MYS~DRILL~LEGAL_FEE_EARNERS~CL_PS_SUPPORTSTAFF_INTL~INT~ | AD40: Comments | AE40: Comments | AF40: NULL | AG40: NULL | AH40: NULL | AJ40: NULL
A41: A24149240511 | B41: 2025 Capital Market Project Investment and Financing Compensation Survey - China | C41: SUBMISSIONINCUMBENT | D41: 10 | E41: Gender | F41: Y | G41: F | H41: Y | I41: 22399 | J41: NULL | K41: NULL | L41: NULL | M41: PICK | N41: FC_GEND_COD | O41: DDE088 | P41: USE | Q41: L | R41: China | S41: CHN | T41: APC | U41: 5 | V41: 0 | W41: W | X41: M-Male F-Female U-Undisclosed/Not reported | Y41: NULL | Z41: M | AA41: Y | AB41: Y | AC41: ADV:~CORE_EMEA~SSO_EMEA~RCE_EMEA~AGRO_ZAF~MDSUK~RENEWABLE_EMEA~RENEWCLUB_FRA~AERO_EMEA~AERO_BRA~HC_GCC~HC_APAC~HIGHER_EDU~DRILL_NAT~DRILL_GLOBAL~LEGAL_FEE_EARNERS~CL_PS_SUPPORTSTAFF_INTL~CL_HRG~;PUB:~CORE_APAC~CORE_NA~AERO_NA~SSO_APAC~RCE_APAC~YOUNGGRAD~MFG_LATAM~RENEWABLE_APAC~CMPIF_CHN~EDU_APAC~UPSTREAM_MYS~PSAR~;INT:~CORE_LATAM~SSO_LATAM~RENEWABLE_BRA~DRILL_NAT_LATAM~PUB~ | AD41: Gender | AE41: The gender of the incumbent. | AF41: M-Male F-Female U-Undisclosed/Not reported | AG41: F | AH41: NULL | AJ41: upper(trim(:FC_GEND_COD))
A42: A24149240511 | B42: 2025 Capital Market Project Investment and Financing Compensation Survey - China | C42: SUBMISSIONCOMPANY | D42: 10 | E42: Participating Entity Geographic Scope | F42: Y | G42: R [Regional] | H42: Y | I42: 567 | J42: NULL | K42: NULL | L42: NULL | M42: PICK | N42: FC_EGEOSC_ITM | O42: DDE039 | P42: USE | Q42: L | R42: China | S42: CHN | T42: APC | U42: 5 | V42: 0 | W42: W | X42: S-Single - single country only M-Multi-Country - small cluster of countries R-Regional - an entire region, or multiple countries across one or two continents G-Global - three or more continents Select Single country when international operations are negligible. Select Multi-Country when international operations are limited to a small clusters of countries, e.g., Benelux, China and Hong Kong, Nordics, UK and Ireland, often grouped under a single legal entity. Select Regional when international operations are significant and covers an entire region, e.g., North America (U.S. and Canada), Western Europe, Middle East and Africa, Greater China (China, Hong Kong and Taiwan), South East Asia (SEA), Latin America, or multiple countries across one or two continents. Select Global when international operations are predominant and covers three or more continents. | Y42: NULL | Z42: M | AA42: Y | AB42: Y | AC42: INT:~CORE_NONEXEC~CORE_NONEXEC_NA~AERO_NA~SSO~RCE~AGRO_ZAF~MFG_LATAM~RENEWABLE~RENEWCLUB_FRA~AERO_EMEA~AERO_BRA~HC_GCC~HC_APAC~HIGHER_EDU~CMPIF_CHN~EDU_APAC~UPSTREAM_MYS~LEGAL_FEE_EARNERS~CL_PS_SUPPORTSTAFF_INTL~;ADV:~CORE_EXEC~CORE_EXEC_NA~MDSUK~YOUNGGRAD~DRILL_GLOBAL~DRILL_NAT~CL_HRG~PSAR~INT~ | AD42: Participating Entity Geographic Scope | AE42: The geographic scope of the participating entity. | AF42: S-Single - single country only M-Multi-Country - small cluster of countries R-Regional - an entire region, or multiple countries across one or two continents G-Global - three or more continents Select Single country when international operations are negligible. Select Multi-Country when international operations are limited to a small clusters of countries, e.g., Benelux, China and Hong Kong, Nordics, UK and Ireland, often grouped under a single legal entity. Select Regional when international operations are significant and covers an entire region, e.g., North America (U.S. and Canada), Western Europe, Middle East and Africa, Greater China (China, Hong Kong and Taiwan), South East Asia (SEA), Latin America, or multiple countries across one or two continents. Select Global when international operations are predominant and covers three or more continents. | AG42: R [Regional] | AH42: NULL | AJ42: NULL
A43: A24149240511 | B43: 2025 Capital Market Project Investment and Financing Compensation Survey - China | C43: SUBMISSIONINCUMBENT | D43: 11 | E43: Date of Birth | F43: Y | G43: 25569 | H43: Y | I43: 312 | J43: NULL | K43: NULL | L43: NULL | M43: DATE | N43: FD_DOB_DAT | O43: DDE051 | P43: USE | Q43: L | R43: China | S43: CHN | T43: APC | U43: 8 | V43: 0 | W43: W | X43: Please enter the date in your normal date format (DD/MM/YY or MM/DD/YY depending on the user default). If you don't want to enter the actual date please use 1 January. | Y43: NULL | Z43: M | AA43: Y | AB43: Y | AC43: INT:~CORE_APAC~CORE_EMEA~CORE_LATAM~ENERGY_CAN~SSO~RCE~AGRO_ZAF~MDSUK~YOUNGGRAD~MFG_LATAM~RENEWABLE~RENEWCLUB_FRA~AERO_EMEA~AERO_BRA~HC_GCC~HC_APAC~HIGHER_EDU~CMPIF_CHN~EDU_APAC~UPSTREAM_MYS~DRILL_GLOBAL~DRILL_NAT_INTL~;ADV:~LEGAL_FEE_EARNERS~CL_PS_SUPPORTSTAFF_INTL~CL_HRG~PSAR~INT~ | AD43: Date of Birth | AE43: The incumbent's date of birth. | AF43: Please enter the date in your normal date format (DD/MM/YY or MM/DD/YY depending on the user default). If you don't want to enter the actual date please use 1 January. | AG43: 25569 | AH43: NULL | AJ43: NULL
A44: A24149240511 | B44: 2025 Capital Market Project Investment and Financing Compensation Survey - China | C44: SUBMISSIONGRANT | D44: 11 | E44: Grant Structure (SO and PP plans only) | F44: N | G44: T | H44: N | I44: 84 | J44: NULL | K44: NULL | L44: NULL | M44: PICK | N44: VESTING | O44: VESTING | P44: USE | Q44: L | R44: China | S44: CHN | T44: APC | U44: 5 | V44: 0 | W44: W | X44: T-Defined target award (With higher/lower payout potential the emphasis to participants is on the target number of shares). M-Defined maximum award (With only lower payout potential the emphasis to participants is on the maximum number of shares). | Y44: NULL | Z44: M | AA44: Y | AB44: Y | AC44: INT,DSW:~CORE_APAC~CORE_EMEA~CORE_LATAM~RCE~MDSUK~YOUNGGRAD~RENEWABLE~HIGHER_EDU~AERO_EMEA~AERO_BRA~CL_HRG~;HID:~SSO~CMPIF_CHN~EDU_APAC~UPSTREAM_MYS~ | AD44: Grant Structure (SO and PP plans only) | AE44: The payout structure for the grant. | AF44: T-Defined target award (With higher/lower payout potential the emphasis to participants is on the target number of shares). M-Defined maximum award (With only lower payout potential the emphasis to participants is on the maximum number of shares). | AG44: T | AH44: NULL | AJ44: NULL
A45: A24149240511 | B45: 2025 Capital Market Project Investment and Financing Compensation Survey - China | C45: SUBMISSIONCOMPANY | D45: 11 | E45: Participating Entity Full Value Chain of Activities | F45: Y | G45: Y [The organization controls the full value chain of activities] | H45: Y | I45: 487 | J45: NULL | K45: NULL | L45: NULL | M45: PICK | N45: FC_EVCACT_YON | O45: DDE032 | P45: USE | Q45: L | R45: China | S45: CHN | T45: APC | U45: 5 | V45: 0 | W45: W | X45: Y-The organization controls the full value chain of activities for all regions/countries/subsidiaries. N-The organization does not control the full value chain of activities for all regions/countries/subsidiaries (e.g., entities may be independent). | Y45: NULL | Z45: M | AA45: Y | AB45: Y | AC45: INT:~CORE~AERO_NA~SSO~RCE~AGRO_ZAF~MDSUK~YOUNGGRAD~MFG_LATAM~RENEWABLE~RENEWCLUB_FRA~AERO_EMEA~AERO_BRA~HC_GCC~HC_APAC~HIGHER_EDU~CMPIF_CHN~EDU_APAC~UPSTREAM_MYS~DRILL_GLOBAL~DRILL_NAT~LEGAL_FEE_EARNERS~CL_PS_SUPPORTSTAFF_INTL~CL_HRG~PSAR~INT~ | AD45: Participating Entity Full Value Chain of Activities | AE45: The extent to which the organization maintains end to end control of the business, including design, creation, sale and support of products and/or services. | AF45: Y-The organization controls the full value chain of activities for all regions/countries/subsidiaries. N-The organization does not control the full value chain of activities for all regions/countries/subsidiaries (e.g., entities may be independent). | AG45: Y [The organization controls the full value chain of activities] | AH45: NULL | AJ45: NULL
A46: A24149240511 | B46: 2025 Capital Market Project Investment and Financing Compensation Survey - China | C46: SUBMISSIONCOMPANY | D46: 12 | E46: Participating Entity Products/Services in Single/Related Industries | F46: Y | G46: Y [Single/Related Industries] | H46: Y | I46: 565 | J46: NULL | K46: NULL | L46: NULL | M46: PICK | N46: FC_EDIVERS_YON | O46: DDE037 | P46: USE | Q46: L | R46: China | S46: CHN | T46: APC | U46: 5 | V46: 0 | W46: W | X46: Y-Single/Related Industries N-Multiple/Diverse Industries | Y46: NULL | Z46: M | AA46: Y | AB46: Y | AC46: INT:~CORE~AERO_NA~SSO~RCE~AGRO_ZAF~MDSUK~YOUNGGRAD~MFG_LATAM~RENEWABLE~RENEWCLUB_FRA~AERO_EMEA~AERO_BRA~HC_GCC~HC_APAC~HIGHER_EDU~CMPIF_CHN~EDU_APAC~UPSTREAM_MYS~DRILL_GLOBAL~DRILL_NAT~LEGAL_FEE_EARNERS~CL_PS_SUPPORTSTAFF_INTL~CL_HRG~PSAR~INT~ | AD46: Participating Entity Products/Services in Single/Related Industries | AE46: Indicate whether the participating entity's products/services are in a single/related industry or span multiple distinct/unrelated industries. | AF46: Y-Single/Related Industries N-Multiple/Diverse Industries | AG46: Y [Single/Related Industries] | AH46: NULL | AJ46: NULL
A47: A24149240511 | B47: 2025 Capital Market Project Investment and Financing Compensation Survey - China | C47: SUBMISSIONINCUMBENT | D47: 12 | E47: Age | F47: N | G47: NULL | H47: N | I47: NULL | J47: NULL | K47: NULL | L47: NULL | M47: NUM | N47: AGE | O47: NULL | P47: USE | Q47: C | R47: China | S47: CHN | T47: APC | U47: 3 | V47: 0 | W47: W | X47: NULL | Y47: NULL | Z47: NULL | AA47: Y | AB47: Y | AC47: PUB:~CORE_APAC~CORE_DEU~CORE_FRA~SSO_APAC~RCE_APAC~RCE_DEU~RCE_FRA~RENEWABLE_APAC~CMPIF_CHN~EDU_APAC~UPSTREAM_MYS~;ADV:~CORE_EMEA~SSO_EMEA~RCE_EMEA~AGRO_ZAF~MDSUK~YOUNGGRAD~RENEWABLE_EMEA~RENEWCLUB_FRA~AERO_EMEA~AERO_BRA~HC_GCC~HC_APAC~HIGHER_EDU~CL_PS_SUPPORTSTAFF_INTL~CL_HRG~;INT:~CORE_LATAM~SSO_LATAM~RENEWABLE_LATAM~DRILL_GLOBAL~DRILL_NAT_APAC~DRILL_NAT_DEU~DRILL_NAT_FRA~PUB~ | AD47: Age | AE47: The age of the incumbent, calculated based on Year of Birth or Date of Birth. | AF47: NULL | AG47: NULL | AH47: NULL | AI47: if(isnull(:FD_DOB_DAT) or :FD_DOB_DAT<Date(1955,4,1) or :FD_DOB_DAT>Date(2009,4,1),null,2024 - Number(FormatDate(:FD_DOB_DAT,"YYYY"))+if(Number(FormatDate(:FD_DOB_DAT,"MM"))<4,1,0)) | AJ47: NULL
A48: A24149240511 | B48: 2025 Capital Market Project Investment and Financing Compensation Survey - China | C48: SUBMISSIONINCUMBENT | D48: 13 | E48: Age Range | F48: N | G48: NULL | H48: N | I48: NULL | J48: NULL | K48: NULL | L48: NULL | M48: PICK | N48: AGE_RANGE | O48: NULL | P48: USE | Q48: C | R48: China | S48: CHN | T48: APC | U48: 5 | V48: 0 | W48: W | Y48: NULL | Z48: NULL | AA48: Y | AB48: Y | AC48: SCOPE:~LEGAL_FEE_EARNERS_JAPAN~LEGAL_FEE_EARNERS_CHINA~CORE_NONEXEC_CHN~CMPIF_CHN~ | AD48: Age Range | AG48: NULL | AH48: NULL | AI48: if(IsNull(:AGE),NULL, if(:AGE < 22,"A", if(:AGE < 26,"B", if(:AGE < 31,"C", if(:AGE < 36,"D", if(:AGE < 41,"E", if(:AGE < 46,"F", if(:AGE < 51,"G", if(:AGE < 56,"H", if(:AGE < 61,"I","J")))))))))) | AJ48: NULL
A49: A24149240511 | B49: 2025 Capital Market Project Investment and Financing Compensation Survey - China | C49: SUBMISSIONCOMPANY | D49: 13 | E49: Participating Entity Survey Grade | F49: N | G49: WTW use only | H49: Y | I49: 34989 | J49: NULL | K49: NULL | L49: NULL | M49: NUM | N49: ENTITY_GG | O49: DDE197 | P49: USE | Q49: L | R49: China | S49: CHN | T49: APC | U49: 2 | V49: 0 | W49: W | X49: Refer to the Organization/Business Unit Survey Grading Guidelines to determine if your organization qualifies as a business unit. Failure to provide any of the country characteristics will prevent the Survey Grade from being calculated. Country Survey Grades are calculated as an indication to guide the job matching of your incumbents within each entity and are used as a reference during data validation to detect incumbent Survey Grades that do not seem plausible. | Y49: NULL | Z49: M | AA49: Y | AB49: Y | AC49: INT:~CORE~AERO_NA~SSO~RCE~AGRO_ZAF~MDSUK~YOUNGGRAD~MFG_LATAM~RENEWABLE~RENEWCLUB_FRA~AERO_EMEA~AERO_BRA~HC_GCC~HC_APAC~HIGHER_EDU~CMPIF_CHN~EDU_APAC~UPSTREAM_MYS~DRILL_GLOBAL~DRILL_NAT~LEGAL_FEE_EARNERS~CL_PS_SUPPORTSTAFF_INTL~CL_HRG~PSAR~INT~ | AD49: Participating Entity Survey Grade | AE49: This field is automatically calculated based on the reported participating entity characteristics (i.e., Annual Revenue Range, FTE Employee Range, Geographic Scope, Full Value Chain of Activities, Products/ Services in Single/Related Industries). | AF49: Refer to the Organization/Business Unit Survey Grading Guidelines to determine if your organization qualifies as a business unit. Failure to provide any of the country characteristics will prevent the Survey Grade from being calculated. Country Survey Grades are calculated as an indication to guide the job matching of your incumbents within each entity and are used as a reference during data validation to detect incumbent Survey Grades that do not seem plausible. | AG49: WTW use only | AH49: =IF(AND(FIND(LEFT(RC[-5],1), " ABCDEFGHIJKLMN")>1,FIND(LEFT(RC[-4],1), " ABCDEFGHIJ")>1,FIND(LEFT(RC[-3],1)," SMRG")>1, FIND(LEFT(RC[-2],1)," NY")>1,FIND(LEFT(RC[-1],1), " NY")>1),AVERAGE(IF(LEFT(RC[-5],1) <= "D", 16, IF(LEFT(RC[-5], 1) = "E", 17, IF(LEFT(RC[-5],1) <= "G", 18, CODE(LEFT(RC[-5],1))-CODE("H")+19))), CODE(LEFT(RC[-4],1))-CODE("A")+16,IF(OR(LEFT(RC[-3],1)="S",LEFT(RC[-3],1)="M"),16,IF(LEFT(RC[-3],1)="G",20,19))+IF(LEFT(RC[-2],1)="Y",2,0)+IF(LEFT(RC[-1],1)="N",2,0)),"CALCULATED") | AJ49: NULL
A50: A24149240511 | B50: 2025 Capital Market Project Investment and Financing Compensation Survey - China | C50: SUBMISSIONINCUMBENT | D50: 14 | E50: Date of Hire | F50: Y | G50: 37809 | H50: Y | I50: 314 | J50: NULL | K50: 312 | L50: NULL | M50: DATE | N50: FD_DOH_DAT | O50: DDE053 | P50: USE | Q50: L | R50: China | S50: CHN | T50: APC | U50: 8 | V50: 0 | W50: W | X50: Please enter the date in your normal date format (DD/MM/YY or MM/DD/YY depending on the user default). If you don't want to enter the actual date enter the year of hire. | Y50: NULL | Z50: M | AA50: Y | AB50: Y | AC50: INT:~CORE~AERO_NA~SSO~RCE~AGRO_ZAF~MDSUK~YOUNGGRAD~MFG_LATAM~RENEWABLE~RENEWCLUB_FRA~AERO_EMEA~AERO_BRA~HC_GCC~HC_APAC~HIGHER_EDU~CMPIF_CHN~EDU_APAC~UPSTREAM_MYS~DRILL_GLOBAL~DRILL_NAT~;ADV:~LEGAL_FEE_EARNERS~CL_PS_SUPPORTSTAFF_INTL~CL_HRG~PSAR~INT~ | AD50: Date of Hire | AE50: The incumbent's date of hire. | AF50: Please enter the date in your normal date format (DD/MM/YY or MM/DD/YY depending on the user default). If you don't want to enter the actual date enter the year of hire. | AG50: 37809 | AH50: NULL | AJ50: NULL
A51: A24149240511 | B51: 2025 Capital Market Project Investment and Financing Compensation Survey - China | C51: SUBMISSIONCOMPANY | D51: 14 | E51: Participating Entity Main Pay Change Month | F51: Y | G51: 01 [January] | H51: Y | I51: 162 | J51: NULL | K51: NULL | L51: NULL | M51: PICK | N51: SALARY_MONTH | O51: DDE020 | P51: USE | Q51: L | R51: China | S51: CHN | T51: APC | U51: 5 | V51: 0 | W51: W | X51: Where pay changes are effective over multiple months, select the month the majority of salary reviews become effective. When pay changes are effective on a rolling/anniversary review basis, select RR-Rolling Review. For countries where there is a union or mandatory increase, please consider the merit date and not the mandatory factor. | Y51: NULL | Z51: M | AA51: Y | AB51: Y | AC51: INT:~CORE~AERO_NA~SSO~RCE~AGRO_ZAF~MDSUK~YOUNGGRAD~MFG_LATAM~RENEWABLE~RENEWCLUB_FRA~AERO_EMEA~AERO_BRA~HC_GCC~HC_APAC~HIGHER_EDU~CMPIF_CHN~EDU_APAC~UPSTREAM_MYS~DRILL_GLOBAL~DRILL_NAT~LEGAL_FEE_EARNERS~CL_PS_SUPPORTSTAFF_INTL~CL_HRG~PSAR~INT~ | AD51: Participating Entity Main Pay Change Month | AE51: The effective date for pay changes. | AF51: Where pay changes are effective over multiple months, select the month the majority of salary reviews become effective. When pay changes are effective on a rolling/anniversary review basis, select RR-Rolling Review. For countries where there is a union or mandatory increase, please consider the merit date and not the mandatory factor. | AG51: 01 [January] | AH51: NULL | AJ51: NULL
A52: A24149240511 | B52: 2025 Capital Market Project Investment and Financing Compensation Survey - China | C52: SUBMISSIONINCUMBENT | D52: 15 | E52: Years of Service | F52: N | G52: NULL | H52: N | I52: NULL | J52: NULL | K52: NULL | L52: NULL | M52: NUM | N52: YEARS_OF_SERVICE | O52: NULL | P52: USE | Q52: C | R52: China | S52: CHN | T52: APC | U52: 3 | V52: 0 | W52: W | Y52: NULL | Z52: NULL | AA52: Y | AB52: Y | AC52: PUB:~CORE_APAC~CORE_EMEA~CORE_LATAM~SSO~RCE~AGRO_ZAF~MDSUK~YOUNGGRAD~RENEWABLE~RENEWCLUB_FRA~AERO_EMEA~AERO_BRA~HC_GCC~HC_APAC~HIGHER_EDU~CMPIF_CHN~EDU_APAC~UPSTREAM_MYS~DRILL_GLOBAL~DRILL_NAT_INTL~CL_PS_SUPPORTSTAFF_INTL~CL_HRG~PSAR~;ADV:~CORE_NA~AERO_NA~DRILL_NAT_NA~LEGAL_FEE_EARNERS~PUB~ | AD52: Years of Service | AE52: The number of years in service in the organization. | AG52: NULL | AH52: NULL | AI52: if(isnull(:FD_DOH_DAT),null,if(Number(FormatDate(:FD_DOH_DAT,"YYYY")) >= 2025,0,2024 - Number(FormatDate(:FD_DOH_DAT,"YYYY"))+if(Number(FormatDate(:FD_DOH_DAT,"MM"))<4,1,0))) | AJ52: NULL
A53: A24149240511 | B53: 2025 Capital Market Project Investment and Financing Compensation Survey - China | C53: SUBMISSIONCOMPANY | D53: 16 | E53: Participating Entity Primary Industry | F53: N | G53: 001 [Agricultural Products] | H53: Y | I53: 29540 | J53: NULL | K53: NULL | L53: NULL | M53: PICK | N53: PRIMARY_IND | O53: DDE178 | P53: USE | Q53: L | R53: China | S53: CHN | T53: APC | U53: 5 | V53: 0 | W53: W | X53: Refer to the Industries tab. | Y53: NULL | Z53: M | AA53: Y | AB53: Y | AC53: ~CORE~AERO_NA~SSO~RCE~AGRO_ZAF~MDSUK~RENEWABLE~HC_GCC~HC_APAC~HIGHER_EDU~CMPIF_CHN~EDU_APAC~RENEWCLUB_FRA~DRILL_GLOBAL~DRILL_NAT~AERO_EMEA~AERO_BRA~UPSTREAM_MYS~LEGAL_FEE_EARNERS~CL_HRG~CL_PS_SUPPORTSTAFF_INTL~PSAR~INT~ | AD53: Participating Entity Primary Industry | AE53: The primary industry that most closely describes the organization's line(s) of business. | AF53: Refer to the Industries tab. | AG53: 001 [Agricultural Products] | AH53: NULL | AJ53: NULL
A54: A24149240511 | B54: 2025 Capital Market Project Investment and Financing Compensation Survey - China | C54: SUBMISSIONINCUMBENT | D54: 16 | E54: Year of Entry into Business/Industry | F54: Y | G54: 2012 | H54: Y | I54: 75610 | J54: NULL | K54: NULL | L54: NULL | M54: NUM | N54: FN_YENTBUS_YRS | O54: DDE450 | P54: USE | Q54: L | R54: China | S54: CHN | T54: APC | U54: 4 | V54: 0 | W54: W | X54: NULL | Y54: NULL | Z54: M | AA54: Y | AB54: Y | AC54: ADV:~CORE_APAC~SSO_APAC~RCE_APAC~RENEWABLE_APAC~CMPIF_CHN~EDU_APAC~UPSTREAM_MYS~HIGHER_EDU~DRILL_GLOBAL~DRILL_NAT_APAC~LEGAL_FEE_EARNERS_APAC~PSAR~ADV~ | AD54: Year of Entry into Business/Industry | AE54: Year of entry into the business/industry within your organization and/or another one. | AF54: NULL | AG54: 2012 | AH54: NULL | AJ54: NULL
A55: A24149240511 | B55: 2025 Capital Market Project Investment and Financing Compensation Survey - China | C55: SUBMISSIONCOMPANY | D55: 17 | E55: Participating Entity Individual Industry | F55: N | G55: 7379 [Computer Related Services, Not Elsewhere Classified] | H55: N | I55: 78153 | J55: NULL | K55: NULL | L55: NULL | M55: PICK | N55: SECT1 | O55: DDE272 | P55: USE | Q55: L | R55: China | S55: CHN | T55: APC | U55: 5 | V55: 0 | W55: W | X55: Refer to the Industries tab. | Y55: NULL | Z55: M | AA55: Y | AB55: Y | AC55: INT:~CORE~AERO_NA~SSO~RCE~AGRO_ZAF~MDSUK~YOUNGGRAD~MFG_LATAM~RENEWABLE~AERO_EMEA~AERO_BRA~HC_GCC~HC_APAC~HIGHER_EDU~CMPIF_CHN~EDU_APAC~UPSTREAM_MYS~DRILL_GLOBAL~DRILL_NAT~LEGAL_FEE_EARNERS~CL_PS_SUPPORTSTAFF_INTL~CL_HRG~PSAR~INT~ | AD55: Participating Entity Individual Industry | AE55: The primary industry that most closely describes the organization's line(s) of business. | AF55: Refer to the Industries tab. | AG55: 7379 [Computer Related Services, Not Elsewhere Classified] | AH55: NULL | AJ55: NULL
A56: A24149240511 | B56: 2025 Capital Market Project Investment and Financing Compensation Survey - China | C56: SUBMISSIONINCUMBENT | D56: 17 | E56: Basic Hours Worked Per Week | F56: Y | G56: 20 | H56: Y | I56: 22163 | J56: NULL | K56: NULL | L56: NULL | M56: NUM | N56: FN_BHRSW | O56: DDE391 | P56: USE | Q56: L | R56: China | S56: CHN | T56: APC | U56: 3 | V56: 2 | W56: W | X56: If an incumbent works part-time, convert Annual Base Salary, and all other compensation data elements to full-time equivalents. | Y56: NULL | Z56: M | AA56: Y | AB56: Y | AC56: INT:~CORE_EMEA~RETAIL_APAC~RETAIL_LATAM~CORE_CAN~CORE_USA~AERO_NA~SSO_EMEA~RCE_EMEA~AGRO_ZAF~MDSUK~RENEWABLE_EMEA~RENEWCLUB_FRA~AERO_EMEA~HC_GCC~HC_APAC~HIGHER_EDU~CMPIF_CHN~DRILL_GLOBAL~DRILL_NAT_EMEA~DRILL_NAT_NA~LEGAL_FEE_EARNERS_EMEA~CL_PS_SUPPORTSTAFF_INTL~CL_HRG~PSAR~INT~ | AD56: Basic Hours Worked Per Week | AE56: The average basic contractual hours worked per week by the incumbent. | AF56: If an incumbent works part-time, convert Annual Base Salary, and all other compensation data elements to full-time equivalents. | AG56: 20 | AH56: NULL | AJ56: If(IsNull(:FN_BHRSW),Null,Round(:FN_BHRSW,2))
A57: A24149240511 | B57: 2025 Capital Market Project Investment and Financing Compensation Survey - China | C57: SUBMISSIONCOMPANY | D57: 18 | E57: Participating Entity Performance Bonus Plan | F57: Y | G57: Y [Yes] | H57: Y | I57: 35003 | J57: NULL | K57: NULL | L57: NULL | M57: BOOL | N57: PE_BONUS_PLAN | O57: DDE056 | P57: USE | Q57: L | R57: China | S57: CHN | T57: APC | U57: 1 | V57: 0 | W57: W | X57: Y-Organization has a performance bonus plan N-No plan | Y57: NULL | Z57: M | AA57: Y | AB57: Y | AC57: INT:~CORE~AERO_NA~SSO~RCE~AGRO_ZAF~MDSUK~YOUNGGRAD~MFG_LATAM~RENEWABLE~RENEWCLUB_FRA~AERO_EMEA~AERO_BRA~HC_GCC~HC_APAC~HIGHER_EDU~CMPIF_CHN~EDU_APAC~UPSTREAM_MYS~DRILL_GLOBAL~DRILL_NAT~LEGAL_FEE_EARNERS~CL_PS_SUPPORTSTAFF_INTL~CL_HRG~PSAR~INT~ | AD57: Participating Entity Performance Bonus Plan | AE57: Organization has a performance bonus plan. This is an incentive scheme with a predetermined performance and reward schedule, whether or not deferred and irrespective of the delivery medium (cash or equity). | AF57: Y-Organization has a performance bonus plan N-No plan | AG57: Y [Yes] | AH57: NULL | AJ57: NULL
A58: A24149240511 | B58: 2025 Capital Market Project Investment and Financing Compensation Survey - China | C58: SUBMISSIONINCUMBENT | D58: 18 | E58: Year Assigned to Position | F58: Y | G58: 2008 | H58: Y | I58: 29360 | J58: NULL | K58: NULL | L58: NULL | M58: NUM | N58: FN_ASSPOS_YRS | O58: DDE422 | P58: USE | Q58: L | R58: China | S58: CHN | T58: APC | U58: 5 | V58: 0 | W58: W | X58: This should be displayed as (YYYY). | Y58: NULL | Z58: M | AA58: Y | AB58: Y | AC58: INT:~FS~CMPIF_CHN~INT~ | AD58: Year Assigned to Position | AE58: Incumbent's year of entry to current position. | AF58: This should be displayed as (YYYY). | AG58: 2008 | AH58: NULL | AI58: NULL | AJ58: NULL
A59: A24149240511 | B59: 2025 Capital Market Project Investment and Financing Compensation Survey - China | C59: SUBMISSIONCOMPANY | D59: 19 | E59: Participating Entity Sales Incentive Plan | F59: Y | G59: C [Organization has a Commission plan] | H59: Y | I59: 35004 | J59: NULL | K59: NULL | L59: NULL | M59: PICK | N59: PE_SALES_PLAN | O59: DDE210 | P59: USE | Q59: L | R59: China | S59: CHN | T59: APC | U59: 5 | V59: 0 | W59: W | X59: C-Organization has a Commission Plan G-Organization has a Goal-Based Sales Incentive Plan B-Organization has both a Commission and Goal-Based Sales Incentive Plan N-No Sales Incentive Plan Goal-Based: incentive earned based on performance relative to a quota, goal or other pre-determined performance objectives; although infrequent, may include goal-based mechanic for performance up to a threshold level (e.g., target, quota or point of excellence) and then commission-based mechanic beyond threshold. Commission: incentive earned / calculated using a commission rate (e.g., percentage of sales, profit, volume) or flat dollar amount applied to every dollar or unit sold. Note: The term "sales commission" or "sales bonus" may be used interchangeably by companies to describe all of the above incentive forms for sales professionals. | Y59: NULL | Z59: M | AA59: Y | AB59: Y | AC59: INT:~CORE~AERO_NA~SSO~RCE~AGRO_ZAF~MDSUK~MFG_LATAM~RENEWABLE~RENEWCLUB_FRA~AERO_EMEA~AERO_BRA~HC_GCC~HC_APAC~HIGHER_EDU~CMPIF_CHN~EDU_APAC~UPSTREAM_MYS~DRILL_GLOBAL~DRILL_NAT~LEGAL_FEE_EARNERS~CL_PS_SUPPORTSTAFF_INTL~CL_HRG~PSAR~INT~ | AD59: Participating Entity Sales Incentive Plan | AE59: Organization has a sales incentive plan. | AF59: C-Organization has a Commission Plan G-Organization has a Goal-Based Sales Incentive Plan B-Organization has both a Commission and Goal-Based Sales Incentive Plan N-No Sales Incentive Plan Goal-Based: incentive earned based on performance relative to a quota, goal or other pre-determined performance objectives; although infrequent, may include goal-based mechanic for performance up to a threshold level (e.g., target, quota or point of excellence) and then commission-based mechanic beyond threshold. Commission: incentive earned / calculated using a commission rate (e.g., percentage of sales, profit, volume) or flat dollar amount applied to every dollar or unit sold. Note: The term "sales commission" or "sales bonus" may be used interchangeably by companies to describe all of the above incentive forms for sales professionals. | AG59: C [Organization has a Commission plan] | AH59: NULL | AJ59: NULL
A60: A24149240511 | B60: 2025 Capital Market Project Investment and Financing Compensation Survey - China | C60: SUBMISSIONINCUMBENT | D60: 19 | E60: Years in Position | F60: N | G60: NULL | H60: N | I60: NULL | J60: NULL | K60: NULL | L60: NULL | M60: NUM | N60: YRS_POS | O60: NULL | P60: USE | Q60: C | R60: China | S60: CHN | T60: APC | U60: 8 | V60: 0 | W60: W | X60: NULL | Y60: NULL | Z60: NULL | AA60: Y | AB60: Y | AC60: ADV:~FS~CMPIF_CHN~ADV~ | AD60: Years in Position | AE60: The number of years in current position in the organization. | AF60: NULL | AG60: NULL | AH60: NULL | AI60: if(isnull(:FN_ASSPOS_YRS),null,if(:FN_ASSPOS_YRS >= 2025,0,2025 - :FN_ASSPOS_YRS)) | AJ60: NULL
A61: A24149240511 | B61: 2025 Capital Market Project Investment and Financing Compensation Survey - China | C61: SUBMISSIONINCUMBENT | D61: 20 | E61: Employee Classification | F61: Y | G61: 1 | H61: Y | I61: 13095 | J61: NULL | K61: NULL | L61: NULL | M61: PICK | N61: FN_EMPLCLASS_ITM | O61: DDE315 | P61: USE | Q61: L | R61: China | S61: CHN | T61: APC | U61: 5 | V61: 0 | W61: W | X61: For employees classified using codes numbered 1 to 3 please supply all requested information, for codes 4 and 5 please provide job match and title information but EXCLUDE compensation and benefits data: 1-Full-Time Employee 2-Part-Time Employee; Full Time Equivalent pay data provided (FTE) 3-Employee for whom there is no suitable job reference. For these employees where possible identify the job reference[s] which you feel are the closest approximation(s) AND provide the corresponding pay data 4-Expatriate Employee; for these incumbents it is beneficial to provide a job match but pay data should not be provided 5-Red-Circled Employee; for these incumbents it is beneficial to provide a job match but pay data should not be provided | Y61: NULL | Z61: M | AA61: Y | AB61: Y | AC61: ADV:~FS~CMPIF_CHN~ADV~ | AD61: Employee Classification | AE61: The code which best describes the employee and the compensation and benefits data you have provided. | AF61: For employees classified using codes numbered 1 to 3 please supply all requested information, for codes 4 and 5 please provide job match and title information but EXCLUDE compensation and benefits data: 1-Full-Time Employee 2-Part-Time Employee; Full Time Equivalent pay data provided (FTE) 3-Employee for whom there is no suitable job reference. For these employees where possible identify the job reference[s] which you feel are the closest approximation(s) AND provide the corresponding pay data 4-Expatriate Employee; for these incumbents it is beneficial to provide a job match but pay data should not be provided 5-Red-Circled Employee; for these incumbents it is beneficial to provide a job match but pay data should not be provided | AG61: 1 | AH61: NULL | AI61: NULL | AJ61: NULL
A62: A24149240511 | B62: 2025 Capital Market Project Investment and Financing Compensation Survey - China | C62: SUBMISSIONCOMPANY | D62: 20 | E62: Participating Entity Profit-Sharing Plan | F62: Y | G62: Y [Yes] | H62: Y | I62: 34994 | J62: NULL | K62: NULL | L62: NULL | M62: BOOL | N62: FC_CPSPLAN | O62: DDE202 | P62: USE | Q62: L | R62: China | S62: CHN | T62: APC | U62: 1 | V62: 0 | W62: W | X62: Y-Organization has a profit-sharing plan N-No plan | Y62: NULL | Z62: M | AA62: Y | AB62: Y | AC62: INT:~CORE_APAC~CORE_EMEA~CORE_ARG~CORE_BRA~CORE_CHL~CORE_COL~CORE_DOM~CORE_ECU~CORE_MEX~CORE_PRY~CORE_PER~CORE_URY~SSO_APAC~SSO_EMEA~SSO_ARG~SSO_BRA~SSO_CHL~SSO_COL~SSO_DOM~SSO_ECU~SSO_MEX~SSO_PRY~SSO_PER~SSO_URY~RCE_APAC~RCE_EMEA~AGRO_ZAF~MDSUK~YOUNGGRAD~MFG_LATAM~RENEWABLE~RENEWCLUB_FRA~AERO_EMEA~AERO_BRA~HC_GCC~HC_APAC~HIGHER_EDU~CMPIF_CHN~EDU_APAC~UPSTREAM_MYS~DRILL_GLOBAL~DRILL_NAT_APAC~DRILL_NAT_EMEA~DRILL_NAT_ARG~DRILL_NAT_BRA~DRILL_NAT_CHL~DRILL_NAT_COL~DRILL_NAT_DOM~DRILL_NAT_ECU~DRILL_NAT_MEX~DRILL_NAT_PRY~DRILL_NAT_PER~DRILL_NAT_URY~LEGAL_FEE_EARNERS~CL_PS_SUPPORTSTAFF_INTL~CL_HRG~PSAR~INT~ | AD62: Participating Entity Profit-Sharing Plan | AE62: Organization has a profit-sharing plan. | AF62: Y-Organization has a profit-sharing plan N-No plan | AG62: Y [Yes] | AH62: NULL | AJ62: NULL
A63: A24149240511 | B63: 2025 Capital Market Project Investment and Financing Compensation Survey - China | C63: SUBMISSIONCOMPANY | D63: 21 | E63: Participating Entity Car Benefit Plan | F63: Y | G63: Y [Yes] | H63: Y | I63: 34996 | J63: NULL | K63: NULL | L63: NULL | M63: BOOL | N63: FC_CCBPLAN | O63: DDE203 | P63: USE | Q63: L | R63: China | S63: CHN | T63: APC | U63: 1 | V63: 0 | W63: W | X63: Y-Organization has a company car benefit plan N-No plan | Y63: NULL | Z63: M | AA63: Y | AB63: Y | AC63: INT:~CORE_APAC~CORE_EMEA~CORE_LATAM~SSO~RCE~AGRO_ZAF~MDSUK~MFG_LATAM~RENEWABLE~RENEWCLUB_FRA~AERO_EMEA~AERO_BRA~HC_GCC~HC_APAC~HIGHER_EDU~CMPIF_CHN~EDU_APAC~UPSTREAM_MYS~DRILL_GLOBAL~DRILL_NAT_INTL~LEGAL_FEE_EARNERS~CL_PS_SUPPORTSTAFF_INTL~CL_HRG~PSAR~INT~ | AD63: Participating Entity Car Benefit Plan | AE63: Organization has a company car benefit plan. | AF63: Y-Organization has a company car benefit plan N-No plan | AG63: Y [Yes] | AH63: NULL | AJ63: NULL
A64: A24149240511 | B64: 2025 Capital Market Project Investment and Financing Compensation Survey - China | C64: SUBMISSIONINCUMBENT | D64: 21 | E64: Effective Date | F64: N | G64: NULL | H64: N | I64: 13 | J64: NULL | K64: NULL | L64: NULL | M64: DATE | N64: EFFECTIVEDATE | O64: EFFECTIVEDATE | P64: USE | Q64: L | R64: China | S64: CHN | T64: APC | U64: 8 | V64: 0 | W64: W | Y64: NULL | Z64: M | AA64: N | AB64: N | AC64: ~CORE~AERO_NA~SSO~RCE~AGRO_ZAF~MDSUK~YOUNGGRAD~MFG_LATAM~RENEWABLE~RENEWCLUB_FRA~AERO_EMEA~AERO_BRA~HC_GCC~HC_APAC~HIGHER_EDU~CMPIF_CHN~EDU_APAC~UPSTREAM_MYS~DRILL_GLOBAL~DRILL_NAT~LEGAL_FEE_EARNERS~CL_PS_SUPPORTSTAFF_INTL~CL_HRG~PSAR~INT~ | AD64: Effective Date | AE64: Effective Date | AG64: NULL | AH64: NULL | AJ64: NULL
A65: A24149240511 | B65: 2025 Capital Market Project Investment and Financing Compensation Survey - China | C65: SUBMISSIONINCUMBENT | D65: 22 | E65: Function Code | F65: Y | G65: AFB | H65: Y | I65: 16 | J65: NULL | K65: NULL | L65: NULL | M65: CHAR | N65: JOBFUNCTIONCODE | O65: JOBFUNCTIONCODE | P65: USE | Q65: L | R65: China | S65: CHN | T65: APC | U65: 12 | V65: 0 | W65: W | X65: The codes are listed in the Functions and Disciplines section of the Position Descriptions file. All incumbents must have a function code. | Y65: NULL | Z65: M | AA65: Y | AB65: N | AC65: ADV:~CORE~AERO_NA~SSO~RCE~AGRO_ZAF~MDSUK~YOUNGGRAD~MFG_LATAM~RENEWABLE~RENEWCLUB_FRA~AERO_EMEA~AERO_BRA~HC_GCC~HC_APAC~HIGHER_EDU~CMPIF_CHN~EDU_APAC~UPSTREAM_MYS~LEGAL_FEE_EARNERS~CL_PS_SUPPORTSTAFF_INTL~CL_HRG~PSAR~ADV~ | AD65: Function Code | AE65: The appropriate three-letter function code (e.g., AHR) for the incumbent's job. | AF65: The codes are listed in the Functions and Disciplines section of the Position Descriptions file. All incumbents must have a function code. | AG65: AFB | AH65: NULL | AJ65: If(:JOBFUNCTIONCODE = "xx",null,upper(trim(:JOBFUNCTIONCODE)))
A66: A24149240511 | B66: 2025 Capital Market Project Investment and Financing Compensation Survey - China | C66: SUBMISSIONCOMPANY | D66: 22 | E66: Participating Entity Long-Term Incentive Plan | F66: Y | G66: Y [Yes] | H66: Y | I66: 34997 | J66: NULL | K66: NULL | L66: NULL | M66: BOOL | N66: FN_PELTIPLAN | O66: DDE204 | P66: USE | Q66: L | R66: China | S66: CHN | T66: APC | U66: 1 | V66: 0 | W66: W | X66: Y-Organization has a long-term incentive plan N-No plan | Y66: NULL | Z66: M | AA66: Y | AB66: Y | AC66: INT:~CORE~AERO_NA~SSO~RCE~AGRO_ZAF~MDSUK~MFG_LATAM~RENEWABLE~RENEWCLUB_FRA~AERO_EMEA~AERO_BRA~HC_GCC~HC_APAC~HIGHER_EDU~CMPIF_CHN~EDU_APAC~UPSTREAM_MYS~DRILL_GLOBAL~DRILL_NAT~LEGAL_FEE_EARNERS~CL_PS_SUPPORTSTAFF_INTL~CL_HRG~PSAR~INT~ | AD66: Participating Entity Long-Term Incentive Plan | AE66: Organization offers Long-Term Incentive Plan. | AF66: Y-Organization has a long-term incentive plan N-No plan | AG66: Y [Yes] | AH66: NULL | AJ66: NULL
A67: A24149240511 | B67: 2025 Capital Market Project Investment and Financing Compensation Survey - China | C67: SUBMISSIONINCUMBENT | D67: 23 | E67: Discipline Code | F67: Y | G67: AFB010 | H67: Y | I67: 17 | J67: NULL | K67: NULL | L67: NULL | M67: CHAR | N67: JOBSPECIALTYCODE | O67: JOBSPECIALTYCODE | P67: USE | Q67: L | R67: China | S67: CHN | T67: APC | U67: 12 | V67: 0 | W67: W | X67: The codes are listed in the Functions and Disciplines section in the Position Descriptions file. All incumbents must have a discipline code. | Y67: NULL | Z67: M | AA67: N | AB67: N | AC67: ADV:~CORE~AERO_NA~SSO~RCE~AGRO_ZAF~MDSUK~YOUNGGRAD~MFG_LATAM~RENEWABLE~RENEWCLUB_FRA~AERO_EMEA~AERO_BRA~HC_GCC~HC_APAC~HIGHER_EDU~CMPIF_CHN~EDU_APAC~UPSTREAM_MYS~LEGAL_FEE_EARNERS~CL_PS_SUPPORTSTAFF_INTL~CL_HRG~PSAR~ADV~ | AD67: Discipline Code | AE67: The appropriate discipline code for the incumbent's job, consisting of three letters and three digits (e.g., AHR000). | AF67: The codes are listed in the Functions and Disciplines section in the Position Descriptions file. All incumbents must have a discipline code. | AG67: AFB010 | AH67: NULL | AJ67: If(:JOBSPECIALTYCODE = "xx",null,upper(trim(:JOBSPECIALTYCODE)))
A68: A24149240511 | B68: 2025 Capital Market Project Investment and Financing Compensation Survey - China | C68: SUBMISSIONCOMPANY | D68: 23 | E68: Parent Name | F68: N | G68: Parent Company Name | H68: Y | I68: 3163 | J68: NULL | K68: NULL | L68: NULL | M68: CHAR | N68: PARENT_COMPANY_NAME | O68: DDE128 | P68: USE | Q68: L | R68: China | S68: CHN | T68: APC | U68: 100 | V68: 0 | W68: W | Y68: NULL | Z68: M | AA68: Y | AB68: Y | AC68: ~CORE~AERO_NA~SSO~RCE~AGRO_ZAF~MDSUK~YOUNGGRAD~MFG_LATAM~RENEWABLE~RENEWCLUB_FRA~AERO_EMEA~AERO_BRA~HC_GCC~HC_APAC~HIGHER_EDU~CMPIF_CHN~EDU_APAC~UPSTREAM_MYS~DRILL_GLOBAL~DRILL_NAT~LEGAL_FEE_EARNERS~CL_PS_SUPPORTSTAFF_INTL~CL_HRG~PSAR~INT~ | AD68: Parent Name | AE68: The name of the parent organization. | AG68: Parent Company Name | AH68: NULL | AJ68: NULL
A69: A24149240511 | B69: 2025 Capital Market Project Investment and Financing Compensation Survey - China | C69: SUBMISSIONCOMPANY | D69: 24 | E69: Parent Nationality | F69: Y | G69: USA [United States] | H69: Y | I69: 169 | J69: NULL | K69: NULL | L69: NULL | M69: PICK | N69: FC_NATION1 | O69: DDE002 | P69: USE | Q69: L | R69: China | S69: CHN | T69: APC | U69: 5 | V69: 0 | W69: W | X69: Refer to the Country Codes tab. | Y69: NULL | Z69: M | AA69: Y | AB69: Y | AC69: ADV:~CORE~AERO_NA~SSO~RCE~AGRO_ZAF~MDSUK~YOUNGGRAD~MFG_LATAM~RENEWABLE~RENEWCLUB_FRA~AERO_EMEA~AERO_BRA~HC_GCC~HIGHER_EDU~DRILL_GLOBAL~DRILL_NAT~;SCOPE:~CORE_APAC~LEGAL_FEE_EARNERS~CL_PS_SUPPORTSTAFF_INTL~CL_HRG~PSAR~RCE_APAC~SSO_APAC~HC_APAC~RENEWABLE_APAC~CMPIF_CHN~EDU_APAC~UPSTREAM_MYS~ | AD69: Parent Nationality | AE69: The nationality of the parent organization. | AF69: Refer to the Country Codes tab. | AG69: USA [United States] | AH69: NULL | AJ69: NULL
A70: A24149240511 | B70: 2025 Capital Market Project Investment and Financing Compensation Survey - China | C70: SUBMISSIONINCUMBENT | D70: 24 | E70: Career Level | F70: Y | G70: P4 | H70: Y | I70: 18 | J70: NULL | K70: NULL | L70: NULL | M70: CHAR | N70: JOBLEVELCODE | O70: JOBLEVELCODE | P70: USE | Q70: L | R70: China | S70: CHN | T70: APC | U70: 12 | V70: 0 | W70: W | X70: For applicable career levels, please refer to the Leveling section of the Position Descriptions file. All incumbents must have a career level. | Y70: NULL | Z70: M | AA70: N | AB70: N | AC70: ADV:~CORE~AERO_NA~SSO~RCE~AGRO_ZAF~MDSUK~YOUNGGRAD~MFG_LATAM~RENEWABLE~RENEWCLUB_FRA~AERO_EMEA~AERO_BRA~HC_GCC~HC_APAC~HIGHER_EDU~CMPIF_CHN~EDU_APAC~UPSTREAM_MYS~CL_PS_SUPPORTSTAFF_INTL~CL_HRG~PSAR~;HID:~LEGAL_FEE_EARNERS~ADV~ | AD70: Career Level | AE70: The appropriate Career Level for the incumbent's job. | AF70: For applicable career levels, please refer to the Leveling section of the Position Descriptions file. All incumbents must have a career level. | AG70: P4 | AH70: NULL | AJ70: If(:JOBLEVELCODE="xx",null,Trim(Upper(:JOBLEVELCODE)))
A71: A24149240511 | B71: 2025 Capital Market Project Investment and Financing Compensation Survey - China | C71: SUBMISSIONCOMPANY | D71: 25 | E71: Region of Parent | F71: N | G71: NULL | H71: N | I71: NULL | J71: NULL | K71: NULL | L71: NULL | M71: PICK | N71: PARENT_LOCATION | O71: NULL | P71: USE | Q71: C | R71: China | S71: CHN | T71: APC | U71: 5 | V71: 0 | W71: W | X71: NULL | Y71: NULL | Z71: NULL | AA71: Y | AB71: Y | AC71: ADV:~CORE_NONEXEC_APAC~CORE_NONEXEC_EMEA~CORE_NONEXEC_LATAM~SSO~RCE~AGRO_ZAF~RENEWABLE~RENEWCLUB_FRA~AERO_EMEA~AERO_BRA~HC_GCC~HC_APAC~HIGHER_EDU~CMPIF_CHN~EDU_APAC~UPSTREAM_MYS~CL_PS_SUPPORTSTAFF_INTL~;INT:~CORE_EXEC_APAC~CORE_EXEC_EMEA~CORE_EXEC_LATAM~MDSUK~CL_HRG~ADV~ | AD71: Region of Parent | AE71: The region reported for the parent organization. | AF71: NULL | AG71: NULL | AH71: NULL | AI71: if(IsNull(:ISO3) Or IsNull(:FC_NATION1), null, if(:ISO3=:FC_NATION1,"C", if(In(:FC_NATION1,"ASM","AUS","BGD","BRN","BTN","CHN","COK","FJI","FSM","GUM","HKG","IDN","IND","JPN","KHM","KOR","LAO","LKA","MAC","MMR","MNG","MYS","NZL","PHL","PLW","PNG","PRK","SGP","THA","TON","TUV","TWN","VNM","VUT","WSM"),"A", if(In(:FC_NATION1,"AFG","AGO","ALB","AND","ARE","ARM","AUT","AZE","BDI","BEL","BGR","BHR","BIH","BLR","BWA","CAF","CHE","CIV","CMR","COD","COG","CYP","CZE","DEU","DNK","DZA","EGY","ESH","ESP","EST","ETH","FIN","FRA","GBR","GEO"),"E", if(In(:FC_NATION1,"GGY","GHA","GIB","GIN","GRC","GRL","HRV","HUN","IMN","IRL","IRN","IRQ","ISL","ISR","ITA","JEY","JOR","KAZ","KEN","KGZ","KWT","LBN","LBR","LBY","LIE","LSO","LTU","LUX","LVA","MAR","MCO","MDA","MDG","MKD","MLI"),"E", if(In(:FC_NATION1,"MLT","MNE","MOZ","MUS","MWI","NAM","NGA","NLD","NOR","NRD","OMN","PAK","POL","PRT","PSE","QAT","ROU","RUS","SAU","SDN","SEN","SRB","SVK","SVN","SWE","SWZ","SXM","SYR","TCD","TJK","TKM","TUN","TUR","TZA","UGA"),"E", if(In(:FC_NATION1,"UKR","UZB","VAT","XKX","YEM","ZAF","ZMB","ZWE"), "E", if(In(:FC_NATION1,"ABW","AIA","ARG","ATG","BES","BHS","BOL","BRA","BRB","CHL","COL","CRI","CUB","CUW","CYM","DOM","ECU","FLK","GTM","HND","HTI","JAM","MEX","NIC","PAN","PER","PRI","PRY","SLV","TTO","URY","VEN","VGB","VIR"),"L", if(In(:FC_NATION1,"BMU","CAN","UMI","USA"),"N", null ))))))))) | AJ71: NULL
A72: A24149240511 | B72: 2025 Capital Market Project Investment and Financing Compensation Survey - China | C72: SUBMISSIONINCUMBENT | D72: 25 | E72: Incumbent Survey Grade | F72: Y | G72: 13 | H72: Y | I72: 104 | J72: NULL | K72: NULL | L72: NULL | M72: CHAR | N72: JOBGRADECODE | O72: JOBGRADECODE | P72: USE | Q72: L | R72: China | S72: CHN | T72: APC | U72: 12 | V72: 0 | W72: W | X72: For applicable survey grades, please refer to the Leveling section of the Position Descriptions file. All incumbents must have a survey grade. | Y72: NULL | Z72: M | AA72: N | AB72: N | AC72: ADV:~CORE~AERO_NA~SSO~RCE~AGRO_ZAF~MDSUK~YOUNGGRAD~MFG_LATAM~RENEWABLE~AERO_EMEA~AERO_BRA~HC_GCC~HC_APAC~HIGHER_EDU~CMPIF_CHN~EDU_APAC~UPSTREAM_MYS~CL_PS_SUPPORTSTAFF_INTL~CL_HRG~PSAR~;INT:~RENEWCLUB_FRA~ADV~ | AD72: Incumbent Survey Grade | AE72: The Survey Grade of the incumbent's job. | AF72: For applicable survey grades, please refer to the Leveling section of the Position Descriptions file. All incumbents must have a survey grade. | AG72: 13 | AH72: NULL | AJ72: If(:JOBGRADECODE = "xx",null,LPad(:JOBGRADECODE,2,"0"))
A73: A24149240511 | B73: 2025 Capital Market Project Investment and Financing Compensation Survey - China | C73: SUBMISSIONCOMPANY | D73: 26 | E73: Parent Annual Revenue Range (USD) | F73: Y | G73: D [25M to 75M USD] | H73: Y | I73: 34991 | J73: NULL | K73: NULL | L73: NULL | M73: PICK | N73: FC_GHIR_T | O73: DDE199 | P73: USE | Q73: L | R73: China | S73: CHN | T73: APC | U73: 5 | V73: 0 | W73: W | X73: A-Less than 5M USD B-5M to 10M USD C-10M to 25M USD D-25M to 75M USD E-75M to 150M USD F-150M to 300M USD G-300M to 500M USD H-500M to 1BN USD I-1BN to 2BN USD J-2BN to 5BN USD K-5BN to 10BN USD L-10BN to 50BN USD M-50BN to 100BN USD N-Greater than 100BN USD | Y73: NULL | Z73: M | AA73: Y | AB73: Y | AC73: ADV:~CORE~AERO_NA~SSO~RCE~AGRO_ZAF~MDSUK~YOUNGGRAD~MFG_LATAM~RENEWABLE~RENEWCLUB_FRA~AERO_EMEA~AERO_BRA~HC_GCC~HC_APAC~HIGHER_EDU~CMPIF_CHN~EDU_APAC~UPSTREAM_MYS~DRILL_GLOBAL~DRILL_NAT~LEGAL_FEE_EARNERS~CL_PS_SUPPORTSTAFF_INTL~CL_HRG~PSAR~ADV~ | AD73: Parent Annual Revenue Range (USD) | AE73: The annual revenue range that most closely matches the parent organization's USD annual revenue. | AF73: A-Less than 5M USD B-5M to 10M USD C-10M to 25M USD D-25M to 75M USD E-75M to 150M USD F-150M to 300M USD G-300M to 500M USD H-500M to 1BN USD I-1BN to 2BN USD J-2BN to 5BN USD K-5BN to 10BN USD L-10BN to 50BN USD M-50BN to 100BN USD N-Greater than 100BN USD | AG73: D [25M to 75M USD] | AH73: NULL | AJ73: NULL
A74: A24149240511 | B74: 2025 Capital Market Project Investment and Financing Compensation Survey - China | C74: SUBMISSIONINCUMBENT | D74: 26 | E74: Job Matching Comments | F74: N | G74: Accountant | H74: Y | I74: 75633 | J74: NULL | K74: NULL | L74: NULL | M74: CHAR | N74: JOB_MATCHING_COMMENT | O74: DDE473 | P74: USE | Q74: L | R74: China | S74: CHN | T74: APC | U74: 500 | V74: 0 | W74: W | X74: NULL | Y74: NULL | Z74: M | AA74: Y | AB74: Y | AC74: ADV:~CORE~AERO_NA~SSO~RCE~AGRO_ZAF~MDSUK~YOUNGGRAD~MFG_LATAM~RENEWABLE~RENEWCLUB_FRA~AERO_EMEA~AERO_BRA~HC_GCC~HC_APAC~HIGHER_EDU~CMPIF_CHN~EDU_APAC~UPSTREAM_MYS~DRILL_GLOBAL~DRILL_NAT~LEGAL_FEE_EARNERS~CL_PS_SUPPORTSTAFF_INTL~CL_HRG~PSAR~ADV~ | AD74: Job Matching Comments | AE74: Any comments that will help in the data cleaning/validation process. | AF74: NULL | AG74: Accountant | AH74: NULL | AJ74: Trim(:JOB_MATCHING_COMMENT)
A75: A24149240511 | B75: 2025 Capital Market Project Investment and Financing Compensation Survey - China | C75: SUBMISSIONINCUMBENT | D75: 27 | E75: Comments | F75: N | G75: NULL | H75: N | I75: 81 | J75: NULL | K75: NULL | L75: NULL | M75: CHAR | N75: COMMENTS | O75: COMMENTS | P75: USE | Q75: L | R75: China | S75: CHN | T75: APC | U75: 255 | V75: 0 | W75: W | Y75: NULL | Z75: M | AA75: Y | AB75: Y | AC75: ~CORE~AERO_NA~SSO~RCE~AGRO_ZAF~MDSUK~YOUNGGRAD~MFG_LATAM~RENEWABLE~RENEWCLUB_FRA~AERO_EMEA~AERO_BRA~HC_GCC~HC_APAC~HIGHER_EDU~CMPIF_CHN~EDU_APAC~UPSTREAM_MYS~DRILL_GLOBAL~DRILL_NAT~LEGAL_FEE_EARNERS~CL_PS_SUPPORTSTAFF_INTL~PSAR~INT~ | AD75: Comments | AE75: Any comments that will help in the data cleaning/validation process. | AG75: NULL | AH75: NULL | AJ75: NULL
A76: A24149240511 | B76: 2025 Capital Market Project Investment and Financing Compensation Survey - China | C76: SUBMISSIONCOMPANY | D76: 27 | E76: Parent FTE Employee Range | F76: Y | G76: H [27,500 to 75,000] | H76: Y | I76: 34992 | J76: NULL | K76: NULL | L76: NULL | M76: PICK | N76: FC_EMPLGHQ_T | O76: DDE200 | P76: USE | Q76: L | R76: China | S76: CHN | T76: APC | U76: 5 | V76: 0 | W76: W | X76: To convert part-timers to FTEs, sum all part-time hours and divide by baseline annual hours (e.g., 40 weekly hours x 52 weeks = 2,080 annual hours). Add this to the number of full-time employees to calculate the total number of FTE employees. A-Under 90 B-90 to 240 C-240 to 620 D-620 to 1,600 E-1,600 to 4,100 F-4,100 to 10,600 G-10,600 to 27,500 H-27,500 to 75,000 I-75,000 to 200,000 J-Greater than 200,000 | Y76: NULL | Z76: M | AA76: Y | AB76: Y | AC76: ADV:~CORE~AERO_NA~SSO~RCE~AGRO_ZAF~MDSUK~YOUNGGRAD~MFG_LATAM~RENEWABLE~RENEWCLUB_FRA~AERO_EMEA~AERO_BRA~HC_GCC~HC_APAC~HIGHER_EDU~CMPIF_CHN~EDU_APAC~UPSTREAM_MYS~DRILL_GLOBAL~DRILL_NAT~LEGAL_FEE_EARNERS~CL_PS_SUPPORTSTAFF_INTL~CL_HRG~PSAR~ADV~ | AD76: Parent FTE Employee Range | AE76: The full-time equivalent (FTE) employee range that best matches the parent organization's total number of FTE employees. | AF76: To convert part-timers to FTEs, sum all part-time hours and divide by baseline annual hours (e.g., 40 weekly hours x 52 weeks = 2,080 annual hours). Add this to the number of full-time employees to calculate the total number of FTE employees. A-Under 90 B-90 to 240 C-240 to 620 D-620 to 1,600 E-1,600 to 4,100 F-4,100 to 10,600 G-10,600 to 27,500 H-27,500 to 75,000 I-75,000 to 200,000 J-Greater than 200,000 | AG76: H [27,500 to 75,000] | AH76: NULL | AJ76: NULL
A77: A24149240511 | B77: 2025 Capital Market Project Investment and Financing Compensation Survey - China | C77: SUBMISSIONINCUMBENT | D77: 28 | E77: Management Indicator | F77: Y | G77: Y | H77: Y | I77: 259 | J77: NULL | K77: NULL | L77: NULL | M77: BOOL | N77: FC_MGMTPOS_YON | O77: DDE086 | P77: USE | Q77: L | R77: China | S77: CHN | T77: APC | U77: 1 | V77: 0 | W77: W | X77: Y-The incumbent has managerial responsibility N-No managerial responsibility | Y77: NULL | Z77: M | AA77: Y | AB77: Y | AC77: ADV:~FS~CMPIF_CHN~ADV~ | AD77: Management Indicator | AE77: Applicable to "R" Career Band ONLY. | AF77: Y-The incumbent has managerial responsibility N-No managerial responsibility | AG77: Y | AH77: NULL | AI77: NULL | AJ77: upper(trim(:FC_MGMTPOS_YON))
A78: A24149240511 | B78: 2025 Capital Market Project Investment and Financing Compensation Survey - China | C78: SUBMISSIONCOMPANY | D78: 28 | E78: Parent Geographic Scope | F78: Y | G78: G [Global] | H78: Y | I78: 482 | J78: NULL | K78: NULL | L78: NULL | M78: PICK | N78: FC_PGEOSC_ITM | O78: DDE027 | P78: USE | Q78: L | R78: China | S78: CHN | T78: APC | U78: 5 | V78: 0 | W78: W | X78: S-Single - single country only M-Multi-Country - small cluster of countries R-Regional - an entire region, or multiple countries across one or two continents G-Global - three or more continents Select Single country when international responsibility is negligible. Select Multi-Country when international responsibility is limited to a small cluster of countries, e.g., Benelux, China and Hong Kong, Nordics, UK and Ireland, often grouped under a single legal entity. Select Regional when international responsibility is significant and covers an entire region, e.g., North America (U.S. and Canada), Western Europe, Middle East and Africa, Greater China (China, Hong Kong and Taiwan), South East Asia (SEA), Latin America, or multiple countries across one or two continents. Select Global when international responsibility is predominant and covers three or more continents. Parent Geographic Scope should also be Global. | Y78: NULL | Z78: M | AA78: Y | AB78: Y | AC78: ADV:~CORE~AERO_NA~SSO~RCE~AGRO_ZAF~MDSUK~YOUNGGRAD~MFG_LATAM~RENEWABLE~RENEWCLUB_FRA~AERO_EMEA~AERO_BRA~HC_GCC~HC_APAC~HIGHER_EDU~CMPIF_CHN~EDU_APAC~UPSTREAM_MYS~DRILL_GLOBAL~DRILL_NAT~CL_PS_SUPPORTSTAFF_INTL~CL_HRG~~;INT:LEGAL_FEE_EARNERS~PSAR~ADV~ | AD78: Parent Geographic Scope | AE78: The geographic scope of the parent organization. | AF78: S-Single - single country only M-Multi-Country - small cluster of countries R-Regional - an entire region, or multiple countries across one or two continents G-Global - three or more continents Select Single country when international responsibility is negligible. Select Multi-Country when international responsibility is limited to a small cluster of countries, e.g., Benelux, China and Hong Kong, Nordics, UK and Ireland, often grouped under a single legal entity. Select Regional when international responsibility is significant and covers an entire region, e.g., North America (U.S. and Canada), Western Europe, Middle East and Africa, Greater China (China, Hong Kong and Taiwan), South East Asia (SEA), Latin America, or multiple countries across one or two continents. Select Global when international responsibility is predominant and covers three or more continents. Parent Geographic Scope should also be Global. | AG78: G [Global] | AH78: NULL | AJ78: NULL
A79: A24149240511 | B79: 2025 Capital Market Project Investment and Financing Compensation Survey - China | C79: SUBMISSIONCOMPANY | D79: 29 | E79: Parent Full Value Chain of Activities | F79: Y | G79: Y [Yes] | H79: Y | I79: 483 | J79: NULL | K79: NULL | L79: NULL | M79: BOOL | N79: FC_PVCACT_YON | O79: DDE028 | P79: USE | Q79: L | R79: China | S79: CHN | T79: APC | U79: 1 | V79: 0 | W79: W | X79: Y-The organization controls the full value chain of activities for all regions/countries/subsidiaries. N-the parent does not control the full value chain of activities for all regions/countries/subsidiaries (e.g., entities may be independent). | Y79: NULL | Z79: M | AA79: Y | AB79: Y | AC79: INT:~CORE_APAC~CORE_EMEA~CORE_LATAM~SSO~RCE~AGRO_ZAF~MFG_LATAM~RENEWABLE~RENEWCLUB_FRA~AERO_EMEA~AERO_BRA~HC_GCC~HC_APAC~HIGHER_EDU~CMPIF_CHN~EDU_APAC~UPSTREAM_MYS~UPSTREAM_MYS~DRILL_GLOBAL~DRILL_NAT_INTL~CL_PS_SUPPORTSTAFF_INTL~CL_HRG~;ADV:~CORE_NA~AERO_NA~MDSUK~YOUNGGRAD~DRILL_NAT_NA~;ADV:~LEGAL_FEE_EARNERS~PSAR~INT~ | AD79: Parent Full Value Chain of Activities | AE79: The extent to which the parent maintains end-to-end control of the business, including design, creation, sale and support of products and/or services. | AF79: Y-The organization controls the full value chain of activities for all regions/countries/subsidiaries. N-the parent does not control the full value chain of activities for all regions/countries/subsidiaries (e.g., entities may be independent). | AG79: Y [Yes] | AH79: NULL | AJ79: NULL
A80: A24149240511 | B80: 2025 Capital Market Project Investment and Financing Compensation Survey - China | C80: SUBMISSIONINCUMBENT | D80: 29 | E80: Macro Product Modifier | F80: Y | G80: AAH | H80: Y | I80: 244 | J80: NULL | K80: NULL | L80: NULL | M80: PICK | N80: FC_MODMACRP_TXT | O80: DDE143 | P80: USE | Q80: L | R80: China | S80: CHN | T80: APC | U80: 5 | V80: 0 | W80: W | X80: The codes are listed in the Functions and Disciplines section of the Position Descriptions file. | Y80: NULL | Z80: M | AA80: Y | AB80: Y | AC80: ADV,SCOPE:~FS~FS_NA~CMPIF_CHN~ADV~ | AD80: Macro Product Modifier | AE80: Identifies the broad financial product specialization, e.g., M&A, Equity Cash Products, Credit Related Products. | AF80: The codes are listed in the Functions and Disciplines section of the Position Descriptions file. | AG80: AAH | AH80: NULL | AJ80: upper(trim(:FC_MODMACRP_TXT))
A81: A24149240511 | B81: 2025 Capital Market Project Investment and Financing Compensation Survey - China | C81: SUBMISSIONCOMPANY | D81: 30 | E81: Parent Products/Services in Single/Related Industries | F81: Y | G81: Y [Single/Related Industries] | H81: Y | I81: 21481 | J81: NULL | K81: NULL | L81: NULL | M81: PICK | N81: FC_PDIVERS_YON | O81: DDE155 | P81: USE | Q81: L | R81: China | S81: CHN | T81: APC | U81: 5 | V81: 0 | W81: W | X81: Y-Single/Related Industries N-Multiple/Diverse Industries | Y81: NULL | Z81: M | AA81: Y | AB81: Y | AC81: ~CORE~AERO_NA~SSO~RCE~AGRO_ZAF~MDSUK~YOUNGGRAD~MFG_LATAM~RENEWABLE~RENEWCLUB_FRA~AERO_EMEA~AERO_BRA~HC_GCC~HC_APAC~HIGHER_EDU~CMPIF_CHN~EDU_APAC~UPSTREAM_MYS~DRILL_GLOBAL~DRILL_NAT~LEGAL_FEE_EARNERS~CL_PS_SUPPORTSTAFF_INTL~CL_HRG~PSAR~INT~ | AD81: Parent Products/Services in Single/Related Industries | AE81: Indicate whether the parent's products/services are in a single/related industry or span multiple distinct/unrelated industries. | AF81: Y-Single/Related Industries N-Multiple/Diverse Industries | AG81: Y [Single/Related Industries] | AH81: NULL | AJ81: NULL
A82: A24149240511 | B82: 2025 Capital Market Project Investment and Financing Compensation Survey - China | C82: SUBMISSIONINCUMBENT | D82: 30 | E82: Detailed Specialization Modifier | F82: Y | G82: ABF | H82: Y | I82: 77974 | J82: NULL | K82: NULL | L82: NULL | M82: PICK | N82: FC_MODDETSPEC_TXT | O82: DDE532 | P82: USE | Q82: L | R82: China | S82: CHN | T82: APC | U82: 5 | V82: 0 | W82: W | X82: The codes are listed in the Functions and Disciplines section of the Position Descriptions file. | Y82: NULL | Z82: M | AA82: Y | AB82: Y | AC82: ADV,SCOPE:~FS~FS_NA~CMPIF_CHN~ADV~ | AD82: Detailed Specialization Modifier | AE82: Identifies the detailed specialization in which the incumbent is working. | AF82: The codes are listed in the Functions and Disciplines section of the Position Descriptions file. | AG82: ABF | AH82: NULL | AJ82: upper(trim(:FC_MODDETSPEC_TXT))
A83: A24149240511 | B83: 2025 Capital Market Project Investment and Financing Compensation Survey - China | C83: SUBMISSIONCOMPANY | D83: 31 | E83: Parent Survey Grade | F83: N | G83: WTW use only | H83: Y | I83: 34990 | J83: NULL | K83: NULL | L83: NULL | M83: NUM | N83: PARENT_GG | O83: DDE198 | P83: USE | Q83: L | R83: China | S83: CHN | T83: APC | U83: 2 | V83: 0 | W83: W | X83: Refer to the Organization/Business Unit Survey Grading Guidelines to determine if your organization qualifies as a business unit. Failure to provide any of the parent characteristics will prevent the Survey Grade from being calculated. Parent Survey Grades are calculated as an indication to guide the job matching of your incumbents within each entity and are used as a reference during data validation to detect incumbent Survey Grades that do not seem plausible. | Y83: NULL | Z83: M | AA83: Y | AB83: Y | AC83: INT:~CORE~AERO_NA~SSO~RCE~AGRO_ZAF~MDSUK~YOUNGGRAD~MFG_LATAM~RENEWABLE~RENEWCLUB_FRA~AERO_EMEA~AERO_BRA~HC_GCC~HC_APAC~HIGHER_EDU~CMPIF_CHN~EDU_APAC~UPSTREAM_MYS~DRILL_GLOBAL~DRILL_NAT~LEGAL_FEE_EARNERS~CL_PS_SUPPORTSTAFF_INTL~CL_HRG~PSAR~INT~ | AD83: Parent Survey Grade | AE83: This field is automatically calculated based on the reported parent organization characteristics (i.e., Annual Revenue Range, FTE Employee Range, Geographic Scope, Full Value Chain of Activities, Products/ Services in Single/Related Industries). | AF83: Refer to the Organization/Business Unit Survey Grading Guidelines to determine if your organization qualifies as a business unit. Failure to provide any of the parent characteristics will prevent the Survey Grade from being calculated. Parent Survey Grades are calculated as an indication to guide the job matching of your incumbents within each entity and are used as a reference during data validation to detect incumbent Survey Grades that do not seem plausible. | AG83: WTW use only | AH83: =IF(AND(FIND(LEFT(RC[-6],1), " ABCDEFGHIJKLMN")>1,FIND(LEFT(RC[-5],1), " ABCDEFGHIJ")>1,FIND(LEFT(RC[-4],1)," SMRG")>1, FIND(LEFT(RC[-3],1)," NY")>1,FIND(LEFT(RC[-2],1), " NY")>1),AVERAGE(IF(LEFT(RC[-6],1) <= "D", 16, IF(LEFT(RC[-6], 1) = "E", 17, IF(LEFT(RC[-6],1) <= "G", 18, CODE(LEFT(RC[-6],1))-CODE("H")+19))), CODE(LEFT(RC[-5],1))-CODE("A")+16,IF(OR(LEFT(RC[-4],1)="S",LEFT(RC[-4],1)="M"),16,IF(LEFT(RC[-4],1)="G",20,19))+IF(LEFT(RC[-3],1)="Y",2,0)+IF(LEFT(RC[-2],1)="N",2,0)),"CALCULATED") | AJ83: NULL
A84: A24149240511 | B84: 2025 Capital Market Project Investment and Financing Compensation Survey - China | C84: SUBMISSIONINCUMBENT | D84: 31 | E84: Market Focus Modifier | F84: Y | G84: AUT | H84: Y | I84: 77938 | J84: NULL | K84: NULL | L84: NULL | M84: PICK | N84: FC_MODMFM_TXT | O84: DDE497 | P84: USE | Q84: L | R84: China | S84: CHN | T84: APC | U84: 5 | V84: 0 | W84: W | X84: The codes are listed in the Functions and Disciplines section of the Position Descriptions file. | Y84: NULL | Z84: M | AA84: Y | AB84: Y | AC84: ADV,SCOPE:~FS~FS_NA~CMPIF_CHN~ADV~ | AD84: Market Focus Modifier | AE84: Identifies the area of focus which an incumbent has, e.g., Developing/Generalist Market, Emerging Market. | AF84: The codes are listed in the Functions and Disciplines section of the Position Descriptions file. | AG84: AUT | AH84: NULL | AJ84: upper(trim(:FC_MODMFM_TXT))
A85: A24149240511 | B85: 2025 Capital Market Project Investment and Financing Compensation Survey - China | C85: SUBMISSIONCOMPANY | D85: 32 | E85: Comments | F85: N | G85: NULL | H85: N | I85: 78 | J85: NULL | K85: NULL | L85: NULL | M85: CHAR | N85: COMMENTS | O85: COMMENTS | P85: USE | Q85: L | R85: China | S85: CHN | T85: APC | U85: 255 | V85: 0 | W85: W | Y85: NULL | Z85: M | AA85: Y | AB85: Y | AC85: ~CORE~AERO_NA~SSO~RCE~AGRO_ZAF~MDSUK~YOUNGGRAD~MFG_LATAM~RENEWABLE~RENEWCLUB_FRA~AERO_EMEA~AERO_BRA~HC_GCC~HC_APAC~HIGHER_EDU~CMPIF_CHN~EDU_APAC~UPSTREAM_MYS~DRILL_GLOBAL~DRILL_NAT~LEGAL_FEE_EARNERS~CL_PS_SUPPORTSTAFF_INTL~CL_HRG~PSAR~INT~ | AD85: Comments | AE85: Organization Comments | AG85: NULL | AH85: NULL | AJ85: NULL
A86: A24149240511 | B86: 2025 Capital Market Project Investment and Financing Compensation Survey - China | C86: SUBMISSIONINCUMBENT | D86: 32 | E86: Unit Number | F86: Y | G86: 1 | H86: N | I86: 11 | J86: NULL | K86: NULL | L86: NULL | M86: CHAR | N86: UNITNUM | O86: UNITNUM | P86: USE | Q86: L | R86: China | S86: CHN | T86: APC | U86: 12 | V86: 0 | W86: W | X86: Enter a unique three-digit code (e.g., 001, 002) to identify each unit. Unit numbers will be assigned to the corresponding incumbent in these units in the Incumbent Data worksheet. | Y86: NULL | Z86: M | AA86: N | AB86: N | AC86: HID:~CORE~AERO_NA~SSO~RCE~AGRO_ZAF~MDSUK~YOUNGGRAD~MFG_LATAM~RENEWABLE~RENEWCLUB_FRA~AERO_EMEA~AERO_BRA~HC_GCC~HC_APAC~HIGHER_EDU~CMPIF_CHN~EDU_APAC~UPSTREAM_MYS~LEGAL_FEE_EARNERS~CL_PS_SUPPORTSTAFF_INTL~CL_HRG~ | AD86: Unit Number | AE86: Unit number (from the Unit Data worksheet) for the incumbent's unit. | AF86: Enter a unique three-digit code (e.g., 001, 002) to identify each unit. Unit numbers will be assigned to the corresponding incumbent in these units in the Incumbent Data worksheet. | AG86: 1 | AH86: NULL | AJ86: NULL
A87: A24149240511 | B87: 2025 Capital Market Project Investment and Financing Compensation Survey - China | C87: SUBMISSIONINCUMBENT | D87: 33 | E87: Business Unit Name | F87: N | G87: Corporate Business | H87: Y | I87: 20526 | J87: NULL | K87: 20525 | L87: NULL | M87: CHAR | N87: BUS_UNIT_NAME | O87: DDE360 | P87: USE | Q87: L | R87: China | S87: CHN | T87: APC | U87: 100 | V87: 0 | W87: W | X87: If corporate employees are included in the submission, one of the business units should be named "parent" or "corporate" for reporting incumbents with organization-wide responsibility. Report incumbents as part of the smallest possible business unit to which they belong (e.g., for a division head within a larger segment, report the name of the division rather than the overall segment). | Y87: NULL | Z87: M | AA87: Y | AB87: Y | AC87: DSW,ADV:~CORE~AERO_NA~SSO~RCE~AGRO_ZAF~MDSUK~MFG_LATAM~RENEWABLE~RENEWCLUB_FRA~AERO_EMEA~AERO_BRA~HC_GCC~HC_APAC~HIGHER_EDU~CMPIF_CHN~EDU_APAC~UPSTREAM_MYS~DRILL_GLOBAL~DRILL_NAT~LEGAL_FEE_EARNERS~CL_PS_SUPPORTSTAFF_INTL~CL_HRG~PSAR~ADV~ | AD87: Business Unit Name | AE87: Name of the business unit where the incumbent sits. | AF87: If corporate employees are included in the submission, one of the business units should be named "parent" or "corporate" for reporting incumbents with organization-wide responsibility. Report incumbents as part of the smallest possible business unit to which they belong (e.g., for a division head within a larger segment, report the name of the division rather than the overall segment). | AG87: Corporate Business | AH87: NULL | AJ87: TRIM(:BUS_UNIT_NAME)
A88: A24149240511 | B88: 2025 Capital Market Project Investment and Financing Compensation Survey - China | C88: SUBMISSIONINCUMBENT | D88: 34 | E88: Number of Employees Supervised (Direct + Indirect) | F88: Y | G88: 1000 | H88: Y | I88: 235 | J88: NULL | K88: NULL | L88: NULL | M88: NUM | N88: FN_SUPERV_NBR | O88: DDE134 | P88: USE | Q88: L | R88: China | S88: CHN | T88: APC | U88: 9 | V88: 0 | W88: W | X88: This should only be provided for jobs matched to the M or EX career bands. Figures for jobs below supervision level will be removed. | Y88: NULL | Z88: M | AA88: Y | AB88: Y | AC88: ADV:~CORE~AERO_NA~SSO~RCE~AGRO_ZAF~MDSUK~MFG_LATAM~RENEWABLE~RENEWCLUB_FRA~AERO_EMEA~AERO_BRA~HC_GCC~HC_APAC~HIGHER_EDU~CMPIF_CHN~EDU_APAC~UPSTREAM_MYS~DRILL_GLOBAL~DRILL_NAT~CL_PS_SUPPORTSTAFF_INTL~CL_HRG~PSAR~;PUB:~CORE_JPN~ADV~ | AD88: Number of Employees Supervised (Direct + Indirect) | AE88: The number of employees reporting (directly and indirectly) to the considered incumbent (e.g., for a general manager this number would be all employees in the business; for a function head, the number in the function). | AF88: This should only be provided for jobs matched to the M or EX career bands. Figures for jobs below supervision level will be removed. | AG88: 1000 | AH88: NULL | AJ88: If(IsNull(:FN_SUPERV_NBR),Null,Round(:FN_SUPERV_NBR,0))
A89: A24149240511 | B89: 2025 Capital Market Project Investment and Financing Compensation Survey - China | C89: SUBMISSIONINCUMBENT | D89: 35 | E89: Corporate/Noncorporate | F89: Y | G89: C | H89: Y | I89: 20523 | J89: NULL | K89: NULL | L89: NULL | M89: PICK | N89: CORP_NONCORP | O89: DDE357 | P89: USE | Q89: L | R89: China | S89: CHN | T89: APC | U89: 5 | V89: 0 | W89: W | X89: C-Corporate - Responsibilities span the entire organization. This should not be used for incumbents in a subsidiary, segment, division or region. N-Noncorporate - Responsibilities limited to a segment of the organization (e.g., subsidiary, segment, division or product category). Always report the head of a segment, region, division or country as "Noncorporate". | Y89: NULL | Z89: M | AA89: Y | AB89: Y | AC89: ADV:~CORE~AERO_NA~SSO~RCE~AGRO_ZAF~MDSUK~MFG_LATAM~RENEWABLE~RENEWCLUB_FRA~AERO_EMEA~AERO_BRA~HC_GCC~HC_APAC~HIGHER_EDU~CMPIF_CHN~EDU_APAC~UPSTREAM_MYS~DRILL_GLOBAL~DRILL_NAT~CL_PS_SUPPORTSTAFF_INTL~CL_HRG~ADV~ | AD89: Corporate/Noncorporate | AE89: Segment of the organization in which the incumbent has primary responsibility. | AF89: C-Corporate - Responsibilities span the entire organization. This should not be used for incumbents in a subsidiary, segment, division or region. N-Noncorporate - Responsibilities limited to a segment of the organization (e.g., subsidiary, segment, division or product category). Always report the head of a segment, region, division or country as "Noncorporate". | AG89: C | AH89: NULL | AJ89: Trim(Decode(:CORP_NONCORP,"NONCORPORATE","N","Noncorporate","N","CORPORATE","C","Corporate","C",:CORP_NONCORP))
A90: A24149240511 | B90: 2025 Capital Market Project Investment and Financing Compensation Survey - China | C90: SUBMISSIONINCUMBENT | D90: 36 | E90: Geographic Scope | F90: Y | G90: G | H90: Y | I90: 254 | J90: NULL | K90: NULL | L90: NULL | M90: PICK | N90: GEOGRAPHIC_SCOPE | O90: DDE081 | P90: USE | Q90: L | R90: China | S90: CHN | T90: APC | U90: 5 | V90: 0 | W90: W | X90: This should only be provided for jobs matched to the M or EX career bands. S-Single - single country only M-Multi-Country - small cluster of countries R-Regional - an entire region, or multiple countries across one or two continents G-Global - three or more continents Select Single country when international responsibility is negligible. Select Multi-Country when international responsibility is limited to a small cluster of countries, e.g., Benelux, China and Hong Kong, Nordics, UK and Ireland, often grouped under a single legal entity. Select Regional when international responsibility is significant and covers an entire region, e.g., North America (U.S. and Canada), Western Europe, Middle East and Africa, Greater China (China, Hong Kong and Taiwan), South East Asia (SEA), Latin America, or multiple countries across one or two continents. Select Global when international responsibility is predominant and covers three or more continents. Parent Geographic Scope should also be Global. | Y90: NULL | Z90: M | AA90: Y | AB90: Y | AC90: PUB,SCOPE:~CMPIF_CHN~CORE~AERO_NA~SSO~RCE~AERO_EMEA~AERO_BRA~HC_GCC~HC_APAC~HIGHER_EDU~DRILL_GLOBAL~DRILL_NAT~CL_PS_SUPPORTSTAFF_INTL~CL_HRG~PSAR~;PUB:~AGRO_ZAF~RENEWABLE~RENEWCLUB_FRA~EDU_APAC~UPSTREAM_MYS~;INT:~HC~MDSUK~MFG_LATAM~;HID:~LEGAL_FEE_EARNERS~;ADV:~LEGAL_FEE_EARNERS_GBR~PUB~ | AD90: Geographic Scope | AE90: The geographic scope of the incumbent. | AF90: This should only be provided for jobs matched to the M or EX career bands. S-Single - single country only M-Multi-Country - small cluster of countries R-Regional - an entire region, or multiple countries across one or two continents G-Global - three or more continents Select Single country when international responsibility is negligible. Select Multi-Country when international responsibility is limited to a small cluster of countries, e.g., Benelux, China and Hong Kong, Nordics, UK and Ireland, often grouped under a single legal entity. Select Regional when international responsibility is significant and covers an entire region, e.g., North America (U.S. and Canada), Western Europe, Middle East and Africa, Greater China (China, Hong Kong and Taiwan), South East Asia (SEA), Latin America, or multiple countries across one or two continents. Select Global when international responsibility is predominant and covers three or more continents. Parent Geographic Scope should also be Global. | AG90: G | AH90: NULL | AJ90: upper(trim(:GEOGRAPHIC_SCOPE))
A91: A24149240511 | B91: 2025 Capital Market Project Investment and Financing Compensation Survey - China | C91: SUBMISSIONINCUMBENT | D91: 37 | E91: Focus of Investments | F91: Y | G91: FVA | H91: Y | I91: 22382 | J91: NULL | K91: NULL | L91: NULL | M91: PICK | N91: FOCUS_INVESTMENTS | O91: DDE405 | P91: USE | Q91: L | R91: China | S91: CHN | T91: APC | U91: 5 | V91: 0 | W91: W | X91: Complete this column for all individuals reported within these functions: FVA-Private Equity Deal Origination FVB-Private Equity Fund Management FVC-Private Equity Portfolio Management LBO-Large Buy-Outs Specialist (investments with more than 100 million USD of equity invested) MBO-Mid-Market Buy-Outs Specialist (investments with 10 million-100 million USD of equity invested) SBO-Small Buy-Outs Specialist (investments with less than 10 million USD of equity invested) DCA-Development/Expansion/Growth Capital VCS-Venture Capital/Start-Up/Seed/Technology Specialist FOF-Fund of Funds Specialist SEC-Secondaries Specialist CIN-Co-Investments INF-Infrastructure RES-Real Estate Specialist MEZ-Mezzanine/Debt Specialist OTH-Other (please provide details in the "Comments" column) | Y91: NULL | Z91: M | AA91: Y | AB91: Y | AC91: ADV:~FS~CMPIF_CHN~ADV~ | AD91: Focus of Investments | AE91: Identifies the markets in which the investment professional normally operates. | AF91: Complete this column for all individuals reported within these functions: FVA-Private Equity Deal Origination FVB-Private Equity Fund Management FVC-Private Equity Portfolio Management LBO-Large Buy-Outs Specialist (investments with more than 100 million USD of equity invested) MBO-Mid-Market Buy-Outs Specialist (investments with 10 million-100 million USD of equity invested) SBO-Small Buy-Outs Specialist (investments with less than 10 million USD of equity invested) DCA-Development/Expansion/Growth Capital VCS-Venture Capital/Start-Up/Seed/Technology Specialist FOF-Fund of Funds Specialist SEC-Secondaries Specialist CIN-Co-Investments INF-Infrastructure RES-Real Estate Specialist MEZ-Mezzanine/Debt Specialist OTH-Other (please provide details in the "Comments" column) | AG91: FVA | AH91: NULL | AI91: NULL | AJ91: upper(trim(:FOCUS_INVESTMENTS))
A92: A24149240511 | B92: 2025 Capital Market Project Investment and Financing Compensation Survey - China | C92: SUBMISSIONINCUMBENT | D92: 38 | E92: Currency of Pay Elements | F92: Y | G92: JPY | H92: Y | I92: 77942 | J92: NULL | K92: NULL | L92: NULL | M92: PICK | N92: PAY_CURRENCY | O92: DDE501 | P92: USE | Q92: L | R92: China | S92: CHN | T92: APC | U92: 5 | V92: 0 | W92: W | X92: Refer to the Country Codes tab. | Y92: NULL | Z92: M | AA92: Y | AB92: Y | AC92: ~CORE~AERO_NA~SSO~RCE~AGRO_ZAF~MDSUK~MFG_LATAM~RENEWABLE~RENEWCLUB_FRA~AERO_EMEA~AERO_BRA~HC_GCC~HC_APAC~HIGHER_EDU~CMPIF_CHN~EDU_APAC~UPSTREAM_MYS~DRILL_GLOBAL~DRILL_NAT~LEGAL_FEE_EARNERS~CL_PS_SUPPORTSTAFF_INTL~CL_HRG~PSAR~INT~ | AD92: Currency of Pay Elements | AE92: The currency code for all pay elements (e.g., Base Salary, Fixed Cash Allowances, Annual Bonus/Incentives, Other Cash). | AF92: Refer to the Country Codes tab. | AG92: JPY | AH92: NULL | AJ92: upper(trim(:PAY_CURRENCY))
A93: A24149240511 | B93: 2025 Capital Market Project Investment and Financing Compensation Survey - China | C93: SUBMISSIONINCUMBENT | D93: 39 | E93: Annual Base Salary | F93: N | G93: 1000000 | H93: Y | I93: 220 | J93: NULL | K93: NULL | L93: NULL | M93: MON | N93: BASE | O93: DDE115 | P93: USE | Q93: L | R93: China | S93: CHN | T93: APC | U93: 15 | V93: 0 | W93: W | X93: Report the full time equivalent (FTE) gross salary amount for each incumbent prior to any deductions (e.g., tax, social security or salary sacrifice), as at their most recent adjustment date. Adjustments include any cost-of-living increase, indexation, merit increase or promotion. Part-time salaries should be converted to full time. Does not include fixed cash allowances. Does not include variable awards such as performance bonus, discretionary bonus, sales incentives, overtime pay, stand-by/call-out pay and shift premiums/payments. For Russia, please include statutory geographical pay coefficients. | Y93: NULL | Z93: M | AA93: N | AB93: N | AC93: INT:~CORE_APAC~CORE_EMEA~CORE_NA~AERO_NA~SSO_APAC~SSO_EMEA~RCE_APAC~RCE_EMEA~AGRO_ZAF~MDSUK~YOUNGGRAD~RENEWABLE_APAC~RENEWABLE_EMEA~RENEWCLUB_FRA~AERO_EMEA~AERO_BRA~HC_GCC~HC_APAC~HIGHER_EDU~CMPIF_CHN~EDU_APAC~UPSTREAM_MYS~LEGAL_FEE_EARNERS~CL_PS_SUPPORTSTAFF_INTL~CL_HRG~PSAR~;HID:~MFG_LATAM~DRILL_GLOBAL~DRILL_NAT_APAC~DRILL_NAT_EMEA~DRILL_NAT_NA~INT~ | AD93: Annual Base Salary | AE93: The current full-time equivalent (FTE) annual base salary. Includes any guaranteed additional fixed payments such as holiday pay and any extra-contractual months required by law, collective agreement or organization practice. | AF93: Report the full time equivalent (FTE) gross salary amount for each incumbent prior to any deductions (e.g., tax, social security or salary sacrifice), as at their most recent adjustment date. Adjustments include any cost-of-living increase, indexation, merit increase or promotion. Part-time salaries should be converted to full time. Does not include fixed cash allowances. Does not include variable awards such as performance bonus, discretionary bonus, sales incentives, overtime pay, stand-by/call-out pay and shift premiums/payments. For Russia, please include statutory geographical pay coefficients. | AG93: 1000000 | AH93: NULL | AJ93: If(IsNull(:BASE),Null,Round(:BASE,0))
